Workbook

Sheet Roteiro
B2: Conferências | E2: Medição | F2: 11/2025 | G2: 45962
A4: 1 | B4: Atualizar geração na aba "Hist.Geração" | H4: G:\Drives compartilhados\8 Geração Distribuída\15. Operação e Manutenção\2.1 Contas de Luz Usinas Solar Maranhão
A5: 2 | B5: Atualizar consumo na aba "Hist.Consumo"
A6: 3 | B6: Atualizar rateio (se houver mudança) - "Cad.Consumo - Paula
A7: 4 | B7: Atualizar banceira tarifária - "Hist BT" - google - site gov (ANEEL)
A8: 5 | B8: Paula confere as medições e saldos Acumulados (aba medições)
A9: 6 | B9: Emitir faturas na ana "Faturas" com base no número do recibo da aba medições
A10: 7
A11: 8
A12: 9
A13: 10
A14: 11
A15: 12
A16: 13
A17: 14
A18: 15

Sheet Cad.Usinas
A1: Cadastro Usinas
A3: Nome | B3: Conta Contrato | C3: Instalação | D3: Potência (kW) | E3: Geração Mês (kWh) | F3: CNPJ Titular | G3: E-mail de acesso equatorial | H3: Desconto | I3: Desconto Band. Tar. | J3: Dia de leitura | K3: Endereço (igual a conta) | L3: Razão do Titular | M3: Data de Inicio | N3: Data de Saída
A4: Usina 1 | B4: 3023633492 | D4: 75 | E4: =168000/12 -> 14000 | F4: 43.790.285/0001-14 | H4: 0.15 | I4: 0.15 | K4: RD MA 315 , S/N , TRATA SE DE UMA USINA DE GERACAO CEP: 65590-000 JATOBA - BARREIRINHAS - MA | L4: SOLAR MARANHAO ENERGIAS RENOVAVEIS LTDA
A5: Usina 2 | B5: 3023594470 | D5: 75 | E5: =168000/12 -> 14000 | F5: 45.101.934/0001-58 | H5: 0.15 | I5: 0.15 | K5: RD SAO SEBASTIAO , S/N , RODOVIA MA 315 KM 21 8 SN CEP: 65590-000 AEROPORTO NOVO - BARREIRINHAS - MA | L5: EMPRESA DE GERACAO DE ENERGIA FOTOVOLTAICA MARANHENSE 02 (EGEFOM02) SPE LTDA
A6: Usina 3 | B6: 3023637013 | D6: 75 | E6: =168000/12 -> 14000 | F6: 45.181.504/0001-93 | H6: 0.15 | I6: 0.15 | K6: PV MANGABA , S/N , RUA PROJETADA CEP: 65590-000 MANGABA - BARREIRINHAS - MA | L6: EMPRESA DE GERACAO DE ENERGIA FOTOVOLTAICA MARANHENSE 05 (EGEFOM05) SPE LTDA

Sheet Cad.RateioConsumo
B1: Cadastro Rateio Consumo
B2: 1 | C2: 2 | D2: 3 | E2: 4 | F2: 5 | G2: 6 | H2: 7 | I2: 8 | J2: 9 | K2: 10 | L2: 11 | M2: 12 | N2: 13 | O2: 14 | U2: 20
B3: ID | C3: Nome | D3: # | E3: CNPJ/CPF | F3: Conta Contrato | G3: Tipo Instalação | H3: Consumo Médio (kWh) | I3: Desconto | J3: Desconto Band. Tar. | K3: Usina Associada | L3: Percentual Rateio (%) | M3: Acesso equatorial | N3: Endereço (igual a conta) | O3: Razão do Titular | P3: Data de Inicio | Q3: Vigente | S3: Whatsaap de Cobrança | T3: E-mail Cobrança | U3: Data de Nascimento | Z3: 2056
A4: =B4&Q4 -> 3.1sim | B4: 3.1 | C4: Associação dos Moradores do Residencial Araçagy | D4: 14 | E4: 20.069.500/0001-97 | F4: 3021142432 | G4: Comercial | H4: 205.36364 | I4: 0.15 | J4: 0.15 | K4: Usina 3 | L4: =ROUND(1.46688311688312%,4) -> 0.0147 | M4: financeiro@amelsolar.com.br | N4: R. da Agranja , 50 , CP 26 CS 59 PS 1, CEP: 65138-000 Aracagi - Raposa - MA | O4: Associação dos Moradores do Residencial Araçagy | P4: 45897 | Q4: =IF(P4<Roteiro!$G$2,"sim","não") -> sim | Z4: 2196
A5: =B5&Q5 -> 3.2sim | B5: 3.2 | C5: Associação dos Moradores do Residencial Araçagy | D5: 14 | E5: 20.069.500/0001-97 | F5: 3021149593 | G5: Comercial | H5: 734.33333 | I5: 0.15 | J5: 0.15 | K5: Usina 3 | L5: =ROUND(5.2452380952381%,4) -> 0.0525 | M5: financeiro@amelsolar.com.br | N5: R. da Agranja , 50 , CP 26 CS 36 PS 4, cep: 65138-000 Aracagi - Raposa - MA | O5: Associação dos Moradores do Residencial Araçagy | P5: 45897 | Q5: =IF(P5<Roteiro!$G$2,"sim","não") -> sim | Z5: 2391
A6: =B6&Q6 -> 3.3sim | B6: 3.3 | C6: Associação dos Moradores do Residencial Araçagy | D6: 14 | E6: 20.069.500/0001-97 | F6: 3021150559 | G6: Comercial | H6: 2086.4545 | I6: 0.15 | J6: 0.15 | K6: Usina 3 | L6: 0.107 | M6: financeiro@amelsolar.com.br | N6: R. Granja , s/n , CP 26 CS 36 PS 1, cep: 65138-000 Aracagi - Raposa - MA, | O6: Associação dos Moradores do Residencial Araçagy | P6: 45897 | Q6: =IF(P6<Roteiro!$G$2,"sim","não") -> sim | S6: suporteigsgestao@gmail.com | T6: claudemirgeo@icloud.com | V6: 1500 | W6: =ROUND(10.71%,4) -> 0.1071 | X6: alteração não implementada | AA6: 4825
A7: =B7&Q7 -> 3.4sim | B7: 3.4 | C7: Antonio Jose Souza Filho | D7: 10 | E7: 682.957.583-49 | F7: 3007625048 | G7: Residencial | H7: 417.15385 | I7: 0.15 | J7: 0.15 | K7: Usina 3 | L7: =ROUND(2.97967032967033%,4) -> 0.0298 | M7: =U7 -> 28283 | N7: R. 03 , 23 , LOT ALTO DO JAGUAREMA QD 05 LOT - ALTO DO JAGUAREMA QD 05 CEP: 65110-000 ARACAGY | O7: =C7 -> Antonio Jose Souza Filho | P7: 45897 | Q7: =IF(P7<Roteiro!$G$2,"sim","não") -> sim | U7: 28283 | Z7: 2436
A8: =B8&Q8 -> 3.5sim | B8: 3.5 | C8: João Carlos Pereira Dutra Filho | D8: 11 | E8: 064837473-49 | F8: 1163310 | G8: Residencial | H8: 848.69231 | I8: 0.15 | J8: 0.15 | K8: Usina 3 | L8: =ROUND(6.06208791208791%,4) -> 0.0606 | M8: =U8 -> 19543 | N8: R. 13 , 31 , QD 7 QD 7 CEP: 65010-000 PLN - VINHAIS II - SAO LUIS - MA | O8: =C8 -> João Carlos Pereira Dutra Filho | P8: 45961 | Q8: =IF(P8<Roteiro!$G$2,"sim","não") -> sim | U8: 19543 | V8: / | Z8: 2376
A9: =B9&Q9 -> 3.6sim | B9: 3.6 | C9: Patricia Maria Abreu Machado | D9: 19 | E9: 676.211.553-53 | F9: 3006793931 | G9: Residencial | H9: 776.76923 | I9: 0.15 | J9: 0.15 | K9: Usina 3 | L9: =ROUND(5.54835164835165%,4) -> 0.0555 | M9: =U9 -> 27174 | N9: R. MARIA F REIS , 20 , QD B CONJ BASA QD B CONJ BASA CEP: 65010-000 SAO FRANCISCO, na cidade de São Luís, Estado do Maranhão | O9: =C9 -> Patricia Maria Abreu Machado | P9: 45961 | Q9: =IF(P9<Roteiro!$G$2,"sim","não") -> sim | U9: 27174 | V9: / | Z9: 1933
A10: =B10&Q10 -> 3.7sim | B10: 3.7 | C10: Fatima Abdel Hafiz Khalifa Cavalcanti | D10: 15 | E10: 840.670.553-15 | F10: 38398091 | G10: Residencial | H10: 1013.3846 | I10: 0.15 | J10: 0.15 | K10: Usina 3 | L10: =ROUND(7.23846153846154%,4) -> 0.0724 | M10: =U10 -> 29085 | N10: Rua Nova nº63, Anil, São Luis, MA CEP: 65046-160 | O10: =C10 -> Fatima Abdel Hafiz Khalifa Cavalcanti | P10: 45961 | Q10: =IF(P10<Roteiro!$G$2,"sim","não") -> sim | S10: 98 8124-7136 | U10: 29085
A11: =B11&Q11 -> 3.8não | B11: 3.8 | C11: Ana Maria Marques De Brito | D11: 31 | E11: 920.517.663-04 | F11: 3020257082 | G11: Residencial | H11: 1193 | I11: 0.15 | J11: 0.15 | K11: Usina 3 | L11: 0.0852 | M11: =U11 -> 29585 | N11: R. F , 20 , QD 5 QD 5 CEP: 65010-000 PQ ATENAS - SAO LUIS - MA | O11: =C11 -> Ana Maria Marques De Brito | P11: 46023 | Q11: =IF(P11<Roteiro!$G$2,"sim","não") -> não | S11: 98 8124-7136 | U11: 29585
A12: =B12&Q12 -> 3.0sim | B12: 3.0 | C12: Usina 3 | D12: PJ | E12: 61.434.675/0001-33 | F12: 3023637013 | H12: =14000-SUM(H4:H9) -> 8931.2331 | I12: 0.15 | J12: 0.15 | K12: Usina 3 | L12: =100%-SUM(L4:L9) -> 0.6799 | M12: financeiro@amelsolar.com.br | N12: =Cad.Usinas!K6 -> PV MANGABA , S/N , RUA PROJETADA CEP: 65590-000 MANGABA - BARREIRINHAS - MA | O12: =C12 -> Usina 3 | P12: 45839 | Q12: =IF(P12<Roteiro!$G$2,"sim","não") -> sim | V12: 45870 | W12: 700 | Z12: 1922
A13: =B13&Q13 | V13: 45901 | W13: =H6-Z21 -> 321.45455 | X13: =W12+W13 -> 1021.4545 | Z13: 1902
A14: =B14&Q14 -> 2.1sim | B14: 2.1 | C14: Lucas Medeiros Lima | D14: PJ | E14: 612.634.903-28 | F14: 3002796782 | G14: Residencial | H14: 1536.5 | I14: 0.15 | J14: 0.15 | K14: Usina 2 | L14: =ROUND(10.975%,4) -> 0.1098 | M14: =U14 -> 35943 | N14: VL ARISTOTELES , S/N , RUA FRANCISCO MARCELINO DE MEDEIROS RUA FRANCISCO MARCELINO DE MEDEIROS CEP: 65728-000 CENTRO - LIMA CAMPOS - MA | O14: =C14 -> Lucas Medeiros Lima | P14: 45961 | Q14: =IF(P14<Roteiro!$G$2,"sim","não") -> sim | S14: (99) 8262-4178 | U14: 35943 | V14: 45931 | W14: =-$Z$21+$V$6 -> -265 | X14: =X10+W14 -> -265 | Z14: 2060
A15: =B15&Q15 -> 2.2sim | B15: 2.2 | C15: SORRISO SAUDE ODONTOLOGIA LTDA | D15: PJ | E15: 60.080.581/0001-40 | F15: 3022893768 | G15: Comercial | H15: 859 | I15: 0.17 | J15: 0.17 | K15: Usina 2 | L15: =ROUND(6.13571428571429%,4) -> 0.0614 | M15: financeiro@amelsolar.com.br | N15: AV RAIMUNDO CORREIA DA SILVA , 1346 , B B CEP: 65633-641 CIDADE NOVA - TIMON - MA | O15: =C15 -> SORRISO SAUDE ODONTOLOGIA LTDA | P15: 45961 | Q15: =IF(P15<Roteiro!$G$2,"sim","não") -> sim | S15: +55 86 8824-9275 | V15: 45931 | W15: =-$Z$21+$V$6 -> -265 | X15: =X12+W15 -> -265 | Z15: 2060
A16: =B16&Q16 -> 2.3não | B16: 2.3 | C16: José de Ribamar Aguiar Costa (Zeca) | D16: PF | E16: 225.692.943-49 | F16: 3005806061 | G16: Residencial | H16: 172.38462 | I16: 0.15 | J16: 0.15 | K16: Usina 2 | L16: 0.0123 | M16: =U16 -> 24298 | N16: R. PRINCIPAL , 10 , CEP: 65590-000 BOA VISTA - BARREIRINHAS - MA | O16: =C16 -> José de Ribamar Aguiar Costa (Zeca) | P16: 46023 | Q16: =IF(P16<Roteiro!$G$2,"sim","não") -> não | S16: +55 86 8824-9275 | U16: 24298 | V16: 45931 | W16: =-$Z$21+$V$6 -> -265 | X16: =X13+W16 -> 756.45455 | Z16: 2060
B17: 2.4 | C17: Fernando Fonseca Diniz (Andre TVN) | D17: PF | E17: 011.087.293-20 | F17: 3022544461 | G17: Residencial | H17: 241.125 | I17: 0.15 | J17: 0.15 | K17: Usina 2 | L17: 0.017223214 | M17: =U17 -> 31103 | N17: AL E , 801 , APT TORRE DA MANHA BRISAS LIFE APT TORRE DA MANHA BRISAS LIFE CEP: 65070-628 ALTO DO CALHAU - SAO LUIS - MA | U17: 31103
A18: =B18&Q22 -> 2.0 | B18: 2.0 | C18: Usina 2 | D18: PJ | E18: 61.434.675/0001-33 | F18: 3023594470 | G18: Comercial | H18: =14000 -> 14000 | I18: 0.15 | J18: 0.15 | K18: Usina 2 | L18: =100% -> 1 | M18: financeiro@amelsolar.com.br | N18: RD SAO SEBASTIAO , S/N , RODOVIA MA 315 KM 21 8 SN CEP: 65590-000 AEROPORTO NOVO - BARREIRINHAS - MA | O18: =C18 -> Usina 2 | P18: 45839 | Q18: =IF(P18<Roteiro!$G$2,"sim","não") -> sim | V18: 45931 | W18: =-$Z$21+$V$6 -> -265 | X18: =X13+W18 -> 756.45455 | Z18: 2060
A19: =B19&Q19 | V19: 45962 | W19: =W18 -> -265 | X19: =X18+W19 -> 491.45455 | Z19: 1671
A20: =B20&Q20 -> 1.0sim | B20: 1.0 | C20: Usina 1 | D20: PJ | E20: 61.434.675/0001-33 | F20: 3023633492 | H20: =14000 -> 14000 | I20: 0.15 | J20: 0.15 | K20: Usina 1 | L20: =100%-SUM(L12:L13) -> 0.3201 | M20: financeiro@amelsolar.com.br | O20: =C20 -> Usina 1 | P20: 45839 | Q20: =IF(P20<Roteiro!$G$2,"sim","não") -> sim | V20: 45992 | W20: =W19 -> -265 | X20: =X19+W20 -> 226.45455 | Z20: 2008
V21: 46023 | W21: =W20 -> -265 | X21: =X20+W21 -> -38.545455 | Z21: 1765
V23: 46082 | Z23: 700
Z24: =P26-Z23 -> 1736
C26: Hitórico Medições | O26: Max | P26: =MAX(Z3:Z21) -> 2436
C27: 45992 | E27: =SUMIF(Medições!K:K,Cad.RateioConsumo!C27,Medições!V:V) -> 7867.43 | O27: Média | P27: =AVERAGE(Z3:Z21) -> 2059.7333
C28: 45962 | E28: =SUMIF(Medições!K:K,Cad.RateioConsumo!C28,Medições!V:V) -> 4128.56
C29: 45931 | E29: =SUMIF(Medições!K:K,Cad.RateioConsumo!C29,Medições!V:V) -> 3478.63
C30: 45901 | E30: =SUMIF(Medições!K:K,Cad.RateioConsumo!C30,Medições!V:V) -> 3005.25
C31: 45870 | E31: =SUMIF(Medições!K:K,Cad.RateioConsumo!C31,Medições!V:V) -> 0
E32: =SUMIF(Medições!K:K,Cad.RateioConsumo!C32,Medições!V:V) -> 0

Sheet Hist.Geração
J1: G:\Drives compartilhados\8 Geração Distribuída\15. Operação e Manutenção\2.1 Contas de Luz Usinas Solar Maranhão
B2: Histórico Geração Usinas
B4: Nome | C4: Conta Contrato | D4: Medição | E4: Leitura | F4: Referência
A5: =B5&F5 -> Usina 107/2025 | B5: Usina 1 | C5: 3023633492 | D5: 12608 | E5: 45863 | F5: 07/2025
A6: =B6&F6 -> Usina 108/2025 | B6: Usina 1 | C6: 3023633492 | D6: 16597 | E6: 45895 | F6: 08/2025
A7: =B7&F7 -> Usina 109/2025 | B7: Usina 1 | C7: 3023633492 | D7: 16887 | E7: 45926 | F7: 09/2025
A8: =B8&F8 -> Usina 110/2025 | B8: Usina 1 | C8: 3023633492 | D8: 16135 | E8: 45957 | F8: 10/2025
A9: =B9&F9 -> Usina 111/2025 | B9: Usina 1 | C9: 3023633492 | D9: 15452 | E9: 45987 | F9: 11/2025
A10: =B10&F10 -> Usina 112/2025 | B10: Usina 1 | C10: 3023633492 | D10: 12122 | E10: 27/12/2025 | F10: 12/2025
A11: =B11&F11 -> Usina 101/2026 | B11: Usina 1 | C11: 3023633492 | D11: 11655 | E11: 46049 | F11: 01/2026
A12: =B12&F12
A13: =B13&F13 -> Usina 207/2025 | B13: Usina 2 | C13: 3023594470 | D13: 15120 | E13: 45863 | F13: 07/2025
A14: =B14&F14 -> Usina 208/2025 | B14: Usina 2 | C14: 3023594470 | D14: 16448 | E14: 45895 | F14: 08/2025
A15: =B15&F15 -> Usina 209/2025 | B15: Usina 2 | C15: 3023594470 | D15: 16732 | E15: 45926 | F15: 09/2025
A16: =B16&F16 -> Usina 210/2025 | B16: Usina 2 | C16: 3023594470 | D16: 16983 | E16: 45957 | F16: 10/2025
A17: =B17&F17 -> Usina 211/2025 | B17: Usina 2 | C17: 3023594470 | D17: 15839 | E17: 45987 | F17: 11/2025
A18: =B18&F18 -> Usina 212/2025 | B18: Usina 2 | C18: 3023594470 | D18: 13792 | E18: 46018 | F18: 12/2025
A19: =B19&F19 -> Usina 201/2026 | B19: Usina 2 | C19: 3023594470 | D19: 13974 | E19: 46049 | F19: 01/2026
A20: =B20&F20
A21: =B21&F21 -> Usina 307/2025 | B21: Usina 3 | C21: 3023637013 | D21: 12794 | E21: 45867 | F21: 07/2025
A22: =B22&F22 -> Usina 308/2025 | B22: Usina 3 | C22: 3023637013 | D22: 16329 | E22: 45898 | F22: 08/2025
A23: =B23&F23 -> Usina 309/2025 | B23: Usina 3 | C23: 3023637013 | D23: 16338 | E23: 45929 | F23: 09/2025
A24: =B24&F24 -> Usina 310/2025 | B24: Usina 3 | C24: 3023637013 | D24: 17371 | E24: 45959 | F24: 10/2025
A25: =B25&F25 -> Usina 311/2025 | B25: Usina 3 | C25: 3023637013 | D25: 15708 | E25: 45989 | F25: 11/2025
A26: =B26&F26 -> Usina 312/2025 | B26: Usina 3 | C26: 3023637013 | D26: 14276 | E26: 46021 | F26: 12/2025
A27: =B27&F27 -> Usina 301/2026 | B27: Usina 3 | C27: 3023637013 | D27: 13888 | E27: 46051 | F27: 01/2026

Sheet Hist.Consum
B1: 1 | C1: 2 | D1: 3 | E1: 4 | F1: 5 | G1: 6 | H1: 7 | I1: 8 | J1: 9 | K1: 10 | L1: 11 | M1: 12 | N1: 13 | O1: 14 | P1: 15 | Q1: 16 | R1: 17 | S1: 18 | T1: 19 | U1: 20 | V1: 21 | W1: 22 | X1: 23 | Y1: 24 | Z1: 12
C2: Histórico Consumo
M3: Consumo | P3: Dev Geração | S3: Bandeira | T3: Tributos (Aliquota | X3: Adicionais | Y3: Observação
C4: Nome | D4: Conta Contrato | E4: Nome | F4: Consumidores | G4: Conta Contrato | H4: Consumo Médio | I4: Percentual Rateio (%) | J4: Referência | K4: Leitura | L4: Vencimento | M4: Quantidade | N4: Tarifa | O4: Valor R$ | P4: Quantidade | Q4: Tarifa | R4: Valor R$ | S4: Valor R$ | T4: ICMS | U4: Pis | V4: Cofins | W4: Tarifa Vigente | X4: Total Combrança adicional GD2 | Z4: SaldoAcumulado Geração | AB4: CPF | AC4: Data Nascimento
A6: ok | B6: =E6&J6 -> 3.102/2026 | C6: Usina 3 | D6: =VLOOKUP(C6,Cad.Usinas!$A$4:$B$6,2,FALSE) -> 3023637013 | E6: 3.1 | F6: =VLOOKUP(E6,Cad.RateioConsumo!$B$4:$Q$77,2,FALSE) -> Associação dos Moradores do Residencial Araçagy | G6: =VLOOKUP(E6,Cad.RateioConsumo!$B$4:$Q$9,5,FALSE) -> 3021142432 | H6: =VLOOKUP(E6,Cad.RateioConsumo!$B$4:$Q$9,7,FALSE) -> 205.36364 | I6: =VLOOKUP(E6,Cad.RateioConsumo!$B$4:$Q$9,11,FALSE) -> 0.0147 | J6: 02/2026 | K6: 46057 | L6: 46077 | M6: 100 | N6: 1.1284 | O6: =M6*N6 -> 112.84 | P6: 108.87 | Q6: =N6 -> 1.1284 | R6: =P6*Q6 -> 122.84891 | T6: 0.23 | U6: 0.005288 | V6: 0.02441 | W6: =ROUND(0.84318/((1-U6-V6)*(1-T6)),4) -> 1.1286 | Z6: 366.56 | AB6: =VLOOKUP(E6,Cad.RateioConsumo!$B$4:$Q$9,4,FALSE) -> 20.069.500/0001-97 | AC6: =VLOOKUP(E6,Cad.RateioConsumo!$B$4:$U$9,20,FALSE) -> 0
A7: ok | B7: =E7&J7 -> 3.202/2026 | C7: Usina 3 | D7: =VLOOKUP(C7,Cad.Usinas!$A$4:$B$6,2,FALSE) -> 3023637013 | E7: 3.2 | F7: =VLOOKUP(E7,Cad.RateioConsumo!$B$4:$Q$77,2,FALSE) -> Associação dos Moradores do Residencial Araçagy | G7: =VLOOKUP(E7,Cad.RateioConsumo!$B$4:$Q$9,5,FALSE) -> 3021149593 | H7: =VLOOKUP(E7,Cad.RateioConsumo!$B$4:$Q$9,7,FALSE) -> 734.33333 | I7: =VLOOKUP(E7,Cad.RateioConsumo!$B$4:$Q$9,11,FALSE) -> 0.0525 | J7: 02/2026 | K7: 46057 | L7: 46077 | M7: 219.41 | N7: 1.128572 | O7: =M7*N7 -> 247.61998 | P7: 818.35 | Q7: =N7 -> 1.128572 | R7: =P7*Q7 -> 923.5669 | T7: 0.23 | U7: 0.005288 | V7: 0.02441 | W7: =ROUND(0.84318/ROUND(((1-U7-V7)*(1-T7)),4),4) -> 1.1286 | AB7: =VLOOKUP(E7,Cad.RateioConsumo!$B$4:$Q$9,4,FALSE) -> 20.069.500/0001-97 | AC7: =VLOOKUP(E7,Cad.RateioConsumo!$B$4:$U$9,20,FALSE) -> 0
A8: ok | B8: =E8&J8 -> 3.302/2026 | C8: Usina 3 | D8: =VLOOKUP(C8,Cad.Usinas!$A$4:$B$6,2,FALSE) -> 3023637013 | E8: 3.3 | F8: =VLOOKUP(E8,Cad.RateioConsumo!$B$4:$Q$77,2,FALSE) -> Associação dos Moradores do Residencial Araçagy | G8: =VLOOKUP(E8,Cad.RateioConsumo!$B$4:$Q$9,5,FALSE) -> 3021150559 | H8: =VLOOKUP(E8,Cad.RateioConsumo!$B$4:$Q$9,7,FALSE) -> 2086.4545 | I8: =VLOOKUP(E8,Cad.RateioConsumo!$B$4:$Q$9,11,FALSE) -> 0.107 | J8: 02/2026 | K8: 46057 | L8: 46077 | M8: 309.27 | N8: 1.128311 | O8: =M8*N8 -> 348.95274 | P8: 1487.4 | Q8: =N8 -> 1.128311 | R8: =P8*Q8 -> 1678.2498 | T8: 0.23 | U8: 0.005288 | V8: 0.02441 | W8: =ROUND(0.84318/((1-U8-V8)*(1-T8)),4) -> 1.1286 | AB8: =VLOOKUP(E8,Cad.RateioConsumo!$B$4:$Q$9,4,FALSE) -> 20.069.500/0001-97 | AC8: =VLOOKUP(E8,Cad.RateioConsumo!$B$4:$U$9,20,FALSE) -> 0
A9: ok | B9: =E9&J9 -> 3.402/2026 | C9: Usina 3 | D9: =VLOOKUP(C9,Cad.Usinas!$A$4:$B$6,2,FALSE) -> 3023637013 | E9: 3.4 | F9: =VLOOKUP(E9,Cad.RateioConsumo!$B$4:$Q$77,2,FALSE) -> Antonio Jose Souza Filho | G9: =VLOOKUP(E9,Cad.RateioConsumo!$B$4:$Q$9,5,FALSE) -> 3007625048 | H9: =VLOOKUP(E9,Cad.RateioConsumo!$B$4:$Q$9,7,FALSE) -> 417.15385 | I9: =VLOOKUP(E9,Cad.RateioConsumo!$B$4:$Q$9,11,FALSE) -> 0.0298 | J9: 02/2026 | K9: 46058 | L9: 46077 | M9: 79.13 | N9: 1.128396 | O9: =M9*N9 -> 89.289975 | P9: 413.86 | Q9: =N9 -> 1.128396 | R9: =P9*Q9 -> 466.99797 | T9: 0.23 | U9: 0.005288 | V9: 0.02441 | W9: =ROUND(0.84318/((1-U9-V9)*(1-T9)),4) -> 1.1286 | AB9: =VLOOKUP(E9,Cad.RateioConsumo!$B$4:$Q$9,4,FALSE) -> 682.957.583-49 | AC9: =VLOOKUP(E9,Cad.RateioConsumo!$B$4:$U$9,20,FALSE) -> 28283
A10: ok | B10: =E10&J10 -> 3.501/2026 | C10: Usina 3 | D10: =VLOOKUP(C10,Cad.Usinas!$A$4:$B$6,2,FALSE) -> 3023637013 | E10: 3.5 | F10: =VLOOKUP(E10,Cad.RateioConsumo!$B$4:$Q$77,2,FALSE) -> João Carlos Pereira Dutra Filho | G10: =VLOOKUP(E10,Cad.RateioConsumo!$B$4:$Q$9,5,FALSE) -> 1163310 | H10: =VLOOKUP(E10,Cad.RateioConsumo!$B$4:$Q$9,7,FALSE) -> 848.69231 | I10: =VLOOKUP(E10,Cad.RateioConsumo!$B$4:$Q$9,11,FALSE) -> 0.0606 | J10: 01/2026 | K10: 46051 | L10: 46059 | M10: 30 | N10: 1.127667 | O10: =M10*N10 -> 33.83001 | P10: 937 | Q10: =N10 -> 1.127667 | R10: =P10*Q10 -> 1056.624 | T10: 0.23 | U10: 0.005288 | V10: 0.02441 | W10: =ROUND(0.84318/((1-U10-V10)*(1-T10)),4) -> 1.1286 | Z10: 16.03 | AB10: =VLOOKUP(E10,Cad.RateioConsumo!$B$4:$Q$9,4,FALSE) -> 064837473-49 | AC10: =VLOOKUP(E10,Cad.RateioConsumo!$B$4:$U$9,20,FALSE) -> 19543
A11: ok | B11: =E11&J11 -> 3.601/2026 | C11: Usina 3 | D11: =VLOOKUP(C11,Cad.Usinas!$A$4:$B$6,2,FALSE) -> 3023637013 | E11: 3.6 | F11: =VLOOKUP(E11,Cad.RateioConsumo!$B$4:$Q$77,2,FALSE) -> Patricia Maria Abreu Machado | G11: =VLOOKUP(E11,Cad.RateioConsumo!$B$4:$Q$9,5,FALSE) -> 3006793931 | H11: =VLOOKUP(E11,Cad.RateioConsumo!$B$4:$Q$9,7,FALSE) -> 776.76923 | I11: =VLOOKUP(E11,Cad.RateioConsumo!$B$4:$Q$9,11,FALSE) -> 0.0555 | J11: 01/2026 | K11: 46050 | L11: 46057 | M11: 100 | N11: 1.1282 | O11: =M11*N11 -> 112.82 | P11: 713 | Q11: =N11 -> 1.1282 | R11: =P11*Q11 -> 804.4066 | T11: 0.23 | U11: 0.005288 | V11: 0.02441 | W11: =ROUND(0.84318/((1-U11-V11)*(1-T11)),4) -> 1.1286 | Y11: =W11-N11 -> 0.0004 | AB11: =VLOOKUP(E11,Cad.RateioConsumo!$B$4:$Q$9,4,FALSE) -> 676.211.553-53 | AC11: =VLOOKUP(E11,Cad.RateioConsumo!$B$4:$U$9,20,FALSE) -> 27174
A12: ok | B12: =E12&J12 -> 3.701/2026 | C12: Usina 3 | D12: =VLOOKUP(C12,Cad.Usinas!$A$4:$B$6,2,FALSE) -> 3023637013 | E12: 3.7 | F12: =VLOOKUP(E12,Cad.RateioConsumo!$B$4:$Q$77,2,FALSE) -> Fatima Abdel Hafiz Khalifa Cavalcanti | G12: =VLOOKUP(E12,Cad.RateioConsumo!$B$4:$Q$22,5,FALSE) -> 38398091 | H12: =VLOOKUP(E12,Cad.RateioConsumo!$B$4:$Q$22,7,FALSE) -> 1013.3846 | I12: =VLOOKUP(E12,Cad.RateioConsumo!$B$4:$Q$22,11,FALSE) -> 0.0724 | J12: 01/2026 | K12: 46042 | L12: 46059 | M12: 169.15 | N12: 1.128348 | O12: =M12*N12 -> 190.86006 | P12: 1074.84 | Q12: =N12 -> 1.128348 | R12: =P12*Q12 -> 1212.7936 | T12: 0.23 | U12: 0.005263 | V12: 0.024274 | W12: =ROUND(0.84318/((1-U12-V12)*(1-T12)),4) -> 1.1284 | X12: =W12-Q12 -> 5.2e-05 | AB12: =VLOOKUP(E12,Cad.RateioConsumo!$B$4:$Q$19,4,FALSE) -> 840.670.553-15 | AC12: =VLOOKUP(E12,Cad.RateioConsumo!$B$4:$U$19,20,FALSE) -> 29085
A13: ok | B13: =E13&J13 -> 3.801/2026 | C13: Usina 3 | D13: =VLOOKUP(C13,Cad.Usinas!$A$4:$B$6,2,FALSE) -> 3023637013 | E13: 3.8 | F13: =VLOOKUP(E13,Cad.RateioConsumo!$B$4:$Q$77,2,FALSE) -> Ana Maria Marques De Brito | G13: =VLOOKUP(E13,Cad.RateioConsumo!$B$4:$Q$22,5,FALSE) -> 3020257082 | H13: =VLOOKUP(E13,Cad.RateioConsumo!$B$4:$Q$22,7,FALSE) -> 1193 | I13: =VLOOKUP(E13,Cad.RateioConsumo!$B$4:$Q$22,11,FALSE) -> 0.0852 | J13: 01/2026 | K13: 46051 | L13: 46064 | M13: 1225 | N13: 1.128343 | O13: =M13*N13 -> 1382.2202 | P13: 0 | Q13: =N13 -> 1.128343 | R13: =P13*Q13 -> 0 | T13: 0.23 | U13: 0.005263 | V13: 0.024274 | W13: =ROUND(0.84318/((1-U13-V13)*(1-T13)),4) -> 1.1284 | X13: =W13-Q13 -> 5.7e-05 | AB13: =VLOOKUP(E13,Cad.RateioConsumo!$B$4:$Q$19,4,FALSE) -> 920.517.663-04 | AC13: =VLOOKUP(E13,Cad.RateioConsumo!$B$4:$U$19,20,FALSE) -> 29585
B14: =E14&J14 -> 3.002/2026 | C14: Usina 3 | D14: =VLOOKUP(C14,Cad.Usinas!$A$4:$B$6,2,FALSE) -> 3023637013 | E14: 3.0 | F14: =VLOOKUP(E14,Cad.RateioConsumo!$B$4:$Q$77,2,FALSE) -> Usina 3 | G14: =VLOOKUP(E14,Cad.RateioConsumo!$B$4:$Q$77,5,FALSE) -> 3023637013 | H14: =VLOOKUP(E14,Cad.RateioConsumo!$B$4:$Q$77,7,FALSE) -> 8931.2331 | I14: =VLOOKUP(E14,Cad.RateioConsumo!$B$4:$Q$77,11,FALSE) -> 0.6799 | J14: 02/2026 | O14: =M14*N14 -> 0 | Q14: =N14 -> 0 | R14: =P14*Q14 -> 0 | W14: =ROUND(0.84318/((1-U14-V14)*(1-T14)),4) -> 0.8432 | AB14: =VLOOKUP(E14,Cad.RateioConsumo!$B$4:$Q$19,4,FALSE) -> 61.434.675/0001-33 | AC14: =VLOOKUP(E14,Cad.RateioConsumo!$B$4:$U$19,20,FALSE) -> 0
B15: =E15&J15 -> 1.002/2026 | C15: Usina 1 | D15: =VLOOKUP(C15,Cad.Usinas!$A$4:$B$6,2,FALSE) -> 3023633492 | E15: 1.0 | F15: =VLOOKUP(E15,Cad.RateioConsumo!$B$4:$Q$77,2,FALSE) -> Usina 1 | G15: =VLOOKUP(E15,Cad.RateioConsumo!$B$4:$Q$77,5,FALSE) -> 3023633492 | H15: =VLOOKUP(E15,Cad.RateioConsumo!$B$4:$Q$77,7,FALSE) -> 14000 | I15: =VLOOKUP(E15,Cad.RateioConsumo!$B$4:$Q$77,11,FALSE) -> 0.3201 | J15: 02/2026 | O15: =M15*N15 -> 0 | Q15: =N15 -> 0 | R15: =P15*Q15 -> 0 | W15: =ROUND(0.84318/((1-U15-V15)*(1-T15)),4) -> 0.8432 | AB15: =VLOOKUP(E15,Cad.RateioConsumo!$B$4:$Q$19,4,FALSE) -> #N/A | AC15: =VLOOKUP(E15,Cad.RateioConsumo!$B$4:$U$19,20,FALSE) -> #N/A
B16: =E16&J16 -> 2.102/2026 | C16: Usina 2 | D16: =VLOOKUP(C16,Cad.Usinas!$A$4:$B$6,2,FALSE) -> 3023594470 | E16: 2.1 | F16: =VLOOKUP(E16,Cad.RateioConsumo!$B$4:$Q$77,2,FALSE) -> Lucas Medeiros Lima | G16: =VLOOKUP(E16,Cad.RateioConsumo!$B$4:$Q$77,5,FALSE) -> 3002796782 | H16: =VLOOKUP(E16,Cad.RateioConsumo!$B$4:$Q$77,7,FALSE) -> 1536.5 | I16: =VLOOKUP(E16,Cad.RateioConsumo!$B$4:$Q$77,11,FALSE) -> 0.1098 | J16: 02/2026 | M16: 80 | O16: =M16*N16 -> 0 | P16: 499 | Q16: =N16 -> 0 | R16: =P16*Q16 -> 0 | W16: =ROUND(0.84318/((1-U16-V16)*(1-T16)),4) -> 0.8432 | X16: =108.62+211.48+79.91-164.51-59.72 -> 175.78 | Y16: A Equatorial errou no faturamento e cobrou indevidamente uma tarifa adicional:1)Benefício Tarifário Bruto SCEE e 2) (-) Benefício Tarifário Líquido SCEE . O saldo deste valor foi dado como desconto para não te afetar os 15% de desconto na conta até que a Equatorial reverter esse valor. | AB16: =VLOOKUP(E16,Cad.RateioConsumo!$B$4:$Q$19,4,FALSE) -> 612.634.903-28 | AC16: =VLOOKUP(E16,Cad.RateioConsumo!$B$4:$U$19,20,FALSE) -> 35943
B17: =E17&J17 -> 2.201/2026 | C17: Usina 2 | D17: =VLOOKUP(C17,Cad.Usinas!$A$4:$B$6,2,FALSE) -> 3023594470 | E17: 2.2 | F17: =VLOOKUP(E17,Cad.RateioConsumo!$B$4:$Q$77,2,FALSE) -> SORRISO SAUDE ODONTOLOGIA LTDA | G17: =VLOOKUP(E17,Cad.RateioConsumo!$B$4:$Q$77,5,FALSE) -> 3022893768 | H17: =VLOOKUP(E17,Cad.RateioConsumo!$B$4:$Q$77,7,FALSE) -> 859 | I17: =VLOOKUP(E17,Cad.RateioConsumo!$B$4:$Q$77,11,FALSE) -> 0.0614 | J17: 01/2026 | M17: 100 | N17: 1.1282 | O17: =M17*N17 -> 112.82 | P17: 399 | Q17: =N17 -> 1.1282 | R17: =P17*Q17 -> 450.1518 | S17: 1.85 | T17: 0.23 | U17: 0.005263 | V17: 0.024274 | W17: =ROUND(0.84318/((1-U17-V17)*(1-T17)),4) -> 1.1284 | AB17: =VLOOKUP(E17,Cad.RateioConsumo!$B$4:$Q$19,4,FALSE) -> 60.080.581/0001-40 | AC17: =VLOOKUP(E17,Cad.RateioConsumo!$B$4:$U$19,20,FALSE) -> 0
A18: ok | B18: =E18&J18 -> 2.301/2026 | C18: Usina 2 | D18: =VLOOKUP(C18,Cad.Usinas!$A$4:$B$6,2,FALSE) -> 3023594470 | E18: 2.3 | F18: =VLOOKUP(E18,Cad.RateioConsumo!$B$4:$Q$77,2,FALSE) -> José de Ribamar Aguiar Costa (Zeca) | G18: =VLOOKUP(E18,Cad.RateioConsumo!$B$4:$Q$77,5,FALSE) -> 3005806061 | H18: =VLOOKUP(E18,Cad.RateioConsumo!$B$4:$Q$77,7,FALSE) -> 172.38462 | I18: =VLOOKUP(E18,Cad.RateioConsumo!$B$4:$Q$77,11,FALSE) -> 0.0123 | J18: 01/2026 | K18: 46051 | L18: 46064 | M18: 205 | N18: 1.12834 | O18: =M18*N18 -> 231.3097 | Q18: =N18 -> 1.12834 | R18: =P18*Q18 -> 0 | S18: 2.85 | T18: 0.23 | U18: 0.005263 | V18: 0.024274 | W18: =ROUND(0.84318/((1-U18-V18)*(1-T18)),4) -> 1.1284 | AB18: =VLOOKUP(E18,Cad.RateioConsumo!$B$4:$Q$19,4,FALSE) -> 225.692.943-49 | AC18: =VLOOKUP(E18,Cad.RateioConsumo!$B$4:$U$19,20,FALSE) -> 24298
A19: ok | B19: =E19&J19 -> 2.402/2026 | C19: Usina 2 | D19: =VLOOKUP(C19,Cad.Usinas!$A$4:$B$6,2,FALSE) -> 3023594470 | E19: 2.4 | F19: =VLOOKUP(E19,Cad.RateioConsumo!$B$4:$Q$77,2,FALSE) -> Fernando Fonseca Diniz (Andre TVN) | G19: =VLOOKUP(E19,Cad.RateioConsumo!$B$4:$Q$77,5,FALSE) -> 3022544461 | H19: =VLOOKUP(E19,Cad.RateioConsumo!$B$4:$Q$77,7,FALSE) -> 241.125 | I19: =VLOOKUP(E19,Cad.RateioConsumo!$B$4:$Q$77,11,FALSE) -> 0.017223214 | J19: 02/2026 | K19: 46051 | L19: 46064 | M19: 269 | N19: 1.128364 | O19: =M19*N19 -> 303.52992 | Q19: =N19 -> 1.128364 | R19: =P19*Q19 -> 0 | S19: 3.85 | T19: 0.23 | U19: 0.005263 | V19: 0.024274 | W19: =ROUND(0.84318/((1-U19-V19)*(1-T19)),4) -> 1.1284 | AB19: =VLOOKUP(E19,Cad.RateioConsumo!$B$4:$Q$19,4,FALSE) -> 011.087.293-20 | AC19: =VLOOKUP(E19,Cad.RateioConsumo!$B$4:$U$19,20,FALSE) -> 31103
B20: =E20&J20 -> 2.002/2026 | C20: Usina 2 | D20: =VLOOKUP(C20,Cad.Usinas!$A$4:$B$6,2,FALSE) -> 3023594470 | E20: 2.0 | F20: =VLOOKUP(E20,Cad.RateioConsumo!$B$4:$Q$77,2,FALSE) -> Usina 2 | G20: =VLOOKUP(E20,Cad.RateioConsumo!$B$4:$Q$77,5,FALSE) -> 3023594470 | H20: =VLOOKUP(E20,Cad.RateioConsumo!$B$4:$Q$77,7,FALSE) -> 14000 | I20: =VLOOKUP(E20,Cad.RateioConsumo!$B$4:$Q$77,11,FALSE) -> 1 | J20: 02/2026 | O20: =M20*N20 -> 0 | Q20: =N20 -> 0 | R20: =P20*Q20 -> 0 | W20: =ROUND(0.84318/((1-U20-V20)*(1-T20)),4) -> 0.8432 | AB20: =VLOOKUP(E20,Cad.RateioConsumo!$B$4:$Q$19,4,FALSE) -> 61.434.675/0001-33 | AC20: =VLOOKUP(E20,Cad.RateioConsumo!$B$4:$U$19,20,FALSE) -> 0
A22: ok | B22: =E22&J22 -> 3.101/2026 | C22: Usina 3 | D22: =VLOOKUP(C22,Cad.Usinas!$A$4:$B$6,2,FALSE) -> 3023637013 | E22: 3.1 | F22: =VLOOKUP(E22,Cad.RateioConsumo!$B$4:$Q$77,2,FALSE) -> Associação dos Moradores do Residencial Araçagy | G22: =VLOOKUP(E22,Cad.RateioConsumo!$B$4:$Q$9,5,FALSE) -> 3021142432 | H22: =VLOOKUP(E22,Cad.RateioConsumo!$B$4:$Q$9,7,FALSE) -> 205.36364 | I22: =VLOOKUP(E22,Cad.RateioConsumo!$B$4:$Q$9,11,FALSE) -> 0.0147 | J22: 01/2026 | K22: 46026 | L22: 46046 | M22: 100 | N22: 1.1282 | O22: =M22*N22 -> 112.82 | P22: 114.86 | Q22: =N22 -> 1.1282 | R22: =P22*Q22 -> 129.58505 | S22: 2.19 | T22: 0.23 | U22: 0.005263 | V22: 0.024274 | W22: =ROUND(0.84318/((1-U22-V22)*(1-T22)),4) -> 1.1284 | AB22: =VLOOKUP(E22,Cad.RateioConsumo!$B$4:$Q$9,4,FALSE) -> 20.069.500/0001-97 | AC22: =VLOOKUP(E22,Cad.RateioConsumo!$B$4:$U$9,20,FALSE) -> 0
A23: ok | B23: =E23&J23 -> 3.201/2026 | C23: Usina 3 | D23: =VLOOKUP(C23,Cad.Usinas!$A$4:$B$6,2,FALSE) -> 3023637013 | E23: 3.2 | F23: =VLOOKUP(E23,Cad.RateioConsumo!$B$4:$Q$77,2,FALSE) -> Associação dos Moradores do Residencial Araçagy | G23: =VLOOKUP(E23,Cad.RateioConsumo!$B$4:$Q$9,5,FALSE) -> 3021149593 | H23: =VLOOKUP(E23,Cad.RateioConsumo!$B$4:$Q$9,7,FALSE) -> 734.33333 | I23: =VLOOKUP(E23,Cad.RateioConsumo!$B$4:$Q$9,11,FALSE) -> 0.0525 | J23: 01/2026 | K23: 46026 | L23: 46046 | M23: 30 | N23: 1.127667 | O23: =M23*N23 -> 33.83001 | P23: 660.25 | Q23: =N23 -> 1.127667 | R23: =P23*Q23 -> 744.54214 | S23: 0.65 | T23: 0.23 | U23: 0.005263 | V23: 0.024274 | W23: =ROUND(0.84318/ROUND(((1-U23-V23)*(1-T23)),4),4) -> 1.1283 | AB23: =VLOOKUP(E23,Cad.RateioConsumo!$B$4:$Q$9,4,FALSE) -> 20.069.500/0001-97 | AC23: =VLOOKUP(E23,Cad.RateioConsumo!$B$4:$U$9,20,FALSE) -> 0
A24: ok | B24: =E24&J24 -> 3.301/2026 | C24: Usina 3 | D24: =VLOOKUP(C24,Cad.Usinas!$A$4:$B$6,2,FALSE) -> 3023637013 | E24: 3.3 | F24: =VLOOKUP(E24,Cad.RateioConsumo!$B$4:$Q$77,2,FALSE) -> Associação dos Moradores do Residencial Araçagy | G24: =VLOOKUP(E24,Cad.RateioConsumo!$B$4:$Q$9,5,FALSE) -> 3021150559 | H24: =VLOOKUP(E24,Cad.RateioConsumo!$B$4:$Q$9,7,FALSE) -> 2086.4545 | I24: =VLOOKUP(E24,Cad.RateioConsumo!$B$4:$Q$9,11,FALSE) -> 0.107 | J24: 01/2026 | K24: 46026 | L24: 46046 | M24: 307.3 | N24: 1.128311 | O24: =M24*N24 -> 346.72997 | P24: 1528.95 | Q24: =N24 -> 1.128311 | R24: =P24*Q24 -> 1725.1311 | S24: 6.75 | T24: 0.23 | U24: 0.005263 | V24: 0.024274 | W24: =ROUND(0.84318/((1-U24-V24)*(1-T24)),4) -> 1.1284 | AB24: =VLOOKUP(E24,Cad.RateioConsumo!$B$4:$Q$9,4,FALSE) -> 20.069.500/0001-97 | AC24: =VLOOKUP(E24,Cad.RateioConsumo!$B$4:$U$9,20,FALSE) -> 0
A25: ok | B25: =E25&J25 -> 3.401/2026 | C25: Usina 3 | D25: =VLOOKUP(C25,Cad.Usinas!$A$4:$B$6,2,FALSE) -> 3023637013 | E25: 3.4 | F25: =VLOOKUP(E25,Cad.RateioConsumo!$B$4:$Q$77,2,FALSE) -> Antonio Jose Souza Filho | G25: =VLOOKUP(E25,Cad.RateioConsumo!$B$4:$Q$9,5,FALSE) -> 3007625048 | H25: =VLOOKUP(E25,Cad.RateioConsumo!$B$4:$Q$9,7,FALSE) -> 417.15385 | I25: =VLOOKUP(E25,Cad.RateioConsumo!$B$4:$Q$9,11,FALSE) -> 0.0298 | J25: 01/2026 | K25: 46029 | L25: 46046 | M25: 129.47 | N25: 1.128292 | O25: =M25*N25 -> 146.07997 | P25: 441.52 | Q25: =N25 -> 1.128292 | R25: =P25*Q25 -> 498.16348 | S25: 2.57 | T25: 0.23 | U25: 0.005263 | V25: 0.024274 | W25: =ROUND(0.84318/((1-U25-V25)*(1-T25)),4) -> 1.1284 | AB25: =VLOOKUP(E25,Cad.RateioConsumo!$B$4:$Q$9,4,FALSE) -> 682.957.583-49 | AC25: =VLOOKUP(E25,Cad.RateioConsumo!$B$4:$U$9,20,FALSE) -> 28283
A26: ok | B26: =E26&J26 -> 3.512/2025 | C26: Usina 3 | D26: =VLOOKUP(C26,Cad.Usinas!$A$4:$B$6,2,FALSE) -> 3023637013 | E26: 3.5 | F26: =VLOOKUP(E26,Cad.RateioConsumo!$B$4:$Q$77,2,FALSE) -> João Carlos Pereira Dutra Filho | G26: =VLOOKUP(E26,Cad.RateioConsumo!$B$4:$Q$9,5,FALSE) -> 1163310 | H26: =VLOOKUP(E26,Cad.RateioConsumo!$B$4:$Q$9,7,FALSE) -> 848.69231 | I26: =VLOOKUP(E26,Cad.RateioConsumo!$B$4:$Q$9,11,FALSE) -> 0.0606 | J26: 12/2025 | K26: 46021 | L26: 46028 | M26: 30 | N26: 1.42 | O26: =M26*N26 -> 42.6 | P26: 864 | Q26: =N26 -> 1.42 | R26: =P26*Q26 -> 1226.88 | S26: 0.83 | T26: 0.23 | U26: 0.007434 | V26: 0.034283 | W26: =ROUND(0.84318/((1-U26-V26)*(1-T26)),4) -> 1.1427 | AB26: =VLOOKUP(E26,Cad.RateioConsumo!$B$4:$Q$9,4,FALSE) -> 064837473-49 | AC26: =VLOOKUP(E26,Cad.RateioConsumo!$B$4:$U$9,20,FALSE) -> 19543
A27: ok | B27: =E27&J27 -> 3.601/2026 | C27: Usina 3 | D27: =VLOOKUP(C27,Cad.Usinas!$A$4:$B$6,2,FALSE) -> 3023637013 | E27: 3.6 | F27: =VLOOKUP(E27,Cad.RateioConsumo!$B$4:$Q$77,2,FALSE) -> Patricia Maria Abreu Machado | G27: =VLOOKUP(E27,Cad.RateioConsumo!$B$4:$Q$9,5,FALSE) -> 3006793931 | H27: =VLOOKUP(E27,Cad.RateioConsumo!$B$4:$Q$9,7,FALSE) -> 776.76923 | I27: =VLOOKUP(E27,Cad.RateioConsumo!$B$4:$Q$9,11,FALSE) -> 0.0555 | J27: 01/2026 | K27: 46034 | L27: 46048 | O27: =M27*N27 -> 0 | Q27: =N27 -> 0 | R27: =P27*Q27 -> 0 | W27: =ROUND(0.84318/((1-U27-V27)*(1-T27)),4) -> 0.8432 | X27: O contrato foi feito com base no consumo médio de 777 kwh e em dezembro foi consumido energia maior que a média por isso a energia paga pela Equatorial foi maior. Se existir uma tendência de aumento do consumo da energia favor nos informar para ajustarmos o contrato. | Y27: =W27-N27 -> 0.8432 | AB27: =VLOOKUP(E27,Cad.RateioConsumo!$B$4:$Q$9,4,FALSE) -> 676.211.553-53 | AC27: =VLOOKUP(E27,Cad.RateioConsumo!$B$4:$U$9,20,FALSE) -> 27174
A28: ok | B28: =E28&J28 -> 3.7 | C28: Usina 3 | D28: =VLOOKUP(C28,Cad.Usinas!$A$4:$B$6,2,FALSE) -> 3023637013 | E28: 3.7 | F28: =VLOOKUP(E28,Cad.RateioConsumo!$B$4:$Q$77,2,FALSE) -> Fatima Abdel Hafiz Khalifa Cavalcanti | G28: =VLOOKUP(E28,Cad.RateioConsumo!$B$4:$Q$22,5,FALSE) -> 38398091 | H28: =VLOOKUP(E28,Cad.RateioConsumo!$B$4:$Q$22,7,FALSE) -> 1013.3846 | I28: =VLOOKUP(E28,Cad.RateioConsumo!$B$4:$Q$22,11,FALSE) -> 0.0724 | O28: =M28*N28 -> 0 | Q28: =N28 -> 0 | R28: =P28*Q28 -> 0 | W28: =ROUND(0.84318/((1-U28-V28)*(1-T28)),4) -> 0.8432 | X28: =W28-Q28 -> 0.8432 | AB28: =VLOOKUP(E28,Cad.RateioConsumo!$B$4:$Q$19,4,FALSE) -> 840.670.553-15 | AC28: =VLOOKUP(E28,Cad.RateioConsumo!$B$4:$U$19,20,FALSE) -> 29085
B29: =E29&J29 -> 3.001/2026 | C29: Usina 3 | D29: =VLOOKUP(C29,Cad.Usinas!$A$4:$B$6,2,FALSE) -> 3023637013 | E29: 3.0 | F29: =VLOOKUP(E29,Cad.RateioConsumo!$B$4:$Q$77,2,FALSE) -> Usina 3 | G29: =VLOOKUP(E29,Cad.RateioConsumo!$B$4:$Q$77,5,FALSE) -> 3023637013 | H29: =VLOOKUP(E29,Cad.RateioConsumo!$B$4:$Q$77,7,FALSE) -> 8931.2331 | I29: =VLOOKUP(E29,Cad.RateioConsumo!$B$4:$Q$77,11,FALSE) -> 0.6799 | J29: 01/2026 | O29: =M29*N29 -> 0 | Q29: =N29 -> 0 | R29: =P29*Q29 -> 0 | W29: =ROUND(0.84318/((1-U29-V29)*(1-T29)),4) -> 0.8432 | AB29: =VLOOKUP(E29,Cad.RateioConsumo!$B$4:$Q$19,4,FALSE) -> 61.434.675/0001-33 | AC29: =VLOOKUP(E29,Cad.RateioConsumo!$B$4:$U$19,20,FALSE) -> 0
B30: =E30&J30 -> 1.001/2026 | C30: Usina 1 | D30: =VLOOKUP(C30,Cad.Usinas!$A$4:$B$6,2,FALSE) -> 3023633492 | E30: 1.0 | F30: =VLOOKUP(E30,Cad.RateioConsumo!$B$4:$Q$77,2,FALSE) -> Usina 1 | G30: =VLOOKUP(E30,Cad.RateioConsumo!$B$4:$Q$77,5,FALSE) -> 3023633492 | H30: =VLOOKUP(E30,Cad.RateioConsumo!$B$4:$Q$77,7,FALSE) -> 14000 | I30: =VLOOKUP(E30,Cad.RateioConsumo!$B$4:$Q$77,11,FALSE) -> 0.3201 | J30: 01/2026 | O30: =M30*N30 -> 0 | Q30: =N30 -> 0 | R30: =P30*Q30 -> 0 | W30: =ROUND(0.84318/((1-U30-V30)*(1-T30)),4) -> 0.8432 | Y30: A Equatorial cobrou errado uma tarida de GD2 , gerando itens que não são devidos: 1)Benefício Tarifário Bruto SCEE R$ 961,08 e 2) (-) Benefício Tarifário Líquido SCEE 702,62. O saldo deste valor foi dado como desconto para não te afetar os 15% de desconto na conta até que a Equatorial reverter esse valor. | AB30: =VLOOKUP(E30,Cad.RateioConsumo!$B$4:$Q$19,4,FALSE) -> #N/A | AC30: =VLOOKUP(E30,Cad.RateioConsumo!$B$4:$U$19,20,FALSE) -> #N/A
B31: =E31&J31 -> 2.101/2026 | C31: Usina 2 | D31: =VLOOKUP(C31,Cad.Usinas!$A$4:$B$6,2,FALSE) -> 3023594470 | E31: 2.1 | F31: =VLOOKUP(E31,Cad.RateioConsumo!$B$4:$Q$77,2,FALSE) -> Lucas Medeiros Lima | G31: =VLOOKUP(E31,Cad.RateioConsumo!$B$4:$Q$77,5,FALSE) -> 3002796782 | H31: =VLOOKUP(E31,Cad.RateioConsumo!$B$4:$Q$77,7,FALSE) -> 1536.5 | I31: =VLOOKUP(E31,Cad.RateioConsumo!$B$4:$Q$77,11,FALSE) -> 0.1098 | J31: 01/2026 | K31: 46034 | L31: 46048 | M31: 80 | O31: =M31*N31 -> 0 | P31: 499 | Q31: =N31 -> 0 | R31: =P31*Q31 -> 0 | W31: =ROUND(0.84318/((1-U31-V31)*(1-T31)),4) -> 0.8432 | X31: =108.62+211.48+79.91-164.51-59.72 -> 175.78 | Y31: A Equatorial errou no faturamento e cobrou indevidamente uma tarifa adicional:1)Benefício Tarifário Bruto SCEE e 2) (-) Benefício Tarifário Líquido SCEE . O saldo deste valor foi dado como desconto para não te afetar os 15% de desconto na conta até que a Equatorial reverter esse valor. | AB31: =VLOOKUP(E31,Cad.RateioConsumo!$B$4:$Q$19,4,FALSE) -> 612.634.903-28 | AC31: =VLOOKUP(E31,Cad.RateioConsumo!$B$4:$U$19,20,FALSE) -> 35943
A32: ok | B32: =E32&J32 -> 2.201/2026 | C32: Usina 2 | D32: =VLOOKUP(C32,Cad.Usinas!$A$4:$B$6,2,FALSE) -> 3023594470 | E32: 2.2 | F32: =VLOOKUP(E32,Cad.RateioConsumo!$B$4:$Q$77,2,FALSE) -> SORRISO SAUDE ODONTOLOGIA LTDA | G32: =VLOOKUP(E32,Cad.RateioConsumo!$B$4:$Q$77,5,FALSE) -> 3022893768 | H32: =VLOOKUP(E32,Cad.RateioConsumo!$B$4:$Q$77,7,FALSE) -> 859 | I32: =VLOOKUP(E32,Cad.RateioConsumo!$B$4:$Q$77,11,FALSE) -> 0.0614 | J32: 01/2026 | K32: 46030 | L32: 46037 | M32: 100 | N32: 1.1282 | O32: =M32*N32 -> 112.82 | P32: 399 | Q32: =N32 -> 1.1282 | R32: =P32*Q32 -> 450.1518 | S32: 1.85 | T32: 0.23 | U32: 0.005263 | V32: 0.024274 | W32: =ROUND(0.84318/((1-U32-V32)*(1-T32)),4) -> 1.1284 | AB32: =VLOOKUP(E32,Cad.RateioConsumo!$B$4:$Q$19,4,FALSE) -> 60.080.581/0001-40 | AC32: =VLOOKUP(E32,Cad.RateioConsumo!$B$4:$U$19,20,FALSE) -> 0
B33: =E33&J33 -> 2.001/2026 | C33: Usina 2 | D33: =VLOOKUP(C33,Cad.Usinas!$A$4:$B$6,2,FALSE) -> 3023594470 | E33: 2.0 | F33: =VLOOKUP(E33,Cad.RateioConsumo!$B$4:$Q$77,2,FALSE) -> Usina 2 | G33: =VLOOKUP(E33,Cad.RateioConsumo!$B$4:$Q$77,5,FALSE) -> 3023594470 | H33: =VLOOKUP(E33,Cad.RateioConsumo!$B$4:$Q$77,7,FALSE) -> 14000 | I33: =VLOOKUP(E33,Cad.RateioConsumo!$B$4:$Q$77,11,FALSE) -> 1 | J33: 01/2026 | O33: =M33*N33 -> 0 | Q33: =N33 -> 0 | R33: =P33*Q33 -> 0 | W33: =ROUND(0.84318/((1-U33-V33)*(1-T33)),4) -> 0.8432 | AB33: =VLOOKUP(E33,Cad.RateioConsumo!$B$4:$Q$19,4,FALSE) -> 61.434.675/0001-33 | AC33: =VLOOKUP(E33,Cad.RateioConsumo!$B$4:$U$19,20,FALSE) -> 0
A35: ok | B35: =E35&J35 -> 3.112/2025 | C35: Usina 3 | D35: =VLOOKUP(C35,Cad.Usinas!$A$4:$B$6,2,FALSE) -> 3023637013 | E35: 3.1 | F35: =VLOOKUP(E35,Cad.RateioConsumo!$B$4:$Q$77,2,FALSE) -> Associação dos Moradores do Residencial Araçagy | G35: =VLOOKUP(E35,Cad.RateioConsumo!$B$4:$Q$9,5,FALSE) -> 3021142432 | H35: =VLOOKUP(E35,Cad.RateioConsumo!$B$4:$Q$9,7,FALSE) -> 205.36364 | I35: =VLOOKUP(E35,Cad.RateioConsumo!$B$4:$Q$9,11,FALSE) -> 0.0147 | J35: 12/2025 | K35: 45995 | L35: 46015 | M35: 100 | N35: 1.142725 | O35: =M35*N35 -> 114.2725 | P35: 120.86 | Q35: =N35 -> 1.142725 | R35: =P35*Q35 -> 138.10974 | S35: 5.21 | T35: 0.23 | U35: 0.007434 | V35: 0.034283 | W35: =ROUND(0.84318/((1-U35-V35)*(1-T35)),4) -> 1.1427
A36: ok | B36: =E36&J36 -> 3.212/2025 | C36: Usina 3 | D36: =VLOOKUP(C36,Cad.Usinas!$A$4:$B$6,2,FALSE) -> 3023637013 | E36: 3.2 | F36: =VLOOKUP(E36,Cad.RateioConsumo!$B$4:$Q$77,2,FALSE) -> Associação dos Moradores do Residencial Araçagy | G36: =VLOOKUP(E36,Cad.RateioConsumo!$B$4:$Q$9,5,FALSE) -> 3021149593 | H36: =VLOOKUP(E36,Cad.RateioConsumo!$B$4:$Q$9,7,FALSE) -> 734.33333 | I36: =VLOOKUP(E36,Cad.RateioConsumo!$B$4:$Q$9,11,FALSE) -> 0.0525 | J36: 12/2025 | K36: 45995 | L36: 46015 | M36: 162.69 | N36: 1.142725 | O36: =M36*N36 -> 185.90993 | P36: 824.67 | Q36: =N36 -> 1.142725 | R36: =P36*Q36 -> 942.37103 | S36: 8.47 | T36: 0.23 | U36: 0.007434 | V36: 0.034283 | W36: =ROUND(0.84318/((1-U36-V36)*(1-T36)),4) -> 1.1427
A37: ok | B37: =E37&J37 -> 3.312/2025 | C37: Usina 3 | D37: =VLOOKUP(C37,Cad.Usinas!$A$4:$B$6,2,FALSE) -> 3023637013 | E37: 3.3 | F37: =VLOOKUP(E37,Cad.RateioConsumo!$B$4:$Q$77,2,FALSE) -> Associação dos Moradores do Residencial Araçagy | G37: =VLOOKUP(E37,Cad.RateioConsumo!$B$4:$Q$9,5,FALSE) -> 3021150559 | H37: =VLOOKUP(E37,Cad.RateioConsumo!$B$4:$Q$9,7,FALSE) -> 2086.4545 | I37: =VLOOKUP(E37,Cad.RateioConsumo!$B$4:$Q$9,11,FALSE) -> 0.107 | J37: 12/2025 | K37: 45995 | L37: 46015 | M37: 374.43 | N37: 1.142725 | O37: =M37*N37 -> 427.87052 | P37: 1682.32 | Q37: =N37 -> 1.142725 | R37: =P37*Q37 -> 1922.4291 | S37: 19.52 | T37: 0.23 | U37: 0.007434 | V37: 0.034283 | W37: =ROUND(0.84318/((1-U37-V37)*(1-T37)),4) -> 1.1427
A38: ok | B38: =E38&J38 -> 3.412/2025 | C38: Usina 3 | D38: =VLOOKUP(C38,Cad.Usinas!$A$4:$B$6,2,FALSE) -> 3023637013 | E38: 3.4 | F38: =VLOOKUP(E38,Cad.RateioConsumo!$B$4:$Q$77,2,FALSE) -> Antonio Jose Souza Filho | G38: =VLOOKUP(E38,Cad.RateioConsumo!$B$4:$Q$9,5,FALSE) -> 3007625048 | H38: =VLOOKUP(E38,Cad.RateioConsumo!$B$4:$Q$9,7,FALSE) -> 417.15385 | I38: =VLOOKUP(E38,Cad.RateioConsumo!$B$4:$Q$9,11,FALSE) -> 0.0298 | J38: 12/2025 | K38: 45996 | L38: 46015 | M38: 30 | N38: 1.142725 | O38: =M38*N38 -> 34.28175 | P38: 452 | Q38: =N38 -> 1.142725 | R38: =P38*Q38 -> 516.5117 | S38: 1.49 | T38: 0.23 | U38: 0.007434 | V38: 0.034283 | W38: =ROUND(0.84318/((1-U38-V38)*(1-T38)),4) -> 1.1427
A39: ok | B39: =E39&J39 -> 3.5 | C39: Usina 3 | D39: =VLOOKUP(C39,Cad.Usinas!$A$4:$B$6,2,FALSE) -> 3023637013 | E39: 3.5 | F39: =VLOOKUP(E39,Cad.RateioConsumo!$B$4:$Q$77,2,FALSE) -> João Carlos Pereira Dutra Filho | G39: =VLOOKUP(E39,Cad.RateioConsumo!$B$4:$Q$9,5,FALSE) -> 1163310 | H39: =VLOOKUP(E39,Cad.RateioConsumo!$B$4:$Q$9,7,FALSE) -> 848.69231 | I39: =VLOOKUP(E39,Cad.RateioConsumo!$B$4:$Q$9,11,FALSE) -> 0.0606 | O39: =M39*N39 -> 0 | Q39: =N39 -> 0 | R39: =P39*Q39 -> 0
A40: ok | B40: =E40&J40 -> 3.612/2025 | C40: Usina 3 | D40: =VLOOKUP(C40,Cad.Usinas!$A$4:$B$6,2,FALSE) -> 3023637013 | E40: 3.6 | F40: =VLOOKUP(E40,Cad.RateioConsumo!$B$4:$Q$77,2,FALSE) -> Patricia Maria Abreu Machado | G40: =VLOOKUP(E40,Cad.RateioConsumo!$B$4:$Q$9,5,FALSE) -> 3006793931 | H40: =VLOOKUP(E40,Cad.RateioConsumo!$B$4:$Q$9,7,FALSE) -> 776.76923 | I40: =VLOOKUP(E40,Cad.RateioConsumo!$B$4:$Q$9,11,FALSE) -> 0.0555 | J40: 12/2025 | K40: 46020 | L40: 46029 | M40: 210.2 | N40: 1.142626 | O40: =M40*N40 -> 240.17999 | P40: 871.79 | Q40: =N40 -> 1.142626 | R40: =P40*Q40 -> 996.12992 | S40: =4.87+1.18 -> 6.05 | T40: 0.23 | U40: 0.007434 | V40: 0.034283 | W40: =ROUND(0.84318/((1-U40-V40)*(1-T40)),4) -> 1.1427 | X40: O contrato foi feito com base no consumo médio de 777 kwh e em dezembro foi consumido energia maior que a média por isso a energia paga pela Equatorial foi maior. Se existir uma tendência de aumento do consumo da energia favor nos informar para ajustarmos o contrato. | Y40: =W40-N40 -> 7.4e-05
A41: ok | B41: =E41&J41 -> 3.712/2025 | C41: Usina 3 | D41: =VLOOKUP(C41,Cad.Usinas!$A$4:$B$6,2,FALSE) -> 3023637013 | E41: 3.7 | F41: =VLOOKUP(E41,Cad.RateioConsumo!$B$4:$Q$77,2,FALSE) -> Fatima Abdel Hafiz Khalifa Cavalcanti | G41: =VLOOKUP(E41,Cad.RateioConsumo!$B$4:$Q$22,5,FALSE) -> 38398091 | H41: =VLOOKUP(E41,Cad.RateioConsumo!$B$4:$Q$22,7,FALSE) -> 1013.3846 | I41: =VLOOKUP(E41,Cad.RateioConsumo!$B$4:$Q$22,11,FALSE) -> 0.0724 | J41: 12/2025 | K41: 46011 | L41: 45663 | M41: 30 | N41: 1.142 | O41: =M41*N41 -> 34.26 | P41: 1096 | Q41: =N41 -> 1.142 | R41: =P41*Q41 -> 1251.632 | S41: =0.48+0.64 -> 1.12 | T41: 0.23 | U41: 0.007434 | V41: 0.034283 | W41: =ROUND(0.84318/((1-U41-V41)*(1-T41)),4) -> 1.1427 | X41: =W41-Q41 -> 0.0007
B42: =E42&J42 -> 3.012/2025 | C42: Usina 3 | D42: =VLOOKUP(C42,Cad.Usinas!$A$4:$B$6,2,FALSE) -> 3023637013 | E42: 3.0 | F42: =VLOOKUP(E42,Cad.RateioConsumo!$B$4:$Q$77,2,FALSE) -> Usina 3 | G42: =VLOOKUP(E42,Cad.RateioConsumo!$B$4:$Q$77,5,FALSE) -> 3023637013 | H42: =VLOOKUP(E42,Cad.RateioConsumo!$B$4:$Q$77,7,FALSE) -> 8931.2331 | I42: =VLOOKUP(E42,Cad.RateioConsumo!$B$4:$Q$77,11,FALSE) -> 0.6799 | J42: 12/2025 | T42: 0.23 | U42: 0.007434 | V42: 0.034283 | W42: =ROUND(0.84318/((1-U42-V42)*(1-T42)),4) -> 1.1427
B43: =E43&J43 -> 1.012/2025 | C43: Usina 1 | D43: =VLOOKUP(C43,Cad.Usinas!$A$4:$B$6,2,FALSE) -> 3023633492 | E43: 1.0 | F43: =VLOOKUP(E43,Cad.RateioConsumo!$B$4:$Q$77,2,FALSE) -> Usina 1 | G43: =VLOOKUP(E43,Cad.RateioConsumo!$B$4:$Q$77,5,FALSE) -> 3023633492 | H43: =VLOOKUP(E43,Cad.RateioConsumo!$B$4:$Q$77,7,FALSE) -> 14000 | I43: =VLOOKUP(E43,Cad.RateioConsumo!$B$4:$Q$77,11,FALSE) -> 0.3201 | J43: 12/2025 | M43: 0 | T43: 0.23 | U43: 0.007434 | V43: 0.034283 | W43: =ROUND(0.84318/((1-U43-V43)*(1-T43)),4) -> 1.1427 | Y43: A Equatorial cobrou errado uma tarida de GD2 , gerando itens que não são devidos: 1)Benefício Tarifário Bruto SCEE R$ 961,08 e 2) (-) Benefício Tarifário Líquido SCEE 702,62. O saldo deste valor foi dado como desconto para não te afetar os 15% de desconto na conta até que a Equatorial reverter esse valor.
A44: ok | B44: =E44&J44 -> 2.112/2025 | C44: Usina 2 | D44: =VLOOKUP(C44,Cad.Usinas!$A$4:$B$6,2,FALSE) -> 3023594470 | E44: 2.1 | F44: =VLOOKUP(E44,Cad.RateioConsumo!$B$4:$Q$77,2,FALSE) -> Lucas Medeiros Lima | G44: =VLOOKUP(E44,Cad.RateioConsumo!$B$4:$Q$77,5,FALSE) -> 3002796782 | H44: =VLOOKUP(E44,Cad.RateioConsumo!$B$4:$Q$77,7,FALSE) -> 1536.5 | I44: =VLOOKUP(E44,Cad.RateioConsumo!$B$4:$Q$77,11,FALSE) -> 0.1098 | J44: 12/2025 | K44: 46003 | L44: 46017 | M44: 80 | N44: 1.142 | P44: 1123 | Q44: =W44 -> 1.1427 | R44: =P44*Q44 -> 1283.2521 | S44: =0.19+0.73 -> 0.92 | T44: 0.23 | U44: 0.007434 | V44: 0.034283 | W44: =ROUND(0.84318/((1-U44-V44)*(1-T44)),4) -> 1.1427 | X44: =225.26+524.3+84.04-391.98-62.01 -> 379.61 | Y44: A Equatorial errou no faturamento e cobrou indevidamente uma tarifa adicional:1)Benefício Tarifário Bruto SCEE e 2) (-) Benefício Tarifário Líquido SCEE . O saldo deste valor foi dado como desconto para não te afetar os 15% de desconto na conta até que a Equatorial reverter esse valor.
A45: ok | B45: =E45&J45 -> 2.212/2025 | C45: Usina 2 | D45: =VLOOKUP(C45,Cad.Usinas!$A$4:$B$6,2,FALSE) -> 3023594470 | E45: 2.2 | F45: =VLOOKUP(E45,Cad.RateioConsumo!$B$4:$Q$77,2,FALSE) -> SORRISO SAUDE ODONTOLOGIA LTDA | G45: =VLOOKUP(E45,Cad.RateioConsumo!$B$4:$Q$77,5,FALSE) -> 3022893768 | H45: =VLOOKUP(E45,Cad.RateioConsumo!$B$4:$Q$77,7,FALSE) -> 859 | I45: =VLOOKUP(E45,Cad.RateioConsumo!$B$4:$Q$77,11,FALSE) -> 0.0614 | J45: 12/2025 | K45: 46000 | L45: 46007 | P45: 917 | Q45: =W45 -> 1.1427 | R45: =P45*Q45 -> 1047.8559 | S45: 4.33 | T45: 0.23 | U45: 0.007434 | V45: 0.034283 | W45: =ROUND(0.84318/((1-U45-V45)*(1-T45)),4) -> 1.1427 | X45: =-552.23-183.42+414.08 -> -321.57 | Y45: A Equatorial errou no faturamento e cobrou indevidamente uma tarifa adicional:1)Benefício Tarifário Bruto SCEE e 2) (-) Benefício Tarifário Líquido SCEE . O saldo deste valor foi dado como desconto para não te afetar os 15% de desconto na conta até que a Equatorial reverter esse valor.
B46: =E46&J46 -> 2.012/2025 | C46: Usina 2 | D46: =VLOOKUP(C46,Cad.Usinas!$A$4:$B$6,2,FALSE) -> 3023594470 | E46: 2.0 | F46: =VLOOKUP(E46,Cad.RateioConsumo!$B$4:$Q$77,2,FALSE) -> Usina 2 | G46: =VLOOKUP(E46,Cad.RateioConsumo!$B$4:$Q$77,5,FALSE) -> 3023594470 | H46: =VLOOKUP(E46,Cad.RateioConsumo!$B$4:$Q$77,7,FALSE) -> 14000 | I46: =VLOOKUP(E46,Cad.RateioConsumo!$B$4:$Q$77,11,FALSE) -> 1 | J46: 12/2025 | M46: 0 | P46: 0 | T46: 0.23 | U46: 0.007434 | V46: 0.034283 | W46: =ROUND(0.84318/((1-U46-V46)*(1-T46)),4) -> 1.1427
B48: =E48&J48 -> 3.111/2025 | C48: Usina 3 | D48: =VLOOKUP(C48,Cad.Usinas!$A$4:$B$6,2,FALSE) -> 3023637013 | E48: 3.1 | F48: =VLOOKUP(E48,Cad.RateioConsumo!$B$4:$Q$77,2,FALSE) -> Associação dos Moradores do Residencial Araçagy | G48: =VLOOKUP(E48,Cad.RateioConsumo!$B$4:$Q$9,5,FALSE) -> 3021142432 | H48: =VLOOKUP(E48,Cad.RateioConsumo!$B$4:$Q$9,7,FALSE) -> 205.36364 | I48: =VLOOKUP(E48,Cad.RateioConsumo!$B$4:$Q$9,11,FALSE) -> 0.0147 | J48: 11/2025 | K48: 45966 | L48: 45985 | M48: 100 | N48: 1.172 | O48: =M48*N48 -> 117.2 | P48: 156.81 | Q48: =N48 -> 1.172 | R48: =P48*Q48 -> 183.78132 | S48: 6.21 | T48: 0.23 | U48: 0.011709 | V48: 0.053971 | W48: =ROUND(0.84318/((1-U48-V48)*(1-T48)),4) -> 1.172
B49: =E49&J49 -> 3.211/2025 | C49: Usina 3 | D49: =VLOOKUP(C49,Cad.Usinas!$A$4:$B$6,2,FALSE) -> 3023637013 | E49: 3.2 | F49: =VLOOKUP(E49,Cad.RateioConsumo!$B$4:$Q$77,2,FALSE) -> Associação dos Moradores do Residencial Araçagy | G49: =VLOOKUP(E49,Cad.RateioConsumo!$B$4:$Q$9,5,FALSE) -> 3021149593 | H49: =VLOOKUP(E49,Cad.RateioConsumo!$B$4:$Q$9,7,FALSE) -> 734.33333 | I49: =VLOOKUP(E49,Cad.RateioConsumo!$B$4:$Q$9,11,FALSE) -> 0.0525 | J49: 11/2025 | K49: 45966 | L49: 45985 | M49: 1086.92 | N49: 1.172009 | O49: =M49*N49 -> 1273.88 | P49: 9.11 | Q49: =N49 -> 1.172009 | R49: =P49*Q49 -> 10.677002 | S49: 67.41 | T49: 0.23 | U49: 0.011709 | V49: 0.053971 | W49: =ROUND(0.84318/((1-U49-V49)*(1-T49)),4) -> 1.172
B50: =E50&J50 -> 3.311/2025 | C50: Usina 3 | D50: =VLOOKUP(C50,Cad.Usinas!$A$4:$B$6,2,FALSE) -> 3023637013 | E50: 3.3 | F50: =VLOOKUP(E50,Cad.RateioConsumo!$B$4:$Q$77,2,FALSE) -> Associação dos Moradores do Residencial Araçagy | G50: =VLOOKUP(E50,Cad.RateioConsumo!$B$4:$Q$9,5,FALSE) -> 3021150559 | H50: =VLOOKUP(E50,Cad.RateioConsumo!$B$4:$Q$9,7,FALSE) -> 2086.4545 | I50: =VLOOKUP(E50,Cad.RateioConsumo!$B$4:$Q$9,11,FALSE) -> 0.107 | J50: 11/2025 | K50: 45966 | L50: 45985 | M50: 1012.83 | N50: 1.172013 | O50: =M50*N50 -> 1187.0499 | P50: 1276.97 | Q50: =N50 -> 1.172013 | R50: =P50*Q50 -> 1496.6254 | S50: 62.83 | T50: 0.23 | U50: 0.011709 | V50: 0.053971 | W50: =ROUND(0.84318/((1-U50-V50)*(1-T50)),4) -> 1.172
B51: =E51&J51 -> 3.411/2025 | C51: Usina 3 | D51: =VLOOKUP(C51,Cad.Usinas!$A$4:$B$6,2,FALSE) -> 3023637013 | E51: 3.4 | F51: =VLOOKUP(E51,Cad.RateioConsumo!$B$4:$Q$77,2,FALSE) -> Antonio Jose Souza Filho | G51: =VLOOKUP(E51,Cad.RateioConsumo!$B$4:$Q$9,5,FALSE) -> 3007625048 | H51: =VLOOKUP(E51,Cad.RateioConsumo!$B$4:$Q$9,7,FALSE) -> 417.15385 | I51: =VLOOKUP(E51,Cad.RateioConsumo!$B$4:$Q$9,11,FALSE) -> 0.0298 | J51: 11/2025 | K51: 45967 | L51: 45985 | M51: 431.34 | N51: 1.171999 | O51: =M51*N51 -> 505.53005 | P51: 36.65 | Q51: =N51 -> 1.171999 | R51: =P51*Q51 -> 42.953763 | S51: 48 | T51: 0.23 | U51: 0.011709 | V51: 0.053971 | W51: =ROUND(0.84318/((1-U51-V51)*(1-T51)),4) -> 1.172
B52: =E52&J52 -> 3.511/2025 | C52: Usina 3 | D52: =VLOOKUP(C52,Cad.Usinas!$A$4:$B$6,2,FALSE) -> 3023637013 | E52: 3.5 | F52: =VLOOKUP(E52,Cad.RateioConsumo!$B$4:$Q$77,2,FALSE) -> João Carlos Pereira Dutra Filho | G52: =VLOOKUP(E52,Cad.RateioConsumo!$B$4:$Q$9,5,FALSE) -> 1163310 | H52: =VLOOKUP(E52,Cad.RateioConsumo!$B$4:$Q$9,7,FALSE) -> 848.69231 | I52: =VLOOKUP(E52,Cad.RateioConsumo!$B$4:$Q$9,11,FALSE) -> 0.0606 | J52: 11/2025 | K52: 45959 | L52: 45967 | M52: 899.47 | N52: 1.169722 | O52: =M52*N52 -> 1052.1298 | P52: 10.52 | Q52: =N52 -> 1.169722 | R52: =P52*Q52 -> 12.305475 | S52: 57.1 | T52: 0.23 | U52: 0.011385 | V52: 0.052488 | W52: =ROUND(0.84318/((1-U52-V52)*(1-T52)),4) -> 1.1698
B53: =E53&J53 -> 3.611/2025 | C53: Usina 3 | D53: =VLOOKUP(C53,Cad.Usinas!$A$4:$B$6,2,FALSE) -> 3023637013 | E53: 3.6 | F53: =VLOOKUP(E53,Cad.RateioConsumo!$B$4:$Q$77,2,FALSE) -> Patricia Maria Abreu Machado | G53: =VLOOKUP(E53,Cad.RateioConsumo!$B$4:$Q$9,5,FALSE) -> 3006793931 | H53: =VLOOKUP(E53,Cad.RateioConsumo!$B$4:$Q$9,7,FALSE) -> 776.76923 | I53: =VLOOKUP(E53,Cad.RateioConsumo!$B$4:$Q$9,11,FALSE) -> 0.0555 | J53: 11/2025 | K53: 28/10025 | L53: 45965 | M53: 850 | N53: 1.169741 | O53: =M53*N53 -> 994.27985 | P53: 0 | Q53: =N53 -> 1.169741 | R53: =P53*Q53 -> 0 | S53: 56.52 | T53: 0.23 | U53: 0.011385 | V53: 0.052488 | W53: =ROUND(0.84318/((1-U53-V53)*(1-T53)),4) -> 1.1698
B54: =E54&J54 -> 3.711/2025 | C54: Usina 3 | D54: =VLOOKUP(C54,Cad.Usinas!$A$4:$B$6,2,FALSE) -> 3023637013 | E54: 3.7 | F54: =VLOOKUP(E54,Cad.RateioConsumo!$B$4:$Q$77,2,FALSE) -> Fatima Abdel Hafiz Khalifa Cavalcanti | G54: =VLOOKUP(E54,Cad.RateioConsumo!$B$4:$Q$22,5,FALSE) -> 38398091 | H54: =VLOOKUP(E54,Cad.RateioConsumo!$B$4:$Q$22,7,FALSE) -> 1013.3846 | I54: =VLOOKUP(E54,Cad.RateioConsumo!$B$4:$Q$22,11,FALSE) -> 0.0724 | J54: 11/2025 | K54: 45980 | L54: 45997 | M54: 1243.42 | N54: 1.169745 | O54: =M54*N54 -> 1454.4843 | P54: 12.57 | Q54: =N54 -> 1.169745 | R54: =P54*Q54 -> 14.703695 | S54: 86.6 | T54: 0.23 | U54: 0.011709 | V54: 0.053971 | W54: =ROUND(0.84318/((1-U54-V54)*(1-T54)),4) -> 1.172
B55: =E55&J55 -> 3.011/2025 | C55: Usina 3 | D55: =VLOOKUP(C55,Cad.Usinas!$A$4:$B$6,2,FALSE) -> 3023637013 | E55: 3.0 | F55: =VLOOKUP(E55,Cad.RateioConsumo!$B$4:$Q$77,2,FALSE) -> Usina 3 | G55: =VLOOKUP(E55,Cad.RateioConsumo!$B$4:$Q$77,5,FALSE) -> 3023637013 | H55: =VLOOKUP(E55,Cad.RateioConsumo!$B$4:$Q$77,7,FALSE) -> 8931.2331 | I55: =VLOOKUP(E55,Cad.RateioConsumo!$B$4:$Q$77,11,FALSE) -> 0.6799 | J55: 11/2025 | M55: 0 | T55: 0.23 | U55: 0.011709 | V55: 0.053971 | W55: =ROUND(0.84318/((1-U55-V55)*(1-T55)),4) -> 1.172
B56: =E56&J56 -> 1.011/2025 | C56: Usina 1 | D56: =VLOOKUP(C56,Cad.Usinas!$A$4:$B$6,2,FALSE) -> 3023633492 | E56: 1.0 | F56: =VLOOKUP(E56,Cad.RateioConsumo!$B$4:$Q$77,2,FALSE) -> Usina 1 | G56: =VLOOKUP(E56,Cad.RateioConsumo!$B$4:$Q$77,5,FALSE) -> 3023633492 | H56: =VLOOKUP(E56,Cad.RateioConsumo!$B$4:$Q$77,7,FALSE) -> 14000 | I56: =VLOOKUP(E56,Cad.RateioConsumo!$B$4:$Q$77,11,FALSE) -> 0.3201 | J56: 11/2025 | M56: 0 | T56: 0.23 | U56: 0.011709 | V56: 0.053971 | W56: =ROUND(0.84318/((1-U56-V56)*(1-T56)),4) -> 1.172 | Y56: A Equatorial cobrou errado uma tarida de GD2 , gerando itens que não são devidos: 1)Benefício Tarifário Bruto SCEE R$ 961,08 e 2) (-) Benefício Tarifário Líquido SCEE 702,62. O saldo deste valor foi dado como desconto para não te afetar os 15% de desconto na conta até que a Equatorial reverter esse valor.
B57: =E57&J57 -> 2.111/2025 | C57: Usina 2 | D57: =VLOOKUP(C57,Cad.Usinas!$A$4:$B$6,2,FALSE) -> 3023594470 | E57: 2.1 | F57: =VLOOKUP(E57,Cad.RateioConsumo!$B$4:$Q$77,2,FALSE) -> Lucas Medeiros Lima | G57: =VLOOKUP(E57,Cad.RateioConsumo!$B$4:$Q$77,5,FALSE) -> 3002796782 | H57: =VLOOKUP(E57,Cad.RateioConsumo!$B$4:$Q$77,7,FALSE) -> 1536.5 | I57: =VLOOKUP(E57,Cad.RateioConsumo!$B$4:$Q$77,11,FALSE) -> 0.1098 | J57: 11/2025 | K57: 45972 | L57: 45979 | M57: 0 | P57: 1556 | Q57: =W57 -> 1.172 | R57: =P57*Q57 -> 1823.632 | S57: 1.86 | T57: 0.23 | U57: 0.011709 | V57: 0.053971 | W57: =ROUND(0.84318/((1-U57-V57)*(1-T57)),4) -> 1.172 | X57: =961.08-702.62 -> 258.46 | Y57: A Equatorial errou no faturamento e cobrou indevidamente uma tarifa adicional:1)Benefício Tarifário Bruto SCEE e 2) (-) Benefício Tarifário Líquido SCEE . O saldo deste valor foi dado como desconto para não te afetar os 15% de desconto na conta até que a Equatorial reverter esse valor.
B58: =E58&J58 -> 2.211/2025 | C58: Usina 2 | D58: =VLOOKUP(C58,Cad.Usinas!$A$4:$B$6,2,FALSE) -> 3023594470 | E58: 2.2 | F58: =VLOOKUP(E58,Cad.RateioConsumo!$B$4:$Q$77,2,FALSE) -> SORRISO SAUDE ODONTOLOGIA LTDA | G58: =VLOOKUP(E58,Cad.RateioConsumo!$B$4:$Q$77,5,FALSE) -> 3022893768 | H58: =VLOOKUP(E58,Cad.RateioConsumo!$B$4:$Q$77,7,FALSE) -> 859 | I58: =VLOOKUP(E58,Cad.RateioConsumo!$B$4:$Q$77,11,FALSE) -> 0.0614 | J58: 11/2025 | K58: 45968 | L58: 45978 | P58: 902 | Q58: =W58 -> 1.172 | R58: =P58*Q58 -> 1057.144 | S58: 6.21 | T58: 0.23 | U58: 0.011709 | V58: 0.053971 | W58: =ROUND(0.84318/((1-U58-V58)*(1-T58)),4) -> 1.172 | X58: =557.12-407.3 -> 149.82 | Y58: A Equatorial errou no faturamento e cobrou indevidamente uma tarifa adicional:1)Benefício Tarifário Bruto SCEE e 2) (-) Benefício Tarifário Líquido SCEE . O saldo deste valor foi dado como desconto para não te afetar os 15% de desconto na conta até que a Equatorial reverter esse valor.
B59: =E59&J59 -> 2.011/2025 | C59: Usina 2 | D59: =VLOOKUP(C59,Cad.Usinas!$A$4:$B$6,2,FALSE) -> 3023594470 | E59: 2.0 | F59: =VLOOKUP(E59,Cad.RateioConsumo!$B$4:$Q$77,2,FALSE) -> Usina 2 | G59: =VLOOKUP(E59,Cad.RateioConsumo!$B$4:$Q$77,5,FALSE) -> 3023594470 | H59: =VLOOKUP(E59,Cad.RateioConsumo!$B$4:$Q$77,7,FALSE) -> 14000 | I59: =VLOOKUP(E59,Cad.RateioConsumo!$B$4:$Q$77,11,FALSE) -> 1 | J59: 11/2025 | M59: 0 | P59: 0 | T59: 0.23 | U59: 0.011709 | V59: 0.053971 | W59: =ROUND(0.84318/((1-U59-V59)*(1-T59)),4) -> 1.172
B62: =E62&J62 -> 3.110/2025 | C62: Usina 3 | D62: =VLOOKUP(C62,Cad.Usinas!$A$4:$B$6,2,FALSE) -> 3023637013 | E62: 3.1 | F62: =VLOOKUP(E62,Cad.RateioConsumo!$B$4:$Q$77,2,FALSE) -> Associação dos Moradores do Residencial Araçagy | G62: =VLOOKUP(E62,Cad.RateioConsumo!$B$4:$Q$9,5,FALSE) -> 3021142432 | H62: =VLOOKUP(E62,Cad.RateioConsumo!$B$4:$Q$9,7,FALSE) -> 205.36364 | I62: =VLOOKUP(E62,Cad.RateioConsumo!$B$4:$Q$9,11,FALSE) -> 0.0147 | J62: 10/2025 | K62: 45933 | L62: 45954 | M62: 100 | N62: 1.1696 | O62: =M62*N62 -> 116.96 | P62: 123.85 | Q62: =N62 -> 1.1696 | R62: =P62*Q62 -> 144.85496 | S62: 10.44 | T62: 0.23 | U62: 0.011385 | V62: 0.052488 | W62: =ROUND(0.84318/((1-U62-V62)*(1-T62)),4) -> 1.1698 | X62: =W62-Q62 -> 0.0002
B63: =E63&J63 -> 3.210/2025 | C63: Usina 3 | D63: =VLOOKUP(C63,Cad.Usinas!$A$4:$B$6,2,FALSE) -> 3023637013 | E63: 3.2 | F63: =VLOOKUP(E63,Cad.RateioConsumo!$B$4:$Q$77,2,FALSE) -> Associação dos Moradores do Residencial Araçagy | G63: =VLOOKUP(E63,Cad.RateioConsumo!$B$4:$Q$9,5,FALSE) -> 3021149593 | H63: =VLOOKUP(E63,Cad.RateioConsumo!$B$4:$Q$9,7,FALSE) -> 734.33333 | I63: =VLOOKUP(E63,Cad.RateioConsumo!$B$4:$Q$9,11,FALSE) -> 0.0525 | J63: 10/2025 | K63: 45933 | L63: 45954 | M63: 165.2 | N63: 1.169673 | O63: =M63*N63 -> 193.22998 | P63: 857.74 | Q63: =N63 -> 1.169673 | R63: =P63*Q63 -> 1003.2753 | S63: 17.26 | T63: 0.23 | U63: 0.011385 | V63: 0.052488 | W63: =ROUND(0.84318/((1-U63-V63)*(1-T63)),4) -> 1.1698 | X63: =W63-Q63 -> 0.000127
B64: =E64&J64 -> 3.310/2025 | C64: Usina 3 | D64: =VLOOKUP(C64,Cad.Usinas!$A$4:$B$6,2,FALSE) -> 3023637013 | E64: 3.3 | F64: =VLOOKUP(E64,Cad.RateioConsumo!$B$4:$Q$77,2,FALSE) -> Associação dos Moradores do Residencial Araçagy | G64: =VLOOKUP(E64,Cad.RateioConsumo!$B$4:$Q$9,5,FALSE) -> 3021150559 | H64: =VLOOKUP(E64,Cad.RateioConsumo!$B$4:$Q$9,7,FALSE) -> 2086.4545 | I64: =VLOOKUP(E64,Cad.RateioConsumo!$B$4:$Q$9,11,FALSE) -> 0.107 | J64: 10/2025 | K64: 45933 | L64: 45954 | M64: 100 | N64: 1.1696 | O64: =M64*N64 -> 116.96 | P64: 1875.71 | Q64: =N64 -> 1.1696 | R64: =P64*Q64 -> 2193.8304 | S64: 10.44 | T64: 0.23 | U64: 0.011385 | V64: 0.052488 | W64: =ROUND(0.84318/((1-U64-V64)*(1-T64)),4) -> 1.1698 | X64: =W64-Q64 -> 0.0002
B65: =E65&J65 -> 3.410/2025 | C65: Usina 3 | D65: =VLOOKUP(C65,Cad.Usinas!$A$4:$B$6,2,FALSE) -> 3023637013 | E65: 3.4 | F65: =VLOOKUP(E65,Cad.RateioConsumo!$B$4:$Q$77,2,FALSE) -> Antonio Jose Souza Filho | G65: =VLOOKUP(E65,Cad.RateioConsumo!$B$4:$Q$9,5,FALSE) -> 3007625048 | H65: =VLOOKUP(E65,Cad.RateioConsumo!$B$4:$Q$9,7,FALSE) -> 417.15385 | I65: =VLOOKUP(E65,Cad.RateioConsumo!$B$4:$Q$9,11,FALSE) -> 0.0298 | J65: 10/2025 | K65: 45936 | L65: 45954 | M65: 30 | N65: 1.1696 | O65: =M65*N65 -> 35.088 | P65: 476 | Q65: =N65 -> 1.1696 | R65: =P65*Q65 -> 556.7296 | S65: 3 | T65: 0.23 | U65: 0.011385 | V65: 0.052488 | W65: =ROUND(0.84318/((1-U65-V65)*(1-T65)),4) -> 1.1698 | X65: =W65-Q65 -> 0.0002
B66: =E66&J66 -> 3.010/2025 | C66: Usina 3 | D66: =VLOOKUP(C66,Cad.Usinas!$A$4:$B$6,2,FALSE) -> 3023637013 | E66: 3.0 | F66: =VLOOKUP(E66,Cad.RateioConsumo!$B$4:$Q$77,2,FALSE) -> Usina 3 | G66: =VLOOKUP(E66,Cad.RateioConsumo!$B$4:$Q$77,5,FALSE) -> 3023637013 | H66: =VLOOKUP(E66,Cad.RateioConsumo!$B$4:$Q$77,7,FALSE) -> 8931.2331 | I66: =VLOOKUP(E66,Cad.RateioConsumo!$B$4:$Q$77,11,FALSE) -> 0.6799 | J66: 10/2025 | T66: 0.23 | U66: 0.011385 | V66: 0.052488 | W66: =ROUND(0.84318/((1-U66-V66)*(1-T66)),4) -> 1.1698
B67: =E67&J67 -> 1.010/2025 | C67: Usina 1 | D67: =VLOOKUP(C67,Cad.Usinas!$A$4:$B$6,2,FALSE) -> 3023633492 | E67: 1.0 | F67: =VLOOKUP(E67,Cad.RateioConsumo!$B$4:$Q$77,2,FALSE) -> Usina 1 | G67: =VLOOKUP(E67,Cad.RateioConsumo!$B$4:$Q$77,5,FALSE) -> 3023633492 | H67: =VLOOKUP(E67,Cad.RateioConsumo!$B$4:$Q$77,7,FALSE) -> 14000 | I67: =VLOOKUP(E67,Cad.RateioConsumo!$B$4:$Q$77,11,FALSE) -> 0.3201 | J67: 10/2025 | M67: 0 | T67: 0.23 | U67: 0.011385 | V67: 0.052488 | W67: =ROUND(0.84318/((1-U67-V67)*(1-T67)),4) -> 1.1698
B68: =E68&J68 -> 2.1 | C68: Usina 2 | D68: =VLOOKUP(C68,Cad.Usinas!$A$4:$B$6,2,FALSE) -> 3023594470 | E68: 2.1 | F68: =VLOOKUP(E68,Cad.RateioConsumo!$B$4:$Q$77,2,FALSE) -> Lucas Medeiros Lima | G68: =VLOOKUP(E68,Cad.RateioConsumo!$B$4:$Q$77,5,FALSE) -> 3002796782 | H68: =VLOOKUP(E68,Cad.RateioConsumo!$B$4:$Q$77,7,FALSE) -> 1536.5 | I68: =VLOOKUP(E68,Cad.RateioConsumo!$B$4:$Q$77,11,FALSE) -> 0.1098
B69: =E69&J69 -> 2.010/2025 | C69: Usina 2 | D69: =VLOOKUP(C69,Cad.Usinas!$A$4:$B$6,2,FALSE) -> 3023594470 | E69: 2.0 | F69: =VLOOKUP(E69,Cad.RateioConsumo!$B$4:$Q$77,2,FALSE) -> Usina 2 | G69: =VLOOKUP(E69,Cad.RateioConsumo!$B$4:$Q$77,5,FALSE) -> 3023594470 | H69: =VLOOKUP(E69,Cad.RateioConsumo!$B$4:$Q$77,7,FALSE) -> 14000 | I69: =VLOOKUP(E69,Cad.RateioConsumo!$B$4:$Q$77,11,FALSE) -> 1 | J69: 10/2025 | M69: 0 | P69: 0 | T69: 0.23 | U69: 0.011385 | V69: 0.052488 | W69: =ROUND(0.84318/((1-U69-V69)*(1-T69)),4) -> 1.1698
B71: =E71&J71 -> 3.109/2025 | C71: Usina 3 | D71: =VLOOKUP(C71,Cad.Usinas!$A$4:$B$6,2,FALSE) -> 3023637013 | E71: 3.1 | F71: =VLOOKUP(E71,Cad.RateioConsumo!$B$4:$Q$77,2,FALSE) -> Associação dos Moradores do Residencial Araçagy | G71: =VLOOKUP(E71,Cad.RateioConsumo!$B$4:$Q$9,5,FALSE) -> 3021142432 | H71: =VLOOKUP(E71,Cad.RateioConsumo!$B$4:$Q$9,7,FALSE) -> 205.36364 | I71: =VLOOKUP(E71,Cad.RateioConsumo!$B$4:$Q$9,11,FALSE) -> 0.0147 | J71: 09/2025 | K71: 45903 | L71: 45924 | M71: 100 | N71: 1.0037 | O71: =M71*N71 -> 100.37 | P71: 135.84 | Q71: =N71 -> 1.0037 | R71: =P71*Q71 -> 136.34261 | S71: 10.63 | T71: 0.23 | U71: 0.006932 | V71: 0.032011 | W71: =Q71 -> 1.0037 | X71: =W71-Q71 -> 0
B72: =E72&J72 -> 3.209/2025 | C72: Usina 3 | D72: =VLOOKUP(C72,Cad.Usinas!$A$4:$B$6,2,FALSE) -> 3023637013 | E72: 3.2 | F72: =VLOOKUP(E72,Cad.RateioConsumo!$B$4:$Q$77,2,FALSE) -> Associação dos Moradores do Residencial Araçagy | G72: =VLOOKUP(E72,Cad.RateioConsumo!$B$4:$Q$9,5,FALSE) -> 3021149593 | H72: =VLOOKUP(E72,Cad.RateioConsumo!$B$4:$Q$9,7,FALSE) -> 734.33333 | I72: =VLOOKUP(E72,Cad.RateioConsumo!$B$4:$Q$9,11,FALSE) -> 0.0525 | J72: 09/2025 | K72: 45903 | L72: 45924 | M72: 53.93 | N72: 1.003523 | O72: =M72*N72 -> 54.119995 | P72: 857.27 | Q72: =N72 -> 1.003523 | R72: =P72*Q72 -> 860.29016 | S72: 5.73 | T72: 0.23 | U72: 0.006932 | V72: 0.032011 | W72: =Q72 -> 1.003523 | X72: =W72-Q72 -> 0
B73: =E73&J73 -> 3.309/2025 | C73: Usina 3 | D73: =VLOOKUP(C73,Cad.Usinas!$A$4:$B$6,2,FALSE) -> 3023637013 | E73: 3.3 | F73: =VLOOKUP(E73,Cad.RateioConsumo!$B$4:$Q$77,2,FALSE) -> Associação dos Moradores do Residencial Araçagy | G73: =VLOOKUP(E73,Cad.RateioConsumo!$B$4:$Q$9,5,FALSE) -> 3021150559 | H73: =VLOOKUP(E73,Cad.RateioConsumo!$B$4:$Q$9,7,FALSE) -> 2086.4545 | I73: =VLOOKUP(E73,Cad.RateioConsumo!$B$4:$Q$9,11,FALSE) -> 0.107 | J73: 09/2025 | K73: 45903 | L73: 45924 | M73: 100 | N73: 1.0037 | O73: =M73*N73 -> 100.37 | P73: 1733.29 | Q73: =N73 -> 1.0037 | R73: =P73*Q73 -> 1739.7032 | S73: 10.63 | T73: 0.23 | U73: 0.006932 | V73: 0.032011 | W73: =Q73 -> 1.0037 | X73: =W73-Q73 -> 0
B74: =E74&J74 -> 3.409/2025 | C74: Usina 3 | D74: =VLOOKUP(C74,Cad.Usinas!$A$4:$B$6,2,FALSE) -> 3023637013 | E74: 3.4 | F74: =VLOOKUP(E74,Cad.RateioConsumo!$B$4:$Q$77,2,FALSE) -> Antonio Jose Souza Filho | G74: =VLOOKUP(E74,Cad.RateioConsumo!$B$4:$Q$9,5,FALSE) -> 3007625048 | H74: =VLOOKUP(E74,Cad.RateioConsumo!$B$4:$Q$9,7,FALSE) -> 417.15385 | I74: =VLOOKUP(E74,Cad.RateioConsumo!$B$4:$Q$9,11,FALSE) -> 0.0298 | J74: 09/2025 | K74: 45905 | L74: 45924 | M74: 30 | N74: 1.014333 | O74: =M74*N74 -> 30.42999 | P74: 466 | Q74: =N74 -> 1.014333 | R74: =P74*Q74 -> 472.67918 | S74: 3.19 | T74: 0.23 | U74: 0.006932 | V74: 0.032011 | W74: =Q74 -> 1.014333 | X74: =W74-Q74 -> 0
B75: =E75&J75 -> 3.509/2025 | C75: Usina 3 | D75: =VLOOKUP(C75,Cad.Usinas!$A$4:$B$6,2,FALSE) -> 3023637013 | E75: 3.5 | F75: =VLOOKUP(E75,Cad.RateioConsumo!$B$4:$Q$77,2,FALSE) -> João Carlos Pereira Dutra Filho | G75: =VLOOKUP(E75,Cad.RateioConsumo!$B$4:$Q$9,5,FALSE) -> 1163310 | H75: =VLOOKUP(E75,Cad.RateioConsumo!$B$4:$Q$9,7,FALSE) -> 848.69231 | I75: =VLOOKUP(E75,Cad.RateioConsumo!$B$4:$Q$9,11,FALSE) -> 0.0606 | J75: 09/2025 | T75: 0.23 | U75: 0.006932 | V75: 0.032011 | W75: =Q75 -> 0
B76: =E76&J76 -> 3.609/2025 | C76: Usina 3 | D76: =VLOOKUP(C76,Cad.Usinas!$A$4:$B$6,2,FALSE) -> 3023637013 | E76: 3.6 | F76: =VLOOKUP(E76,Cad.RateioConsumo!$B$4:$Q$77,2,FALSE) -> Patricia Maria Abreu Machado | G76: =VLOOKUP(E76,Cad.RateioConsumo!$B$4:$Q$9,5,FALSE) -> 3006793931 | H76: =VLOOKUP(E76,Cad.RateioConsumo!$B$4:$Q$9,7,FALSE) -> 776.76923 | I76: =VLOOKUP(E76,Cad.RateioConsumo!$B$4:$Q$9,11,FALSE) -> 0.0555 | J76: 09/2025 | T76: 0.23 | U76: 0.006932 | V76: 0.032011 | W76: =Q76 -> 0
B77: =E77&J77 -> 3.009/2025 | C77: Usina 3 | D77: =VLOOKUP(C77,Cad.Usinas!$A$4:$B$6,2,FALSE) -> 3023637013 | E77: 3.0 | F77: =VLOOKUP(E77,Cad.RateioConsumo!$B$4:$Q$77,2,FALSE) -> Usina 3 | G77: =VLOOKUP(E77,Cad.RateioConsumo!$B$4:$Q$77,5,FALSE) -> 3023637013 | H77: =VLOOKUP(E77,Cad.RateioConsumo!$B$4:$Q$77,7,FALSE) -> 8931.2331 | I77: =VLOOKUP(E77,Cad.RateioConsumo!$B$4:$Q$77,11,FALSE) -> 0.6799 | J77: 09/2025 | T77: 0.23 | U77: 0.006932 | V77: 0.032011 | W77: =Q77 -> 0
B78: =E78&J78 -> 3.008/2025 | C78: Usina 3 | D78: =VLOOKUP(C78,Cad.Usinas!$A$4:$B$6,2,FALSE) -> 3023637013 | E78: 3.0 | F78: =VLOOKUP(E78,Cad.RateioConsumo!$B$4:$Q$77,2,FALSE) -> Usina 3 | G78: =VLOOKUP(E78,Cad.RateioConsumo!$B$4:$Q$77,5,FALSE) -> 3023637013 | H78: =VLOOKUP(E78,Cad.RateioConsumo!$B$4:$Q$77,7,FALSE) -> 8931.2331 | I78: =VLOOKUP(E78,Cad.RateioConsumo!$B$4:$Q$77,11,FALSE) -> 0.6799 | J78: 08/2025
B79: =E79&J79 -> 3.007/2025 | C79: Usina 3 | D79: =VLOOKUP(C79,Cad.Usinas!$A$4:$B$6,2,FALSE) -> 3023637013 | E79: 3.0 | F79: =VLOOKUP(E79,Cad.RateioConsumo!$B$4:$Q$77,2,FALSE) -> Usina 3 | G79: =VLOOKUP(E79,Cad.RateioConsumo!$B$4:$Q$77,5,FALSE) -> 3023637013 | H79: =VLOOKUP(E79,Cad.RateioConsumo!$B$4:$Q$77,7,FALSE) -> 8931.2331 | I79: =VLOOKUP(E79,Cad.RateioConsumo!$B$4:$Q$77,11,FALSE) -> 0.6799 | J79: 07/2025
B81: =E81&J81 -> 1.009/2025 | C81: Usina 1 | D81: =VLOOKUP(C81,Cad.Usinas!$A$4:$B$6,2,FALSE) -> 3023633492 | E81: 1.0 | F81: =VLOOKUP(E81,Cad.RateioConsumo!$B$4:$Q$77,2,FALSE) -> Usina 1 | G81: =VLOOKUP(E81,Cad.RateioConsumo!$B$4:$Q$77,5,FALSE) -> 3023633492 | H81: =VLOOKUP(E81,Cad.RateioConsumo!$B$4:$Q$77,7,FALSE) -> 14000 | I81: =VLOOKUP(E81,Cad.RateioConsumo!$B$4:$Q$77,11,FALSE) -> 0.3201 | J81: 09/2025 | M81: 0
B82: =E82&J82 -> 1.008/2025 | C82: Usina 1 | D82: =VLOOKUP(C82,Cad.Usinas!$A$4:$B$6,2,FALSE) -> 3023633492 | E82: 1.0 | F82: =VLOOKUP(E82,Cad.RateioConsumo!$B$4:$Q$77,2,FALSE) -> Usina 1 | G82: =VLOOKUP(E82,Cad.RateioConsumo!$B$4:$Q$77,5,FALSE) -> 3023633492 | H82: =VLOOKUP(E82,Cad.RateioConsumo!$B$4:$Q$77,7,FALSE) -> 14000 | I82: =VLOOKUP(E82,Cad.RateioConsumo!$B$4:$Q$77,11,FALSE) -> 0.3201 | J82: 08/2025 | M82: 0
B83: =E83&J83 -> 1.007/2025 | C83: Usina 1 | D83: =VLOOKUP(C83,Cad.Usinas!$A$4:$B$6,2,FALSE) -> 3023633492 | E83: 1.0 | F83: =VLOOKUP(E83,Cad.RateioConsumo!$B$4:$Q$77,2,FALSE) -> Usina 1 | G83: =VLOOKUP(E83,Cad.RateioConsumo!$B$4:$Q$77,5,FALSE) -> 3023633492 | H83: =VLOOKUP(E83,Cad.RateioConsumo!$B$4:$Q$77,7,FALSE) -> 14000 | I83: =VLOOKUP(E83,Cad.RateioConsumo!$B$4:$Q$77,11,FALSE) -> 0.3201 | J83: 07/2025 | M83: 0
B85: =E85&J85 -> 2.009/2025 | C85: Usina 2 | D85: =VLOOKUP(C85,Cad.Usinas!$A$4:$B$6,2,FALSE) -> 3023594470 | E85: 2.0 | F85: =VLOOKUP(E85,Cad.RateioConsumo!$B$4:$Q$77,2,FALSE) -> Usina 2 | G85: =VLOOKUP(E85,Cad.RateioConsumo!$B$4:$Q$77,5,FALSE) -> 3023594470 | H85: =VLOOKUP(E85,Cad.RateioConsumo!$B$4:$Q$77,7,FALSE) -> 14000 | I85: =VLOOKUP(E85,Cad.RateioConsumo!$B$4:$Q$77,11,FALSE) -> 1 | J85: 09/2025 | M85: 0 | P85: 0
B86: =E86&J86 -> 2.008/2025 | C86: Usina 2 | D86: =VLOOKUP(C86,Cad.Usinas!$A$4:$B$6,2,FALSE) -> 3023594470 | E86: 2.0 | F86: =VLOOKUP(E86,Cad.RateioConsumo!$B$4:$Q$77,2,FALSE) -> Usina 2 | G86: =VLOOKUP(E86,Cad.RateioConsumo!$B$4:$Q$77,5,FALSE) -> 3023594470 | H86: =VLOOKUP(E86,Cad.RateioConsumo!$B$4:$Q$77,7,FALSE) -> 14000 | I86: =VLOOKUP(E86,Cad.RateioConsumo!$B$4:$Q$77,11,FALSE) -> 1 | J86: 08/2025 | M86: 0 | P86: 0
B87: =E87&J87 -> 2.007/2025 | C87: Usina 2 | D87: =VLOOKUP(C87,Cad.Usinas!$A$4:$B$6,2,FALSE) -> 3023594470 | E87: 2.0 | F87: =VLOOKUP(E87,Cad.RateioConsumo!$B$4:$Q$77,2,FALSE) -> Usina 2 | G87: =VLOOKUP(E87,Cad.RateioConsumo!$B$4:$Q$77,5,FALSE) -> 3023594470 | H87: =VLOOKUP(E87,Cad.RateioConsumo!$B$4:$Q$77,7,FALSE) -> 14000 | I87: =VLOOKUP(E87,Cad.RateioConsumo!$B$4:$Q$77,11,FALSE) -> 1 | J87: 07/2025 | M87: 0 | P87: 0
J105: TOTAL | X105: =X45-X58 -> -471.39

Sheet Medições
D1: Medição | E1: 1 | F1: 2 | G1: 3 | H1: 4 | I1: 5 | J1: 6 | K1: 7 | L1: 8 | M1: 9 | N1: 10 | O1: 11 | P1: 12 | Q1: 13 | R1: 14 | S1: 15 | T1: 16 | U1: 17 | V1: 18 | W1: 19 | X1: 20 | Y1: 21 | Z1: 22 | AA1: 23 | AB1: 24 | AC1: 25 | AD1: 26 | AE1: 27
Q2: C.Comopensado | R2: C.Comopensado | S2: Energia pela Equatorial | T2: Bandeira Tarifária | U2: Bandeira Tarifária | V2: Locação | W2: Economia | X2: Saldo de Geração | Y2: Saldo | Z2: Vencimento fatura | AA2: Economia Acumulada | AB2: Consumo Compensado Acumulado | AC2: Desconto | AD2: Ação | AG2: Desconto
B3: Consumo | C3: Geração | D3: Recibo | E3: Recibos | F3: Nome | G3: Conta Contrato | H3: Nome | I3: Consumidores | J3: Conta Contrato | K3: Referência Consumo | L3: Referência Geração | M3: Consumo Médio | N3: Percentual Rateio (%) | O3: Geração Proporcional | P3: Consumo | Q3: Consumo Compensado | R3: Tarifa | S3: Valor | T3: Tipo | U3: Valor | X3: Mês | Y3: Acumulado
B4: =H4&K4 -> 1.002/2026 | C4: =F4&L4 -> Usina 101/2026 | D4: =IF(J4=G4,0,1) -> 0 | E4: =IF(D4=0,"N/A",SUM($D4:D$83)) -> N/A | F4: Usina 1 | G4: =VLOOKUP(F4,Cad.Usinas!$A$4:$B$6,2,FALSE) -> 3023633492 | H4: 1.0 | I4: =VLOOKUP(H4,Cad.RateioConsumo!$B$4:$Z$106,2,FALSE) -> Usina 1 | J4: =VLOOKUP(H4,Cad.RateioConsumo!$B$4:$Z$106,5,FALSE) -> 3023633492 | K4: 02/2026 | L4: 01/2026 | M4: =VLOOKUP(H4,Cad.RateioConsumo!$B$4:$Z$106,7,FALSE) -> 14000 | N4: =ROUND(VLOOKUP(H4,Cad.RateioConsumo!$B$4:$Z$106,11,FALSE),4) -> 0.3201 | O4: =IFERROR(ROUND(VLOOKUP(C4,Hist.Geração!$A$4:$F$64,4,FALSE)*N4,2)," ") -> 3730.77 | P4: =IFERROR(VLOOKUP(B4,Hist.Consum!$B$5:$V$120,12,FALSE),"") -> 0 | Q4: =IFERROR(VLOOKUP(B4,Hist.Consum!$B$5:$V$120,15,FALSE),"") -> 0 | R4: =IFERROR(VLOOKUP(B4,Hist.Consum!$B$5:$W$120,22,FALSE),"") -> 0.8432 | S4: =IFERROR(Q4*R4,"") -> 0 | T4: =VLOOKUP(K4,Hist.BT!$A$4:$C$127,3,FALSE) -> Verde | U4: =IFERROR(ROUND(VLOOKUP(T4,Hist.BT!$G$3:$I$6,3,FALSE)*Q4,2),"") -> 0 | V4: =IFERROR(ROUND(SUM(S4+U4)*(1-AG4),2),"") -> 0 | W4: =S4+U4-V4 -> 0 | X4: =O4-Q4 -> 3730.77 | Y4: =SUMIF($J4:J$84,J4,$X4:X$84) -> 37788.77 | AB4: =SUMIF(J4:$J$84,J4,Q4:$Q$84) -> 0 | AC4: =IFERROR(VLOOKUP(B4,Hist.Consum!$B$5:$AD$120,23,FALSE),"") -> 0 | AE4: =IFERROR(VLOOKUP(B4,Hist.Consum!$B$5:$AD$120,24,FALSE),"") -> 0 | AG4: =VLOOKUP(H4,Cad.RateioConsumo!$B$4:$Z$106,8,FALSE) -> 0.15
B5: =H5&K5 -> 2.102/2026 | C5: =F5&L5 -> Usina 201/2026 | D5: =IF(J5=G5,0,1) -> 1 | E5: =IF(D5=0,"N/A",SUM($D5:D$83)) -> 49 | F5: Usina 2 | G5: =VLOOKUP(F5,Cad.Usinas!$A$4:$B$6,2,FALSE) -> 3023594470 | H5: 2.1 | I5: =VLOOKUP(H5,Cad.RateioConsumo!$B$4:$Z$106,2,FALSE) -> Lucas Medeiros Lima | J5: =VLOOKUP(H5,Cad.RateioConsumo!$B$4:$Z$106,5,FALSE) -> 3002796782 | K5: 02/2026 | L5: 01/2026 | M5: =VLOOKUP(H5,Cad.RateioConsumo!$B$4:$Z$106,7,FALSE) -> 1536.5 | N5: =ROUND(VLOOKUP(H5,Cad.RateioConsumo!$B$4:$Z$106,11,FALSE),4) -> 0.1098 | O5: =IFERROR(ROUND(VLOOKUP(C5,Hist.Geração!$A$4:$F$64,4,FALSE)*N5,2)," ") -> 1534.35 | P5: =IFERROR(VLOOKUP(B5,Hist.Consum!$B$5:$V$120,12,FALSE),"") -> 80 | Q5: =IFERROR(VLOOKUP(B5,Hist.Consum!$B$5:$V$120,15,FALSE),"") -> 499 | R5: =IFERROR(VLOOKUP(B5,Hist.Consum!$B$5:$W$120,22,FALSE),"") -> 0.8432 | S5: =IFERROR(Q5*R5,"") -> 420.7568 | T5: =VLOOKUP(K5,Hist.BT!$A$4:$C$127,3,FALSE) -> Verde | U5: =IFERROR(ROUND(VLOOKUP(T5,Hist.BT!$G$3:$I$6,3,FALSE)*Q5,2),"") -> 0 | V5: =IFERROR(ROUND(SUM(S5+U5)*(1-AG5),2),"") -> 357.64 | W5: =S5+U5-V5 -> 63.1168 | X5: =O5-Q5 -> 1035.35 | Y5: =SUMIF($J5:J$84,J5,$X5:X$84) -> #VALUE! | AC5: =IFERROR(VLOOKUP(B5,Hist.Consum!$B$5:$AD$120,23,FALSE),"") -> 175.78 | AD5: GD2 | AE5: =IFERROR(VLOOKUP(B5,Hist.Consum!$B$5:$AD$120,24,FALSE),"") -> A Equatorial errou no faturamento e cobrou indevidamente uma tarifa adicional:1)Benefício Tarifário Bruto SCEE e 2) (-) Benefício Tarifário Líquido SCEE . O saldo deste valor foi dado como desconto para não te afetar os 15% de desconto na conta até que a Equatorial reverter esse valor. | AG5: =VLOOKUP(H5,Cad.RateioConsumo!$B$4:$Z$106,8,FALSE) -> 0.15
B6: =H6&K6 -> 2.202/2026 | C6: =F6&L6 -> Usina 201/2026 | D6: =IF(J6=G6,0,1) -> 1 | E6: =IF(D6=0,"N/A",SUM($D6:D$83)) -> 48 | F6: Usina 2 | G6: =VLOOKUP(F6,Cad.Usinas!$A$4:$B$6,2,FALSE) -> 3023594470 | H6: 2.2 | I6: =VLOOKUP(H6,Cad.RateioConsumo!$B$4:$Z$106,2,FALSE) -> SORRISO SAUDE ODONTOLOGIA LTDA | J6: =VLOOKUP(H6,Cad.RateioConsumo!$B$4:$Z$106,5,FALSE) -> 3022893768 | K6: 02/2026 | L6: 01/2026 | M6: =VLOOKUP(H6,Cad.RateioConsumo!$B$4:$Z$106,7,FALSE) -> 859 | N6: =ROUND(VLOOKUP(H6,Cad.RateioConsumo!$B$4:$Z$106,11,FALSE),4) -> 0.0614 | O6: =IFERROR(ROUND(VLOOKUP(C6,Hist.Geração!$A$4:$F$64,4,FALSE)*N6,2)," ") -> 858 | P6: =IFERROR(VLOOKUP(B6,Hist.Consum!$B$5:$V$120,12,FALSE),"") | Q6: =IFERROR(VLOOKUP(B6,Hist.Consum!$B$5:$V$120,15,FALSE),"") | R6: =IFERROR(VLOOKUP(B6,Hist.Consum!$B$5:$W$120,22,FALSE),"") | S6: =IFERROR(Q6*R6,"") | T6: =VLOOKUP(K6,Hist.BT!$A$4:$C$127,3,FALSE) -> Verde | U6: =IFERROR(ROUND(VLOOKUP(T6,Hist.BT!$G$3:$I$6,3,FALSE)*Q6,2),"") | V6: =IFERROR(ROUND(SUM(S6+U6)*(1-AG6),2),"") | W6: =S6+U6-V6 -> #VALUE! | X6: =O6-Q6 -> #VALUE! | Y6: =SUMIF($J6:J$84,J6,$X6:X$84) -> #VALUE! | AC6: =IFERROR(VLOOKUP(B6,Hist.Consum!$B$5:$AD$120,23,FALSE),"") | AD6: GD2 | AE6: =IFERROR(VLOOKUP(B6,Hist.Consum!$B$5:$AD$120,24,FALSE),"") | AG6: =VLOOKUP(H6,Cad.RateioConsumo!$B$4:$Z$106,8,FALSE) -> 0.17
B7: =H7&K7 -> 2.302/2027 | C7: =F7&L7 -> Usina 201/2026 | D7: =IF(J7=G7,0,1) -> 1 | E7: =IF(D7=0,"N/A",SUM($D7:D$83)) -> 47 | F7: Usina 2 | G7: =VLOOKUP(F7,Cad.Usinas!$A$4:$B$6,2,FALSE) -> 3023594470 | H7: 2.3 | I7: =VLOOKUP(H7,Cad.RateioConsumo!$B$4:$Z$106,2,FALSE) -> José de Ribamar Aguiar Costa (Zeca) | J7: =VLOOKUP(H7,Cad.RateioConsumo!$B$4:$Z$106,5,FALSE) -> 3005806061 | K7: 02/2027 | L7: 01/2026 | M7: =VLOOKUP(H7,Cad.RateioConsumo!$B$4:$Z$106,7,FALSE) -> 172.38462 | N7: =ROUND(VLOOKUP(H7,Cad.RateioConsumo!$B$4:$Z$106,11,FALSE),4) -> 0.0123 | O7: =IFERROR(ROUND(VLOOKUP(C7,Hist.Geração!$A$4:$F$64,4,FALSE)*N7,2)," ") -> 171.88 | P7: =IFERROR(VLOOKUP(B7,Hist.Consum!$B$5:$V$120,12,FALSE),"") | Q7: =IFERROR(VLOOKUP(B7,Hist.Consum!$B$5:$V$120,15,FALSE),"") | R7: =IFERROR(VLOOKUP(B7,Hist.Consum!$B$5:$W$120,22,FALSE),"") | S7: =IFERROR(Q7*R7,"") | T7: =VLOOKUP(K7,Hist.BT!$A$4:$C$127,3,FALSE) -> #N/A | U7: =IFERROR(ROUND(VLOOKUP(T7,Hist.BT!$G$3:$I$6,3,FALSE)*Q7,2),"") | V7: =IFERROR(ROUND(SUM(S7+U7)*(1-AG7),2),"") | W7: =S7+U7-V7 -> #VALUE! | X7: =O7-Q7 -> #VALUE! | Y7: =SUMIF($J7:J$84,J7,$X7:X$84) -> #VALUE! | AC7: =IFERROR(VLOOKUP(B7,Hist.Consum!$B$5:$AD$120,23,FALSE),"") | AD7: GD3 | AE7: =IFERROR(VLOOKUP(B7,Hist.Consum!$B$5:$AD$120,24,FALSE),"") | AG7: =VLOOKUP(H7,Cad.RateioConsumo!$B$4:$Z$106,8,FALSE) -> 0.15
B8: =H8&K8 -> 2.402/2028 | C8: =F8&L8 -> Usina 201/2028 | D8: =IF(J8=G8,0,1) -> 1 | E8: =IF(D8=0,"N/A",SUM($D8:D$83)) -> 46 | F8: Usina 2 | G8: =VLOOKUP(F8,Cad.Usinas!$A$4:$B$6,2,FALSE) -> 3023594470 | H8: 2.4 | I8: =VLOOKUP(H8,Cad.RateioConsumo!$B$4:$Z$106,2,FALSE) -> Fernando Fonseca Diniz (Andre TVN) | J8: =VLOOKUP(H8,Cad.RateioConsumo!$B$4:$Z$106,5,FALSE) -> 3022544461 | K8: 02/2028 | L8: 01/2028 | M8: =VLOOKUP(H8,Cad.RateioConsumo!$B$4:$Z$106,7,FALSE) -> 241.125 | N8: =ROUND(VLOOKUP(H8,Cad.RateioConsumo!$B$4:$Z$106,11,FALSE),4) -> 0.0172 | O8: =IFERROR(ROUND(VLOOKUP(C8,Hist.Geração!$A$4:$F$64,4,FALSE)*N8,2)," ") | P8: =IFERROR(VLOOKUP(B8,Hist.Consum!$B$5:$V$120,12,FALSE),"") | Q8: =IFERROR(VLOOKUP(B8,Hist.Consum!$B$5:$V$120,15,FALSE),"") | R8: =IFERROR(VLOOKUP(B8,Hist.Consum!$B$5:$W$120,22,FALSE),"") | S8: =IFERROR(Q8*R8,"") | T8: =VLOOKUP(K8,Hist.BT!$A$4:$C$127,3,FALSE) -> #N/A | U8: =IFERROR(ROUND(VLOOKUP(T8,Hist.BT!$G$3:$I$6,3,FALSE)*Q8,2),"") | V8: =IFERROR(ROUND(SUM(S8+U8)*(1-AG8),2),"") | W8: =S8+U8-V8 -> #VALUE! | X8: =O8-Q8 -> #VALUE! | Y8: =SUMIF($J8:J$84,J8,$X8:X$84) -> #VALUE! | AC8: =IFERROR(VLOOKUP(B8,Hist.Consum!$B$5:$AD$120,23,FALSE),"") | AD8: GD4 | AE8: =IFERROR(VLOOKUP(B8,Hist.Consum!$B$5:$AD$120,24,FALSE),"") | AG8: =VLOOKUP(H8,Cad.RateioConsumo!$B$4:$Z$106,8,FALSE) -> 0.15
B9: =H9&K9 -> 2.002/2026 | C9: =F9&L9 -> Usina 201/2026 | D9: =IF(J9=G9,0,1) -> 0 | E9: =IF(D9=0,"N/A",SUM($D9:D$83)) -> N/A | F9: Usina 2 | G9: =VLOOKUP(F9,Cad.Usinas!$A$4:$B$6,2,FALSE) -> 3023594470 | H9: 2.0 | I9: =VLOOKUP(H9,Cad.RateioConsumo!$B$4:$Z$106,2,FALSE) -> Usina 2 | J9: =VLOOKUP(H9,Cad.RateioConsumo!$B$4:$Z$106,5,FALSE) -> 3023594470 | K9: 02/2026 | L9: 01/2026 | M9: =VLOOKUP(H9,Cad.RateioConsumo!$B$4:$Z$106,7,FALSE) -> 14000 | N9: =VLOOKUP(H9,Cad.RateioConsumo!$B$4:$Z$106,11,FALSE) -> 1 | O9: =IFERROR(ROUND(VLOOKUP(C9,Hist.Geração!$A$4:$F$64,4,FALSE)*N9,2)," ") -> 13974 | P9: =IFERROR(VLOOKUP(B9,Hist.Consum!$B$5:$V$120,12,FALSE),"") -> 0 | Q9: =IFERROR(VLOOKUP(B9,Hist.Consum!$B$5:$V$120,15,FALSE),"") -> 0 | R9: =IFERROR(VLOOKUP(B9,Hist.Consum!$B$5:$W$120,22,FALSE),"") -> 0.8432 | S9: =IFERROR(Q9*R9,"") -> 0 | T9: =VLOOKUP(K9,Hist.BT!$A$4:$C$127,3,FALSE) -> Verde | U9: =IFERROR(ROUND(VLOOKUP(T9,Hist.BT!$G$3:$I$6,3,FALSE)*Q9,2),"") -> 0 | V9: =IFERROR(ROUND(SUM(S9+U9)*(1-AG9),2),"") -> 0 | W9: =S9+U9-V9 -> 0 | X9: =O9-Q9 -> 13974 | Y9: =SUMIF($J9:J$84,J9,$X9:X$84) -> 125336 | AB9: =SUMIF($J9:J$84,J9,$Q9:Q$84) -> 0 | AC9: =IFERROR(VLOOKUP(B9,Hist.Consum!$B$5:$AD$120,23,FALSE),"") -> 0 | AG9: =VLOOKUP(H9,Cad.RateioConsumo!$B$4:$Z$106,8,FALSE) -> 0.15
B10: =H10&K10 -> 3.102/2026 | C10: =F10&L10 -> Usina 301/2026 | D10: =IF(J10=G10,0,1) -> 1 | E10: =IF(D10=0,"N/A",SUM($D10:D$83)) -> 45 | F10: Usina 3 | G10: =VLOOKUP(F10,Cad.Usinas!$A$4:$B$6,2,FALSE) -> 3023637013 | H10: 3.1 | I10: =VLOOKUP(H10,Cad.RateioConsumo!$B$4:$Z$106,2,FALSE) -> Associação dos Moradores do Residencial Araçagy | J10: =VLOOKUP(H10,Cad.RateioConsumo!$B$4:$Z$106,5,FALSE) -> 3021142432 | K10: 02/2026 | L10: 01/2026 | M10: =VLOOKUP(H10,Cad.RateioConsumo!$B$4:$Z$106,7,FALSE) -> 205.36364 | N10: =ROUND(VLOOKUP(H10,Cad.RateioConsumo!$B$4:$Z$106,11,FALSE),4) -> 0.0147 | O10: =IFERROR(ROUND(VLOOKUP(C10,Hist.Geração!$A$4:$F$64,4,FALSE)*N10,2)," ") -> 204.15 | P10: =IFERROR(VLOOKUP(B10,Hist.Consum!$B$5:$V$120,12,FALSE),"") -> 100 | Q10: =IFERROR(VLOOKUP(B10,Hist.Consum!$B$5:$V$120,15,FALSE),"") -> 108.87 | R10: =IFERROR(VLOOKUP(B10,Hist.Consum!$B$5:$W$120,22,FALSE),"") -> 1.1286 | S10: =IFERROR(Q10*R10,"") -> 122.87068 | T10: =VLOOKUP(K10,Hist.BT!$A$4:$C$127,3,FALSE) -> Verde | U10: =IFERROR(ROUND(VLOOKUP(T10,Hist.BT!$G$3:$I$6,3,FALSE)*Q10,2),"") -> 0 | V10: =IFERROR(ROUND(SUM(S10+U10)*(1-AG10),2),"") -> 104.44 | W10: =S10+U10-V10 -> 18.430682 | X10: =O10-Q10 -> 95.28 | Y10: =SUMIF($J10:J$84,J10,$X10:X$84) -> 366.59 | Z10: =Y10/M10 -> 1.7850775 | AB10: =SUMIF($J10:J$84,J10,$Q10:Q$84) -> 761.09 | AC10: =IFERROR(VLOOKUP(B10,Hist.Consum!$B$5:$AD$120,23,FALSE),"") -> 0 | AD10: Reduzir Percentual | AG10: =VLOOKUP(H10,Cad.RateioConsumo!$B$4:$Z$106,8,FALSE) -> 0.15
B11: =H11&K11 -> 3.202/2026 | C11: =F11&L11 -> Usina 301/2026 | D11: =IF(J11=G11,0,1) -> 1 | E11: =IF(D11=0,"N/A",SUM($D11:D$83)) -> 44 | F11: Usina 3 | G11: =VLOOKUP(F11,Cad.Usinas!$A$4:$B$6,2,FALSE) -> 3023637013 | H11: 3.2 | I11: =VLOOKUP(H11,Cad.RateioConsumo!$B$4:$Z$106,2,FALSE) -> Associação dos Moradores do Residencial Araçagy | J11: =VLOOKUP(H11,Cad.RateioConsumo!$B$4:$Z$106,5,FALSE) -> 3021149593 | K11: 02/2026 | L11: 01/2026 | M11: =VLOOKUP(H11,Cad.RateioConsumo!$B$4:$Z$106,7,FALSE) -> 734.33333 | N11: =ROUND(VLOOKUP(H11,Cad.RateioConsumo!$B$4:$Z$106,11,FALSE),4) -> 0.0525 | O11: =IFERROR(ROUND(VLOOKUP(C11,Hist.Geração!$A$4:$F$64,4,FALSE)*N11,2)," ") -> 729.12 | P11: =IFERROR(VLOOKUP(B11,Hist.Consum!$B$5:$V$120,12,FALSE),"") -> 219.41 | Q11: =IFERROR(VLOOKUP(B11,Hist.Consum!$B$5:$V$120,15,FALSE),"") -> 818.35 | R11: =IFERROR(VLOOKUP(B11,Hist.Consum!$B$5:$W$120,22,FALSE),"") -> 1.1286 | S11: =IFERROR(Q11*R11,"") -> 923.58981 | T11: =VLOOKUP(K11,Hist.BT!$A$4:$C$127,3,FALSE) -> Verde | U11: =IFERROR(ROUND(VLOOKUP(T11,Hist.BT!$G$3:$I$6,3,FALSE)*Q11,2),"") -> 0 | V11: =IFERROR(ROUND(SUM(S11+U11)*(1-AG11),2),"") -> 785.05 | W11: =S11+U11-V11 -> 138.53981 | X11: =O11-Q11 -> -89.23 | Y11: =SUMIF($J11:J$84,J11,$X11:X$84) -> 0.03 | AB11: =SUMIF($J11:J$84,J11,$Q11:Q$84) -> 4027.39 | AC11: =IFERROR(VLOOKUP(B11,Hist.Consum!$B$5:$AD$120,23,FALSE),"") -> 0 | AG11: =VLOOKUP(H11,Cad.RateioConsumo!$B$4:$Z$106,8,FALSE) -> 0.15
B12: =H12&K12 -> 3.302/2026 | C12: =F12&L12 -> Usina 301/2026 | D12: =IF(J12=G12,0,1) -> 1 | E12: =IF(D12=0,"N/A",SUM($D12:D$83)) -> 43 | F12: Usina 3 | G12: =VLOOKUP(F12,Cad.Usinas!$A$4:$B$6,2,FALSE) -> 3023637013 | H12: 3.3 | I12: =VLOOKUP(H12,Cad.RateioConsumo!$B$4:$Z$106,2,FALSE) -> Associação dos Moradores do Residencial Araçagy | J12: =VLOOKUP(H12,Cad.RateioConsumo!$B$4:$Z$106,5,FALSE) -> 3021150559 | K12: 02/2026 | L12: 01/2026 | M12: =VLOOKUP(H12,Cad.RateioConsumo!$B$4:$Z$106,7,FALSE) -> 2086.4545 | N12: =ROUND(VLOOKUP(H12,Cad.RateioConsumo!$B$4:$Z$106,11,FALSE),4) -> 0.107 | O12: =IFERROR(ROUND(VLOOKUP(C12,Hist.Geração!$A$4:$F$64,4,FALSE)*N12,2)," ") -> 1486.02 | P12: =IFERROR(VLOOKUP(B12,Hist.Consum!$B$5:$V$120,12,FALSE),"") -> 309.27 | Q12: =IFERROR(VLOOKUP(B12,Hist.Consum!$B$5:$V$120,15,FALSE),"") -> 1487.4 | R12: =IFERROR(VLOOKUP(B12,Hist.Consum!$B$5:$W$120,22,FALSE),"") -> 1.1286 | S12: =IFERROR(Q12*R12,"") -> 1678.6796 | T12: =VLOOKUP(K12,Hist.BT!$A$4:$C$127,3,FALSE) -> Verde | U12: =IFERROR(ROUND(VLOOKUP(T12,Hist.BT!$G$3:$I$6,3,FALSE)*Q12,2),"") -> 0 | V12: =IFERROR(ROUND(SUM(S12+U12)*(1-AG12),2),"") -> 1426.88 | W12: =S12+U12-V12 -> 251.79964 | X12: =O12-Q12 -> -1.38 | Y12: =SUMIF($J12:J$84,J12,$X12:X$84) -> -4.35 | AB12: =SUMIF($J12:J$84,J12,$Q12:Q$84) -> 9584.64 | AC12: =IFERROR(VLOOKUP(B12,Hist.Consum!$B$5:$AD$120,23,FALSE),"") -> 0 | AD12: Aumentar Percentual | AG12: =VLOOKUP(H12,Cad.RateioConsumo!$B$4:$Z$106,8,FALSE) -> 0.15
B13: =H13&K13 -> 3.402/2026 | C13: =F13&L13 -> Usina 301/2026 | D13: =IF(J13=G13,0,1) -> 1 | E13: =IF(D13=0,"N/A",SUM($D13:D$83)) -> 42 | F13: Usina 3 | G13: =VLOOKUP(F13,Cad.Usinas!$A$4:$B$6,2,FALSE) -> 3023637013 | H13: 3.4 | I13: =VLOOKUP(H13,Cad.RateioConsumo!$B$4:$Z$106,2,FALSE) -> Antonio Jose Souza Filho | J13: =VLOOKUP(H13,Cad.RateioConsumo!$B$4:$Z$106,5,FALSE) -> 3007625048 | K13: 02/2026 | L13: 01/2026 | M13: =VLOOKUP(H13,Cad.RateioConsumo!$B$4:$Z$106,7,FALSE) -> 417.15385 | N13: =ROUND(VLOOKUP(H13,Cad.RateioConsumo!$B$4:$Z$106,11,FALSE),4) -> 0.0298 | O13: =IFERROR(ROUND(VLOOKUP(C13,Hist.Geração!$A$4:$F$64,4,FALSE)*N13,2)," ") -> 413.86 | P13: =IFERROR(VLOOKUP(B13,Hist.Consum!$B$5:$V$120,12,FALSE),"") -> 79.13 | Q13: =IFERROR(VLOOKUP(B13,Hist.Consum!$B$5:$V$120,15,FALSE),"") -> 413.86 | R13: =IFERROR(VLOOKUP(B13,Hist.Consum!$B$5:$W$120,22,FALSE),"") -> 1.1286 | S13: =IFERROR(Q13*R13,"") -> 467.0824 | T13: =VLOOKUP(K13,Hist.BT!$A$4:$C$127,3,FALSE) -> Verde | U13: =IFERROR(ROUND(VLOOKUP(T13,Hist.BT!$G$3:$I$6,3,FALSE)*Q13,2),"") -> 0 | V13: =IFERROR(ROUND(SUM(S13+U13)*(1-AG13),2),"") -> 397.02 | W13: =S13+U13-V13 -> 70.062396 | X13: =O13-Q13 -> 0 | Y13: =SUMIF($J13:J$84,J13,$X13:X$84) -> 8.5265128e-14 | AB13: =SUMIF($J13:J$84,J13,$Q13:Q$84) -> 2286.03 | AC13: =IFERROR(VLOOKUP(B13,Hist.Consum!$B$5:$AD$120,23,FALSE),"") -> 0 | AG13: =VLOOKUP(H13,Cad.RateioConsumo!$B$4:$Z$106,8,FALSE) -> 0.15
B14: =H14&K14 -> 3.501/2026 | C14: =F14&L14 -> Usina 312/2025 | D14: =IF(J14=G14,0,1) -> 1 | E14: =IF(D14=0,"N/A",SUM($D14:D$83)) -> 41 | F14: Usina 3 | G14: =VLOOKUP(F14,Cad.Usinas!$A$4:$B$6,2,FALSE) -> 3023637013 | H14: 3.5 | I14: =VLOOKUP(H14,Cad.RateioConsumo!$B$4:$Z$106,2,FALSE) -> João Carlos Pereira Dutra Filho | J14: =VLOOKUP(H14,Cad.RateioConsumo!$B$4:$Z$106,5,FALSE) -> 1163310 | K14: 01/2026 | L14: 12/2025 | M14: =VLOOKUP(H14,Cad.RateioConsumo!$B$4:$Z$106,7,FALSE) -> 848.69231 | N14: =ROUND(VLOOKUP(H14,Cad.RateioConsumo!$B$4:$Z$106,11,FALSE),4) -> 0.0606 | O14: =IFERROR(ROUND(VLOOKUP(C14,Hist.Geração!$A$4:$F$64,4,FALSE)*N14,2)," ") -> 865.13 | P14: =IFERROR(VLOOKUP(B14,Hist.Consum!$B$5:$V$120,12,FALSE),"") -> 30 | Q14: =IFERROR(VLOOKUP(B14,Hist.Consum!$B$5:$V$120,15,FALSE),"") -> 937 | R14: =IFERROR(VLOOKUP(B14,Hist.Consum!$B$5:$W$120,22,FALSE),"") -> 1.1286 | S14: =IFERROR(Q14*R14,"") -> 1057.4982 | T14: =VLOOKUP(K14,Hist.BT!$A$4:$C$127,3,FALSE) -> Verde | U14: =IFERROR(ROUND(VLOOKUP(T14,Hist.BT!$G$3:$I$6,3,FALSE)*Q14,2),"") -> 0 | V14: =IFERROR(ROUND(SUM(S14+U14)*(1-AG14),2),"") -> 898.87 | W14: =S14+U14-V14 -> 158.6282 | X14: =O14-Q14 -> -71.87 | Y14: =SUMIF(J4:$J$84,J14,X4:$X$84) -> 16.04 | AB14: =SUMIF(J4:$J$84,J14,Q4:$Q$84) -> 1811.52 | AC14: =IFERROR(VLOOKUP(B14,Hist.Consum!$B$5:$AD$120,23,FALSE),"") -> 0 | AD14: =IF((Y14/M14)>1,"Mudar Urgente",IF((Y14/M14)>0.4,"Rever Rateio",("ok"))) -> ok | AG14: =VLOOKUP(H14,Cad.RateioConsumo!$B$4:$Z$106,8,FALSE) -> 0.15
B15: =H15&K15 -> 3.801/2026 | C15: =F15&L15 -> Usina 312/2025 | D15: =IF(J15=G15,0,1) -> 1 | E15: =IF(D15=0,"N/A",SUM($D15:D$83)) -> 40 | F15: Usina 3 | G15: =VLOOKUP(F15,Cad.Usinas!$A$4:$B$6,2,FALSE) -> 3023637013 | H15: 3.8 | I15: =VLOOKUP(H15,Cad.RateioConsumo!$B$4:$Z$106,2,FALSE) -> Ana Maria Marques De Brito | J15: =VLOOKUP(H15,Cad.RateioConsumo!$B$4:$Z$106,5,FALSE) -> 3020257082 | K15: 01/2026 | L15: 12/2025 | M15: =VLOOKUP(H15,Cad.RateioConsumo!$B$4:$Z$106,7,FALSE) -> 1193 | N15: =ROUND(VLOOKUP(H15,Cad.RateioConsumo!$B$4:$Z$106,11,FALSE),4) -> 0.0852 | O15: =IFERROR(ROUND(VLOOKUP(C15,Hist.Geração!$A$4:$F$64,4,FALSE)*N15,2)," ") -> 1216.32 | P15: =IFERROR(VLOOKUP(B15,Hist.Consum!$B$5:$V$120,12,FALSE),"") -> 1225 | Q15: =IFERROR(VLOOKUP(B15,Hist.Consum!$B$5:$V$120,15,FALSE),"") -> 0 | R15: =IFERROR(VLOOKUP(B15,Hist.Consum!$B$5:$W$120,22,FALSE),"") -> 1.1284 | S15: =IFERROR(Q15*R15,"") -> 0 | T15: =VLOOKUP(K15,Hist.BT!$A$4:$C$127,3,FALSE) -> Verde | U15: =IFERROR(ROUND(VLOOKUP(T15,Hist.BT!$G$3:$I$6,3,FALSE)*Q15,2),"") -> 0 | V15: =IFERROR(ROUND(SUM(S15+U15)*(1-AG15),2),"") -> 0 | W15: =S15+U15-V15 -> 0 | X15: =O15-Q15 -> 1216.32 | Y15: =SUMIF(J5:$J$84,J15,X5:$X$84) -> 1216.32 | AB15: =SUMIF(J5:$J$84,J15,Q5:$Q$84) -> 0 | AC15: =IFERROR(VLOOKUP(B15,Hist.Consum!$B$5:$AD$120,23,FALSE),"") -> 5.7e-05 | AD15: =IF((Y15/M15)>1,"Mudar Urgente",IF((Y15/M15)>0.4,"Rever Rateio",("ok"))) -> Mudar Urgente | AG15: =VLOOKUP(H15,Cad.RateioConsumo!$B$4:$Z$106,8,FALSE) -> 0.15
B16: =H16&K16 -> 3.601/2026 | C16: =F16&L16 -> Usina 312/2025 | D16: =IF(J16=G16,0,1) -> 1 | E16: =IF(D16=0,"N/A",SUM($D16:D$83)) -> 39 | F16: Usina 3 | G16: =VLOOKUP(F16,Cad.Usinas!$A$4:$B$6,2,FALSE) -> 3023637013 | H16: 3.6 | I16: =VLOOKUP(H16,Cad.RateioConsumo!$B$4:$Z$106,2,FALSE) -> Patricia Maria Abreu Machado | J16: =VLOOKUP(H16,Cad.RateioConsumo!$B$4:$Z$106,5,FALSE) -> 3006793931 | K16: 01/2026 | L16: 12/2025 | M16: =VLOOKUP(H16,Cad.RateioConsumo!$B$4:$Z$106,7,FALSE) -> 776.76923 | N16: =ROUND(VLOOKUP(H16,Cad.RateioConsumo!$B$4:$Z$106,11,FALSE),4) -> 0.0555 | O16: =IFERROR(ROUND(VLOOKUP(C16,Hist.Geração!$A$4:$F$64,4,FALSE)*N16,2)," ") -> 792.32 | P16: =IFERROR(VLOOKUP(B16,Hist.Consum!$B$5:$V$120,12,FALSE),"") -> 100 | Q16: =IFERROR(VLOOKUP(B16,Hist.Consum!$B$5:$V$120,15,FALSE),"") -> 713 | R16: =IFERROR(VLOOKUP(B16,Hist.Consum!$B$5:$W$120,22,FALSE),"") -> 1.1286 | S16: =IFERROR(Q16*R16,"") -> 804.6918 | T16: =VLOOKUP(K16,Hist.BT!$A$4:$C$127,3,FALSE) -> Verde | U16: =IFERROR(ROUND(VLOOKUP(T16,Hist.BT!$G$3:$I$6,3,FALSE)*Q16,2),"") -> 0 | V16: =IFERROR(ROUND(SUM(S16+U16)*(1-AG16),2),"") -> 683.99 | W16: =S16+U16-V16 -> 120.7018 | X16: =O16-Q16 -> 79.32 | Y16: =SUMIF(J5:$J$84,J16,X5:$X$84) -> 158.64 | AG16: =VLOOKUP(H16,Cad.RateioConsumo!$B$4:$Z$106,8,FALSE) -> 0.15
B17: =H17&K17 -> 3.701/2026 | C17: =F17&L17 -> Usina 312/2025 | D17: =IF(J17=G17,0,1) -> 1 | E17: =IF(D17=0,"N/A",SUM($D17:D$83)) -> 38 | F17: Usina 3 | G17: =VLOOKUP(F17,Cad.Usinas!$A$4:$B$6,2,FALSE) -> 3023637013 | H17: 3.7 | I17: =VLOOKUP(H17,Cad.RateioConsumo!$B$4:$Z$106,2,FALSE) -> Fatima Abdel Hafiz Khalifa Cavalcanti | J17: =VLOOKUP(H17,Cad.RateioConsumo!$B$4:$Z$106,5,FALSE) -> 38398091 | K17: 01/2026 | L17: 12/2025 | M17: =VLOOKUP(H17,Cad.RateioConsumo!$B$4:$Z$106,7,FALSE) -> 1013.3846 | N17: =ROUND(VLOOKUP(H17,Cad.RateioConsumo!$B$4:$Z$106,11,FALSE),4) -> 0.0724 | O17: =IFERROR(ROUND(VLOOKUP(C17,Hist.Geração!$A$4:$F$64,4,FALSE)*N17,2)," ") -> 1033.58 | P17: =IFERROR(VLOOKUP(B17,Hist.Consum!$B$5:$V$120,12,FALSE),"") -> 169.15 | Q17: =IFERROR(VLOOKUP(B17,Hist.Consum!$B$5:$V$120,15,FALSE),"") -> 1074.84 | R17: =IFERROR(VLOOKUP(B17,Hist.Consum!$B$5:$W$120,22,FALSE),"") -> 1.1284 | S17: =IFERROR(Q17*R17,"") -> 1212.8495 | T17: =VLOOKUP(K17,Hist.BT!$A$4:$C$127,3,FALSE) -> Verde | U17: =IFERROR(ROUND(VLOOKUP(T17,Hist.BT!$G$3:$I$6,3,FALSE)*Q17,2),"") -> 0 | V17: =IFERROR(ROUND(SUM(S17+U17)*(1-AG17),2),"") -> 1030.92 | W17: =S17+U17-V17 -> 181.92946 | X17: =O17-Q17 -> -41.26 | Y17: =SUMIF(J6:$J$84,J17,X6:$X$84) -> 0.01 | AB17: =SUMIF($J17:J$84,J17,$Q17:Q$84) -> 2183.41 | AC17: =IFERROR(VLOOKUP(B17,Hist.Consum!$B$5:$AD$120,23,FALSE),"") -> 5.2e-05 | AD17: =IF((Y17/M17)>1,"Mudar Urgente",IF((Y17/M17)>0.4,"Rever Rateio",("ok"))) -> ok | AG17: =VLOOKUP(H17,Cad.RateioConsumo!$B$4:$Z$106,8,FALSE) -> 0.15
B18: =H18&K18 -> 3.601/2026 | C18: =F18&L18 -> Usina 312/2025 | D18: =IF(J18=G18,0,1) -> 1 | E18: =IF(D18=0,"N/A",SUM($D18:D$83)) -> 37 | F18: Usina 3 | G18: =VLOOKUP(F18,Cad.Usinas!$A$4:$B$6,2,FALSE) -> 3023637013 | H18: 3.6 | I18: =VLOOKUP(H18,Cad.RateioConsumo!$B$4:$Z$106,2,FALSE) -> Patricia Maria Abreu Machado | J18: =VLOOKUP(H18,Cad.RateioConsumo!$B$4:$Z$106,5,FALSE) -> 3006793931 | K18: 01/2026 | L18: 12/2025 | M18: =VLOOKUP(H18,Cad.RateioConsumo!$B$4:$Z$106,7,FALSE) -> 776.76923 | N18: =ROUND(VLOOKUP(H18,Cad.RateioConsumo!$B$4:$Z$106,11,FALSE),4) -> 0.0555 | O18: =IFERROR(ROUND(VLOOKUP(C18,Hist.Geração!$A$4:$F$64,4,FALSE)*N18,2)," ") -> 792.32 | P18: =IFERROR(VLOOKUP(B18,Hist.Consum!$B$5:$V$120,12,FALSE),"") -> 100 | Q18: =IFERROR(VLOOKUP(B18,Hist.Consum!$B$5:$V$120,15,FALSE),"") -> 713 | R18: =IFERROR(VLOOKUP(B18,Hist.Consum!$B$5:$W$120,22,FALSE),"") -> 1.1286 | S18: =IFERROR(Q18*R18,"") -> 804.6918 | T18: =VLOOKUP(K18,Hist.BT!$A$4:$C$127,3,FALSE) -> Verde | U18: =IFERROR(ROUND(VLOOKUP(T18,Hist.BT!$G$3:$I$6,3,FALSE)*Q18,2),"") -> 0 | V18: =IFERROR(ROUND(SUM(S18+U18)*(1-AG18),2),"") -> 683.99 | W18: =S18+U18-V18 -> 120.7018 | X18: =O18-Q18 -> 79.32 | Y18: =SUMIF(J9:$J$84,J18,X9:$X$84) -> 158.64 | AG18: =VLOOKUP(H18,Cad.RateioConsumo!$B$4:$Z$106,8,FALSE) -> 0.15
B19: =H19&K19 -> 3.002/2026 | C19: =F19&L19 -> Usina 301/2026 | D19: =IF(J19=G19,0,1) -> 0 | E19: =IF(D19=0,"N/A",SUM($D19:D$83)) -> N/A | F19: Usina 3 | G19: =VLOOKUP(F19,Cad.Usinas!$A$4:$B$6,2,FALSE) -> 3023637013 | H19: 3.0 | I19: =VLOOKUP(H19,Cad.RateioConsumo!$B$4:$Z$106,2,FALSE) -> Usina 3 | J19: =VLOOKUP(H19,Cad.RateioConsumo!$B$4:$Z$106,5,FALSE) -> 3023637013 | K19: 02/2026 | L19: 01/2026 | M19: =VLOOKUP(H19,Cad.RateioConsumo!$B$4:$Z$106,7,FALSE) -> 8931.2331 | N19: =ROUND(VLOOKUP(H19,Cad.RateioConsumo!$B$4:$Z$106,11,FALSE),4) -> 0.6799 | O19: =IFERROR(ROUND(VLOOKUP(C19,Hist.Geração!$A$4:$F$64,4,FALSE)*N19,2)," ") -> 9442.45 | P19: =IFERROR(VLOOKUP(B19,Hist.Consum!$B$5:$V$120,12,FALSE),"") -> 0 | Q19: =IFERROR(VLOOKUP(B19,Hist.Consum!$B$5:$V$120,15,FALSE),"") -> 0 | R19: =IFERROR(VLOOKUP(B19,Hist.Consum!$B$5:$W$120,22,FALSE),"") -> 0.8432 | S19: =IFERROR(Q19*R19,"") -> 0 | T19: =VLOOKUP(K19,Hist.BT!$A$4:$C$127,3,FALSE) -> Verde | U19: =IFERROR(ROUND(VLOOKUP(T19,Hist.BT!$G$3:$I$6,3,FALSE)*Q19,2),"") -> 0 | V19: =IFERROR(ROUND(SUM(S19+U19)*(1-AG19),2),"") -> 0 | W19: =S19+U19-V19 -> 0 | X19: =O19-Q19 -> 9442.45 | Y19: =SUMIF($J19:J$84,J19,$X19:X$84) -> 94182.39 | AB19: =SUMIF($J19:J$84,J19,$Q19:Q$84) -> 0 | AC19: =IFERROR(VLOOKUP(B19,Hist.Consum!$B$5:$AD$120,23,FALSE),"") -> 0 | AG19: =VLOOKUP(H19,Cad.RateioConsumo!$B$4:$Z$106,8,FALSE) -> 0.15
B20: =H20&K20 | W20: =S20+U20-V20 -> 0 | AB20: =SUMIF($J20:J$84,J20,$Q20:Q$84) -> 0 | AC20: =IFERROR(VLOOKUP(B20,Hist.Consum!$B$5:$AD$120,23,FALSE),"") | AG20: =VLOOKUP(H20,Cad.RateioConsumo!$B$4:$Z$106,8,FALSE) -> #N/A
B21: =H21&K21 -> 1.001/2026 | C21: =F21&L21 -> Usina 112/2025 | D21: =IF(J21=G21,0,1) -> 0 | E21: =IF(D21=0,"N/A",SUM($D21:D$83)) -> N/A | F21: Usina 1 | G21: =VLOOKUP(F21,Cad.Usinas!$A$4:$B$6,2,FALSE) -> 3023633492 | H21: 1.0 | I21: =VLOOKUP(H21,Cad.RateioConsumo!$B$4:$Z$106,2,FALSE) -> Usina 1 | J21: =VLOOKUP(H21,Cad.RateioConsumo!$B$4:$Z$106,5,FALSE) -> 3023633492 | K21: 01/2026 | L21: 12/2025 | M21: =VLOOKUP(H21,Cad.RateioConsumo!$B$4:$Z$106,7,FALSE) -> 14000 | N21: =ROUND(VLOOKUP(H21,Cad.RateioConsumo!$B$4:$Z$106,11,FALSE),4) -> 0.3201 | O21: =IFERROR(ROUND(VLOOKUP(C21,Hist.Geração!$A$4:$F$64,4,FALSE)*N21,2)," ") -> 3880.25 | P21: =IFERROR(VLOOKUP(B21,Hist.Consum!$B$5:$V$120,12,FALSE),"") -> 0 | Q21: =IFERROR(VLOOKUP(B21,Hist.Consum!$B$5:$V$120,15,FALSE),"") -> 0 | R21: =IFERROR(VLOOKUP(B21,Hist.Consum!$B$5:$W$120,22,FALSE),"") -> 0.8432 | S21: =IFERROR(Q21*R21,"") -> 0 | T21: =VLOOKUP(K21,Hist.BT!$A$4:$C$127,3,FALSE) -> Verde | U21: =IFERROR(ROUND(VLOOKUP(T21,Hist.BT!$G$3:$I$6,3,FALSE)*Q21,2),"") -> 0 | V21: =IFERROR(ROUND(SUM(S21+U21)*(1-AG21),2),"") -> 0 | W21: =S21+U21-V21 -> 0 | X21: =O21-Q21 -> 3880.25 | Y21: =SUMIF($J21:J$84,J21,$X21:X$84) -> 34058 | AB21: =SUMIF(J21:$J$84,J21,Q21:$Q$84) -> 0 | AC21: =IFERROR(VLOOKUP(B21,Hist.Consum!$B$5:$AD$120,23,FALSE),"") -> 0 | AE21: =IFERROR(VLOOKUP(B21,Hist.Consum!$B$5:$AD$120,24,FALSE),"") -> A Equatorial cobrou errado uma tarida de GD2 , gerando itens que não são devidos: 1)Benefício Tarifário Bruto SCEE R$ 961,08 e 2) (-) Benefício Tarifário Líquido SCEE 702,62. O saldo deste valor foi dado como desconto para não te afetar os 15% de desconto na conta até que a Equatorial reverter esse valor. | AG21: =VLOOKUP(H21,Cad.RateioConsumo!$B$4:$Z$106,8,FALSE) -> 0.15
B22: =H22&K22 -> 2.101/2026 | C22: =F22&L22 -> Usina 212/2025 | D22: =IF(J22=G22,0,1) -> 1 | E22: =IF(D22=0,"N/A",SUM($D22:D$83)) -> 36 | F22: Usina 2 | G22: =VLOOKUP(F22,Cad.Usinas!$A$4:$B$6,2,FALSE) -> 3023594470 | H22: 2.1 | I22: =VLOOKUP(H22,Cad.RateioConsumo!$B$4:$Z$106,2,FALSE) -> Lucas Medeiros Lima | J22: =VLOOKUP(H22,Cad.RateioConsumo!$B$4:$Z$106,5,FALSE) -> 3002796782 | K22: 01/2026 | L22: 12/2025 | M22: =VLOOKUP(H22,Cad.RateioConsumo!$B$4:$Z$106,7,FALSE) -> 1536.5 | N22: =ROUND(VLOOKUP(H22,Cad.RateioConsumo!$B$4:$Z$106,11,FALSE),4) -> 0.1098 | O22: =IFERROR(ROUND(VLOOKUP(C22,Hist.Geração!$A$4:$F$64,4,FALSE)*N22,2)," ") -> 1514.36 | P22: =IFERROR(VLOOKUP(B22,Hist.Consum!$B$5:$V$120,12,FALSE),"") -> 80 | Q22: =IFERROR(VLOOKUP(B22,Hist.Consum!$B$5:$V$120,15,FALSE),"") -> 499 | R22: =IFERROR(VLOOKUP(B22,Hist.Consum!$B$5:$W$120,22,FALSE),"") -> 0.8432 | S22: =IFERROR(Q22*R22,"") -> 420.7568 | T22: =VLOOKUP(K22,Hist.BT!$A$4:$C$127,3,FALSE) -> Verde | U22: =IFERROR(ROUND(VLOOKUP(T22,Hist.BT!$G$3:$I$6,3,FALSE)*Q22,2),"") -> 0 | V22: =IFERROR(ROUND(SUM(S22+U22)*(1-AG22),2),"") -> 357.64 | W22: =S22+U22-V22 -> 63.1168 | X22: =O22-Q22 -> 1015.36 | Y22: =SUMIF($J22:J$84,J22,$X22:X$84) -> #VALUE! | AC22: =IFERROR(VLOOKUP(B22,Hist.Consum!$B$5:$AD$120,23,FALSE),"") -> 175.78 | AD22: GD2 | AE22: =IFERROR(VLOOKUP(B22,Hist.Consum!$B$5:$AD$120,24,FALSE),"") -> A Equatorial errou no faturamento e cobrou indevidamente uma tarifa adicional:1)Benefício Tarifário Bruto SCEE e 2) (-) Benefício Tarifário Líquido SCEE . O saldo deste valor foi dado como desconto para não te afetar os 15% de desconto na conta até que a Equatorial reverter esse valor. | AG22: =VLOOKUP(H22,Cad.RateioConsumo!$B$4:$Z$106,8,FALSE) -> 0.15
A23: ok | B23: =H23&K23 -> 2.201/2026 | C23: =F23&L23 -> Usina 212/2025 | D23: =IF(J23=G23,0,1) -> 1 | E23: =IF(D23=0,"N/A",SUM($D23:D$83)) -> 35 | F23: Usina 2 | G23: =VLOOKUP(F23,Cad.Usinas!$A$4:$B$6,2,FALSE) -> 3023594470 | H23: 2.2 | I23: =VLOOKUP(H23,Cad.RateioConsumo!$B$4:$Z$106,2,FALSE) -> SORRISO SAUDE ODONTOLOGIA LTDA | J23: =VLOOKUP(H23,Cad.RateioConsumo!$B$4:$Z$106,5,FALSE) -> 3022893768 | K23: 01/2026 | L23: 12/2025 | M23: =VLOOKUP(H23,Cad.RateioConsumo!$B$4:$Z$106,7,FALSE) -> 859 | N23: =ROUND(VLOOKUP(H23,Cad.RateioConsumo!$B$4:$Z$106,11,FALSE),4) -> 0.0614 | O23: =IFERROR(ROUND(VLOOKUP(C23,Hist.Geração!$A$4:$F$64,4,FALSE)*N23,2)," ") -> 846.83 | P23: =IFERROR(VLOOKUP(B23,Hist.Consum!$B$5:$V$120,12,FALSE),"") -> 100 | Q23: =IFERROR(VLOOKUP(B23,Hist.Consum!$B$5:$V$120,15,FALSE),"") -> 399 | R23: =IFERROR(VLOOKUP(B23,Hist.Consum!$B$5:$W$120,22,FALSE),"") -> 1.1284 | S23: =IFERROR(Q23*R23,"") -> 450.2316 | T23: =VLOOKUP(K23,Hist.BT!$A$4:$C$127,3,FALSE) -> Verde | U23: =IFERROR(ROUND(VLOOKUP(T23,Hist.BT!$G$3:$I$6,3,FALSE)*Q23,2),"") -> 0 | V23: =IFERROR(ROUND(SUM(S23+U23)*(1-AG23),2),"") -> 373.69 | W23: =S23+U23-V23 -> 76.5416 | X23: =O23-Q23 -> 447.83 | Y23: =SUMIF($J23:J$84,J23,$X23:X$84) -> 644.1 | AC23: =IFERROR(VLOOKUP(B23,Hist.Consum!$B$5:$AD$120,23,FALSE),"") -> 0 | AD23: GD2 | AE23: =IFERROR(VLOOKUP(B23,Hist.Consum!$B$5:$AD$120,24,FALSE),"") -> 0 | AG23: =VLOOKUP(H23,Cad.RateioConsumo!$B$4:$Z$106,8,FALSE) -> 0.17
B24: =H24&K24 -> 2.001/2026 | C24: =F24&L24 -> Usina 212/2025 | D24: =IF(J24=G24,0,1) -> 0 | E24: =IF(D24=0,"N/A",SUM($D24:D$83)) -> N/A | F24: Usina 2 | G24: =VLOOKUP(F24,Cad.Usinas!$A$4:$B$6,2,FALSE) -> 3023594470 | H24: 2.0 | I24: =VLOOKUP(H24,Cad.RateioConsumo!$B$4:$Z$106,2,FALSE) -> Usina 2 | J24: =VLOOKUP(H24,Cad.RateioConsumo!$B$4:$Z$106,5,FALSE) -> 3023594470 | K24: 01/2026 | L24: 12/2025 | M24: =VLOOKUP(H24,Cad.RateioConsumo!$B$4:$Z$106,7,FALSE) -> 14000 | N24: =VLOOKUP(H24,Cad.RateioConsumo!$B$4:$Z$106,11,FALSE) -> 1 | O24: =IFERROR(ROUND(VLOOKUP(C24,Hist.Geração!$A$4:$F$64,4,FALSE)*N24,2)," ") -> 13792 | P24: =IFERROR(VLOOKUP(B24,Hist.Consum!$B$5:$V$120,12,FALSE),"") -> 0 | Q24: =IFERROR(VLOOKUP(B24,Hist.Consum!$B$5:$V$120,15,FALSE),"") -> 0 | R24: =IFERROR(VLOOKUP(B24,Hist.Consum!$B$5:$W$120,22,FALSE),"") -> 0.8432 | S24: =IFERROR(Q24*R24,"") -> 0 | T24: =VLOOKUP(K24,Hist.BT!$A$4:$C$127,3,FALSE) -> Verde | U24: =IFERROR(ROUND(VLOOKUP(T24,Hist.BT!$G$3:$I$6,3,FALSE)*Q24,2),"") -> 0 | V24: =IFERROR(ROUND(SUM(S24+U24)*(1-AG24),2),"") -> 0 | W24: =S24+U24-V24 -> 0 | X24: =O24-Q24 -> 13792 | Y24: =SUMIF($J24:J$84,J24,$X24:X$84) -> 111362 | AB24: =SUMIF($J24:J$84,J24,$Q24:Q$84) -> 0 | AC24: =IFERROR(VLOOKUP(B24,Hist.Consum!$B$5:$AD$120,23,FALSE),"") -> 0 | AG24: =VLOOKUP(H24,Cad.RateioConsumo!$B$4:$Z$106,8,FALSE) -> 0.15
A25: ok | B25: =H25&K25 -> 3.101/2026 | C25: =F25&L25 -> Usina 312/2025 | D25: =IF(J25=G25,0,1) -> 1 | E25: =IF(D25=0,"N/A",SUM($D25:D$83)) -> 34 | F25: Usina 3 | G25: =VLOOKUP(F25,Cad.Usinas!$A$4:$B$6,2,FALSE) -> 3023637013 | H25: 3.1 | I25: =VLOOKUP(H25,Cad.RateioConsumo!$B$4:$Z$106,2,FALSE) -> Associação dos Moradores do Residencial Araçagy | J25: =VLOOKUP(H25,Cad.RateioConsumo!$B$4:$Z$106,5,FALSE) -> 3021142432 | K25: 01/2026 | L25: 12/2025 | M25: =VLOOKUP(H25,Cad.RateioConsumo!$B$4:$Z$106,7,FALSE) -> 205.36364 | N25: =ROUND(VLOOKUP(H25,Cad.RateioConsumo!$B$4:$Z$106,11,FALSE),4) -> 0.0147 | O25: =IFERROR(ROUND(VLOOKUP(C25,Hist.Geração!$A$4:$F$64,4,FALSE)*N25,2)," ") -> 209.86 | P25: =IFERROR(VLOOKUP(B25,Hist.Consum!$B$5:$V$120,12,FALSE),"") -> 100 | Q25: =IFERROR(VLOOKUP(B25,Hist.Consum!$B$5:$V$120,15,FALSE),"") -> 114.86 | R25: =IFERROR(VLOOKUP(B25,Hist.Consum!$B$5:$W$120,22,FALSE),"") -> 1.1284 | S25: =IFERROR(Q25*R25,"") -> 129.60802 | T25: =VLOOKUP(K25,Hist.BT!$A$4:$C$127,3,FALSE) -> Verde | U25: =IFERROR(ROUND(VLOOKUP(T25,Hist.BT!$G$3:$I$6,3,FALSE)*Q25,2),"") -> 0 | V25: =IFERROR(ROUND(SUM(S25+U25)*(1-AG25),2),"") -> 110.17 | W25: =S25+U25-V25 -> 19.438024 | X25: =O25-Q25 -> 95 | Y25: =SUMIF($J25:J$84,J25,$X25:X$84) -> 271.31 | Z25: =Y25/M25 -> 1.32112 | AB25: =SUMIF($J25:J$84,J25,$Q25:Q$84) -> 652.22 | AC25: =IFERROR(VLOOKUP(B25,Hist.Consum!$B$5:$AD$120,23,FALSE),"") -> 0 | AD25: Reduzir Percentual | AG25: =VLOOKUP(H25,Cad.RateioConsumo!$B$4:$Z$106,8,FALSE) -> 0.15
A26: ok | B26: =H26&K26 -> 3.201/2026 | C26: =F26&L26 -> Usina 312/2025 | D26: =IF(J26=G26,0,1) -> 1 | E26: =IF(D26=0,"N/A",SUM($D26:D$83)) -> 33 | F26: Usina 3 | G26: =VLOOKUP(F26,Cad.Usinas!$A$4:$B$6,2,FALSE) -> 3023637013 | H26: 3.2 | I26: =VLOOKUP(H26,Cad.RateioConsumo!$B$4:$Z$106,2,FALSE) -> Associação dos Moradores do Residencial Araçagy | J26: =VLOOKUP(H26,Cad.RateioConsumo!$B$4:$Z$106,5,FALSE) -> 3021149593 | K26: 01/2026 | L26: 12/2025 | M26: =VLOOKUP(H26,Cad.RateioConsumo!$B$4:$Z$106,7,FALSE) -> 734.33333 | N26: =ROUND(VLOOKUP(H26,Cad.RateioConsumo!$B$4:$Z$106,11,FALSE),4) -> 0.0525 | O26: =IFERROR(ROUND(VLOOKUP(C26,Hist.Geração!$A$4:$F$64,4,FALSE)*N26,2)," ") -> 749.49 | P26: =IFERROR(VLOOKUP(B26,Hist.Consum!$B$5:$V$120,12,FALSE),"") -> 30 | Q26: =IFERROR(VLOOKUP(B26,Hist.Consum!$B$5:$V$120,15,FALSE),"") -> 660.25 | R26: =IFERROR(VLOOKUP(B26,Hist.Consum!$B$5:$W$120,22,FALSE),"") -> 1.1283 | S26: =IFERROR(Q26*R26,"") -> 744.96008 | T26: =VLOOKUP(K26,Hist.BT!$A$4:$C$127,3,FALSE) -> Verde | U26: =IFERROR(ROUND(VLOOKUP(T26,Hist.BT!$G$3:$I$6,3,FALSE)*Q26,2),"") -> 0 | V26: =IFERROR(ROUND(SUM(S26+U26)*(1-AG26),2),"") -> 633.22 | W26: =S26+U26-V26 -> 111.74008 | X26: =O26-Q26 -> 89.24 | Y26: =SUMIF($J26:J$84,J26,$X26:X$84) -> 89.26 | AB26: =SUMIF($J26:J$84,J26,$Q26:Q$84) -> 3209.04 | AC26: =IFERROR(VLOOKUP(B26,Hist.Consum!$B$5:$AD$120,23,FALSE),"") -> 0 | AG26: =VLOOKUP(H26,Cad.RateioConsumo!$B$4:$Z$106,8,FALSE) -> 0.15
A27: ok | B27: =H27&K27 -> 3.301/2026 | C27: =F27&L27 -> Usina 312/2025 | D27: =IF(J27=G27,0,1) -> 1 | E27: =IF(D27=0,"N/A",SUM($D27:D$83)) -> 32 | F27: Usina 3 | G27: =VLOOKUP(F27,Cad.Usinas!$A$4:$B$6,2,FALSE) -> 3023637013 | H27: 3.3 | I27: =VLOOKUP(H27,Cad.RateioConsumo!$B$4:$Z$106,2,FALSE) -> Associação dos Moradores do Residencial Araçagy | J27: =VLOOKUP(H27,Cad.RateioConsumo!$B$4:$Z$106,5,FALSE) -> 3021150559 | K27: 01/2026 | L27: 12/2025 | M27: =VLOOKUP(H27,Cad.RateioConsumo!$B$4:$Z$106,7,FALSE) -> 2086.4545 | N27: =ROUND(VLOOKUP(H27,Cad.RateioConsumo!$B$4:$Z$106,11,FALSE),4) -> 0.107 | O27: =IFERROR(ROUND(VLOOKUP(C27,Hist.Geração!$A$4:$F$64,4,FALSE)*N27,2)," ") -> 1527.53 | P27: =IFERROR(VLOOKUP(B27,Hist.Consum!$B$5:$V$120,12,FALSE),"") -> 307.3 | Q27: =IFERROR(VLOOKUP(B27,Hist.Consum!$B$5:$V$120,15,FALSE),"") -> 1528.95 | R27: =IFERROR(VLOOKUP(B27,Hist.Consum!$B$5:$W$120,22,FALSE),"") -> 1.1284 | S27: =IFERROR(Q27*R27,"") -> 1725.2672 | T27: =VLOOKUP(K27,Hist.BT!$A$4:$C$127,3,FALSE) -> Verde | U27: =IFERROR(ROUND(VLOOKUP(T27,Hist.BT!$G$3:$I$6,3,FALSE)*Q27,2),"") -> 0 | V27: =IFERROR(ROUND(SUM(S27+U27)*(1-AG27),2),"") -> 1466.48 | W27: =S27+U27-V27 -> 258.78718 | X27: =O27-Q27 -> -1.42 | Y27: =SUMIF($J27:J$84,J27,$X27:X$84) -> -2.97 | AB27: =SUMIF($J27:J$84,J27,$Q27:Q$84) -> 8097.24 | AC27: =IFERROR(VLOOKUP(B27,Hist.Consum!$B$5:$AD$120,23,FALSE),"") -> 0 | AD27: Aumentar Percentual | AG27: =VLOOKUP(H27,Cad.RateioConsumo!$B$4:$Z$106,8,FALSE) -> 0.15
A28: ok | B28: =H28&K28 -> 3.401/2026 | C28: =F28&L28 -> Usina 312/2025 | D28: =IF(J28=G28,0,1) -> 1 | E28: =IF(D28=0,"N/A",SUM($D28:D$83)) -> 31 | F28: Usina 3 | G28: =VLOOKUP(F28,Cad.Usinas!$A$4:$B$6,2,FALSE) -> 3023637013 | H28: 3.4 | I28: =VLOOKUP(H28,Cad.RateioConsumo!$B$4:$Z$106,2,FALSE) -> Antonio Jose Souza Filho | J28: =VLOOKUP(H28,Cad.RateioConsumo!$B$4:$Z$106,5,FALSE) -> 3007625048 | K28: 01/2026 | L28: 12/2025 | M28: =VLOOKUP(H28,Cad.RateioConsumo!$B$4:$Z$106,7,FALSE) -> 417.15385 | N28: =ROUND(VLOOKUP(H28,Cad.RateioConsumo!$B$4:$Z$106,11,FALSE),4) -> 0.0298 | O28: =IFERROR(ROUND(VLOOKUP(C28,Hist.Geração!$A$4:$F$64,4,FALSE)*N28,2)," ") -> 425.42 | P28: =IFERROR(VLOOKUP(B28,Hist.Consum!$B$5:$V$120,12,FALSE),"") -> 129.47 | Q28: =IFERROR(VLOOKUP(B28,Hist.Consum!$B$5:$V$120,15,FALSE),"") -> 441.52 | R28: =IFERROR(VLOOKUP(B28,Hist.Consum!$B$5:$W$120,22,FALSE),"") -> 1.1284 | S28: =IFERROR(Q28*R28,"") -> 498.21117 | T28: =VLOOKUP(K28,Hist.BT!$A$4:$C$127,3,FALSE) -> Verde | U28: =IFERROR(ROUND(VLOOKUP(T28,Hist.BT!$G$3:$I$6,3,FALSE)*Q28,2),"") -> 0 | V28: =IFERROR(ROUND(SUM(S28+U28)*(1-AG28),2),"") -> 423.48 | W28: =S28+U28-V28 -> 74.731168 | X28: =O28-Q28 -> -16.1 | Y28: =SUMIF($J28:J$84,J28,$X28:X$84) -> 8.5265128e-14 | AB28: =SUMIF($J28:J$84,J28,$Q28:Q$84) -> 1872.17 | AC28: =IFERROR(VLOOKUP(B28,Hist.Consum!$B$5:$AD$120,23,FALSE),"") -> 0 | AG28: =VLOOKUP(H28,Cad.RateioConsumo!$B$4:$Z$106,8,FALSE) -> 0.15
B29: =H29&K29 -> 3.512/2025 | C29: =F29&L29 -> Usina 311/2025 | D29: =IF(J29=G29,0,1) -> 1 | E29: =IF(D29=0,"N/A",SUM($D29:D$83)) -> 30 | F29: Usina 3 | G29: =VLOOKUP(F29,Cad.Usinas!$A$4:$B$6,2,FALSE) -> 3023637013 | H29: 3.5 | I29: =VLOOKUP(H29,Cad.RateioConsumo!$B$4:$Z$106,2,FALSE) -> João Carlos Pereira Dutra Filho | J29: =VLOOKUP(H29,Cad.RateioConsumo!$B$4:$Z$106,5,FALSE) -> 1163310 | K29: 12/2025 | L29: 11/2025 | M29: =VLOOKUP(H29,Cad.RateioConsumo!$B$4:$Z$106,7,FALSE) -> 848.69231 | N29: =ROUND(VLOOKUP(H29,Cad.RateioConsumo!$B$4:$Z$106,11,FALSE),4) -> 0.0606 | O29: =IFERROR(ROUND(VLOOKUP(C29,Hist.Geração!$A$4:$F$64,4,FALSE)*N29,2)," ") -> 951.9 | P29: =IFERROR(VLOOKUP(B29,Hist.Consum!$B$5:$V$120,12,FALSE),"") -> 30 | Q29: =IFERROR(VLOOKUP(B29,Hist.Consum!$B$5:$V$120,15,FALSE),"") -> 864 | R29: =IFERROR(VLOOKUP(B29,Hist.Consum!$B$5:$W$120,22,FALSE),"") -> 1.1427 | S29: =IFERROR(Q29*R29,"") -> 987.2928 | T29: =VLOOKUP(K29,Hist.BT!$A$4:$C$127,3,FALSE) -> Amarela | U29: =IFERROR(ROUND(VLOOKUP(T29,Hist.BT!$G$3:$I$6,3,FALSE)*Q29,2),"") -> 21.15 | V29: =IFERROR(ROUND(SUM(S29+U29)*(1-AG29),2),"") -> 857.18 | W29: =S29+U29-V29 -> 151.2628 | X29: =O29-Q29 -> 87.9 | Y29: =SUMIF(J21:$J$84,J29,X21:$X$84) -> 87.91 | AB29: =SUMIF(J21:$J$84,J29,Q21:$Q$84) -> 874.52 | AC29: =IFERROR(VLOOKUP(B29,Hist.Consum!$B$5:$AD$120,23,FALSE),"") -> 0 | AD29: =IF((Y29/M29)>1,"Mudar Urgente",IF((Y29/M29)>0.4,"Rever Rateio",("ok"))) -> ok | AG29: =VLOOKUP(H29,Cad.RateioConsumo!$B$4:$Z$106,8,FALSE) -> 0.15
A30: ok | B30: =H30&K30 -> 3.6 | C30: =F30&L30 -> Usina 3 | D30: =IF(J30=G30,0,1) -> 1 | E30: =IF(D30=0,"N/A",SUM($D30:D$83)) -> 29 | F30: Usina 3 | G30: =VLOOKUP(F30,Cad.Usinas!$A$4:$B$6,2,FALSE) -> 3023637013 | H30: 3.6 | I30: =VLOOKUP(H30,Cad.RateioConsumo!$B$4:$Z$106,2,FALSE) -> Patricia Maria Abreu Machado | AD30: Percentual errado | AE30: O contrato foi feito com base no consumo médio de 777 kwh e em dezembro foi consumido energia maior que a média por isso a energia paga pela Equatorial foi maior. Se existir uma tendência de aumento do consumo da energia favor nos informar para ajustarmos o contrato. | AG30: =VLOOKUP(H30,Cad.RateioConsumo!$B$4:$Z$106,8,FALSE) -> 0.15
B31: =H31&K31 -> 3.7 | C31: =F31&L31 -> Usina 3 | D31: =IF(J31=G31,0,1) -> 1 | E31: =IF(D31=0,"N/A",SUM($D31:D$83)) -> 28 | F31: Usina 3 | G31: =VLOOKUP(F31,Cad.Usinas!$A$4:$B$6,2,FALSE) -> 3023637013 | H31: 3.7 | I31: =VLOOKUP(H31,Cad.RateioConsumo!$B$4:$Z$106,2,FALSE) -> Fatima Abdel Hafiz Khalifa Cavalcanti | AB31: =SUMIF($J31:J$84,J31,$Q31:Q$84) -> 0 | AC31: =IFERROR(VLOOKUP(B31,Hist.Consum!$B$5:$AD$120,23,FALSE),"") -> 0.8432 | AD31: =IF((Y31/M31)>1,"Mudar Urgente",IF((Y31/M31)>0.4,"Rever Rateio",("ok"))) -> #DIV/0! | AG31: =VLOOKUP(H31,Cad.RateioConsumo!$B$4:$Z$106,8,FALSE) -> 0.15
B32: =H32&K32 -> 3.001/2026 | C32: =F32&L32 -> Usina 312/2025 | D32: =IF(J32=G32,0,1) -> 0 | E32: =IF(D32=0,"N/A",SUM($D32:D$83)) -> N/A | F32: Usina 3 | G32: =VLOOKUP(F32,Cad.Usinas!$A$4:$B$6,2,FALSE) -> 3023637013 | H32: 3.0 | I32: =VLOOKUP(H32,Cad.RateioConsumo!$B$4:$Z$106,2,FALSE) -> Usina 3 | J32: =VLOOKUP(H32,Cad.RateioConsumo!$B$4:$Z$106,5,FALSE) -> 3023637013 | K32: 01/2026 | L32: 12/2025 | M32: =VLOOKUP(H32,Cad.RateioConsumo!$B$4:$Z$106,7,FALSE) -> 8931.2331 | N32: =ROUND(VLOOKUP(H32,Cad.RateioConsumo!$B$4:$Z$106,11,FALSE),4) -> 0.6799 | O32: =IFERROR(ROUND(VLOOKUP(C32,Hist.Geração!$A$4:$F$64,4,FALSE)*N32,2)," ") -> 9706.25 | P32: =IFERROR(VLOOKUP(B32,Hist.Consum!$B$5:$V$120,12,FALSE),"") -> 0 | Q32: =IFERROR(VLOOKUP(B32,Hist.Consum!$B$5:$V$120,15,FALSE),"") -> 0 | R32: =IFERROR(VLOOKUP(B32,Hist.Consum!$B$5:$W$120,22,FALSE),"") -> 0.8432 | S32: =IFERROR(Q32*R32,"") -> 0 | T32: =VLOOKUP(K32,Hist.BT!$A$4:$C$127,3,FALSE) -> Verde | U32: =IFERROR(ROUND(VLOOKUP(T32,Hist.BT!$G$3:$I$6,3,FALSE)*Q32,2),"") -> 0 | V32: =IFERROR(ROUND(SUM(S32+U32)*(1-AG32),2),"") -> 0 | W32: =S32+U32-V32 -> 0 | X32: =O32-Q32 -> 9706.25 | Y32: =SUMIF($J32:J$84,J32,$X32:X$84) -> 84739.94 | AB32: =SUMIF($J32:J$84,J32,$Q32:Q$84) -> 0 | AC32: =IFERROR(VLOOKUP(B32,Hist.Consum!$B$5:$AD$120,23,FALSE),"") -> 0 | AG32: =VLOOKUP(H32,Cad.RateioConsumo!$B$4:$Z$106,8,FALSE) -> 0.15
B33: =H33&K33 | W33: =S33+U33-V33 -> 0 | AB33: =SUMIF($J33:J$84,J33,$Q33:Q$84) -> 0 | AC33: =IFERROR(VLOOKUP(B33,Hist.Consum!$B$5:$AD$120,23,FALSE),"") | AG33: =VLOOKUP(H33,Cad.RateioConsumo!$B$4:$Z$106,8,FALSE) -> #N/A
B34: =H34&K34 -> 1.012/2025 | C34: =F34&L34 -> Usina 111/2025 | D34: =IF(J34=G34,0,1) -> 0 | E34: =IF(D34=0,"N/A",SUM($D34:D$83)) -> N/A | F34: Usina 1 | G34: =VLOOKUP(F34,Cad.Usinas!$A$4:$B$6,2,FALSE) -> 3023633492 | H34: 1.0 | I34: =VLOOKUP(H34,Cad.RateioConsumo!$B$4:$Z$106,2,FALSE) -> Usina 1 | J34: =VLOOKUP(H34,Cad.RateioConsumo!$B$4:$Z$106,5,FALSE) -> 3023633492 | K34: 12/2025 | L34: 11/2025 | M34: =VLOOKUP(H34,Cad.RateioConsumo!$B$4:$Z$106,7,FALSE) -> 14000 | N34: =ROUND(VLOOKUP(H34,Cad.RateioConsumo!$B$4:$Z$106,11,FALSE),4) -> 0.3201 | O34: =IFERROR(ROUND(VLOOKUP(C34,Hist.Geração!$A$4:$F$64,4,FALSE)*N34,2)," ") -> 4946.19 | P34: =IFERROR(VLOOKUP(B34,Hist.Consum!$B$5:$V$120,12,FALSE),"") -> 0 | Q34: =IFERROR(VLOOKUP(B34,Hist.Consum!$B$5:$V$120,15,FALSE),"") -> 0 | R34: =IFERROR(VLOOKUP(B34,Hist.Consum!$B$5:$W$120,22,FALSE),"") -> 1.1427 | S34: =IFERROR(Q34*R34,"") -> 0 | T34: =VLOOKUP(K34,Hist.BT!$A$4:$C$27,3,FALSE) -> Amarela | U34: =IFERROR(ROUND(VLOOKUP(T34,Hist.BT!$G$3:$I$6,3,FALSE)*Q34,2),"") -> 0 | V34: =IFERROR(ROUND(SUM(S34+U34)*(1-AG34),2),"") -> 0 | W34: =S34+U34-V34 -> 0 | X34: =O34-Q34 -> 4946.19 | Y34: =SUMIF($J34:J$84,J34,$X34:X$84) -> 30177.75 | AB34: =SUMIF(J34:$J$84,J34,Q34:$Q$84) -> 0 | AC34: =IFERROR(VLOOKUP(B34,Hist.Consum!$B$5:$AD$120,23,FALSE),"") -> 0 | AE34: =IFERROR(VLOOKUP(B34,Hist.Consum!$B$5:$AD$120,24,FALSE),"") -> A Equatorial cobrou errado uma tarida de GD2 , gerando itens que não são devidos: 1)Benefício Tarifário Bruto SCEE R$ 961,08 e 2) (-) Benefício Tarifário Líquido SCEE 702,62. O saldo deste valor foi dado como desconto para não te afetar os 15% de desconto na conta até que a Equatorial reverter esse valor. | AG34: =VLOOKUP(H34,Cad.RateioConsumo!$B$4:$Z$106,8,FALSE) -> 0.15
A35: ok | B35: =H35&K35 -> 2.112/2025 | C35: =F35&L35 -> Usina 211/2025 | D35: =IF(J35=G35,0,1) -> 1 | E35: =IF(D35=0,"N/A",SUM($D35:D$83)) -> 27 | F35: Usina 2 | G35: =VLOOKUP(F35,Cad.Usinas!$A$4:$B$6,2,FALSE) -> 3023594470 | H35: 2.1 | I35: =VLOOKUP(H35,Cad.RateioConsumo!$B$4:$Z$106,2,FALSE) -> Lucas Medeiros Lima | J35: =VLOOKUP(H35,Cad.RateioConsumo!$B$4:$Z$106,5,FALSE) -> 3002796782 | K35: 12/2025 | L35: 11/2025 | M35: =VLOOKUP(H35,Cad.RateioConsumo!$B$4:$Z$106,7,FALSE) -> 1536.5 | N35: =ROUND(VLOOKUP(H35,Cad.RateioConsumo!$B$4:$Z$106,11,FALSE),4) -> 0.1098 | O35: =IFERROR(ROUND(VLOOKUP(C35,Hist.Geração!$A$4:$F$64,4,FALSE)*N35,2)," ") -> 1739.12 | P35: =IFERROR(VLOOKUP(B35,Hist.Consum!$B$5:$V$120,12,FALSE),"") -> 80 | Q35: =IFERROR(VLOOKUP(B35,Hist.Consum!$B$5:$V$120,15,FALSE),"") -> 1123 | R35: =IFERROR(VLOOKUP(B35,Hist.Consum!$B$5:$W$120,22,FALSE),"") -> 1.1427 | S35: =IFERROR(Q35*R35,"") -> 1283.2521 | T35: =VLOOKUP(K35,Hist.BT!$A$4:$C$27,3,FALSE) -> Amarela | U35: =IFERROR(ROUND(VLOOKUP(T35,Hist.BT!$G$3:$I$6,3,FALSE)*Q35,2),"") -> 27.49 | V35: =IFERROR(ROUND(SUM(S35+U35)*(1-AG35),2),"") -> 1114.13 | W35: =S35+U35-V35 -> 196.6121 | X35: =O35-Q35 -> 616.12 | Y35: =SUMIF($J35:J$84,J35,$X35:X$84) -> #VALUE! | AC35: =IFERROR(VLOOKUP(B35,Hist.Consum!$B$5:$AD$120,23,FALSE),"") -> 379.61 | AD35: GD2 | AE35: =IFERROR(VLOOKUP(B35,Hist.Consum!$B$5:$AD$120,24,FALSE),"") -> A Equatorial errou no faturamento e cobrou indevidamente uma tarifa adicional:1)Benefício Tarifário Bruto SCEE e 2) (-) Benefício Tarifário Líquido SCEE . O saldo deste valor foi dado como desconto para não te afetar os 15% de desconto na conta até que a Equatorial reverter esse valor. | AG35: =VLOOKUP(H35,Cad.RateioConsumo!$B$4:$Z$106,8,FALSE) -> 0.15
A36: ok | B36: =H36&K36 -> 2.212/2025 | C36: =F36&L36 -> Usina 211/2025 | D36: =IF(J36=G36,0,1) -> 1 | E36: =IF(D36=0,"N/A",SUM($D36:D$83)) -> 26 | F36: Usina 2 | G36: =VLOOKUP(F36,Cad.Usinas!$A$4:$B$6,2,FALSE) -> 3023594470 | H36: 2.2 | I36: =VLOOKUP(H36,Cad.RateioConsumo!$B$4:$Z$106,2,FALSE) -> SORRISO SAUDE ODONTOLOGIA LTDA | J36: =VLOOKUP(H36,Cad.RateioConsumo!$B$4:$Z$106,5,FALSE) -> 3022893768 | K36: 12/2025 | L36: 11/2025 | M36: =VLOOKUP(H36,Cad.RateioConsumo!$B$4:$Z$106,7,FALSE) -> 859 | N36: =ROUND(VLOOKUP(H36,Cad.RateioConsumo!$B$4:$Z$106,11,FALSE),4) -> 0.0614 | O36: =IFERROR(ROUND(VLOOKUP(C36,Hist.Geração!$A$4:$F$64,4,FALSE)*N36,2)," ") -> 972.51 | P36: =IFERROR(VLOOKUP(B36,Hist.Consum!$B$5:$V$120,12,FALSE),"") -> 0 | Q36: =IFERROR(VLOOKUP(B36,Hist.Consum!$B$5:$V$120,15,FALSE),"") -> 917 | R36: =IFERROR(VLOOKUP(B36,Hist.Consum!$B$5:$W$120,22,FALSE),"") -> 1.1427 | S36: =IFERROR(Q36*R36,"") -> 1047.8559 | T36: =VLOOKUP(K36,Hist.BT!$A$4:$C$27,3,FALSE) -> Amarela | U36: =IFERROR(ROUND(VLOOKUP(T36,Hist.BT!$G$3:$I$6,3,FALSE)*Q36,2),"") -> 22.45 | V36: =IFERROR(ROUND(SUM(S36+U36)*(1-AG36),2),"") -> 888.35 | W36: =S36+U36-V36 -> 181.9559 | X36: =O36-Q36 -> 55.51 | Y36: =SUMIF($J36:J$84,J36,$X36:X$84) -> 196.27 | AC36: =IFERROR(VLOOKUP(B36,Hist.Consum!$B$5:$AD$120,23,FALSE),"") -> -321.57 | AD36: GD2 | AE36: =IFERROR(VLOOKUP(B36,Hist.Consum!$B$5:$AD$120,24,FALSE),"") -> A Equatorial errou no faturamento e cobrou indevidamente uma tarifa adicional:1)Benefício Tarifário Bruto SCEE e 2) (-) Benefício Tarifário Líquido SCEE . O saldo deste valor foi dado como desconto para não te afetar os 15% de desconto na conta até que a Equatorial reverter esse valor. | AG36: =VLOOKUP(H36,Cad.RateioConsumo!$B$4:$Z$106,8,FALSE) -> 0.17
B37: =H37&K37 -> 2.012/2025 | C37: =F37&L37 -> Usina 211/2025 | D37: =IF(J37=G37,0,1) -> 0 | E37: =IF(D37=0,"N/A",SUM($D37:D$83)) -> N/A | F37: Usina 2 | G37: =VLOOKUP(F37,Cad.Usinas!$A$4:$B$6,2,FALSE) -> 3023594470 | H37: 2.0 | I37: =VLOOKUP(H37,Cad.RateioConsumo!$B$4:$Z$106,2,FALSE) -> Usina 2 | J37: =VLOOKUP(H37,Cad.RateioConsumo!$B$4:$Z$106,5,FALSE) -> 3023594470 | K37: 12/2025 | L37: 11/2025 | M37: =VLOOKUP(H37,Cad.RateioConsumo!$B$4:$Z$106,7,FALSE) -> 14000 | N37: =VLOOKUP(H37,Cad.RateioConsumo!$B$4:$Z$106,11,FALSE) -> 1 | O37: =IFERROR(ROUND(VLOOKUP(C37,Hist.Geração!$A$4:$F$64,4,FALSE)*N37,2)," ") -> 15839 | P37: =IFERROR(VLOOKUP(B37,Hist.Consum!$B$5:$V$120,12,FALSE),"") -> 0 | Q37: =IFERROR(VLOOKUP(B37,Hist.Consum!$B$5:$V$120,15,FALSE),"") -> 0 | R37: =IFERROR(VLOOKUP(B37,Hist.Consum!$B$5:$W$120,22,FALSE),"") -> 1.1427 | S37: =IFERROR(Q37*R37,"") -> 0 | T37: =VLOOKUP(K37,Hist.BT!$A$4:$C$27,3,FALSE) -> Amarela | U37: =IFERROR(ROUND(VLOOKUP(T37,Hist.BT!$G$3:$I$6,3,FALSE)*Q37,2),"") -> 0 | V37: =IFERROR(ROUND(SUM(S37+U37)*(1-AG37),2),"") -> 0 | W37: =S37+U37-V37 -> 0 | X37: =O37-Q37 -> 15839 | Y37: =SUMIF($J37:J$84,J37,$X37:X$84) -> 97570 | AB37: =SUMIF($J37:J$84,J37,$Q37:Q$84) -> 0 | AC37: =IFERROR(VLOOKUP(B37,Hist.Consum!$B$5:$AD$120,23,FALSE),"") -> 0 | AG37: =VLOOKUP(H37,Cad.RateioConsumo!$B$4:$Z$106,8,FALSE) -> 0.15
A38: ok | B38: =H38&K38 -> 3.112/2025 | C38: =F38&L38 -> Usina 311/2025 | D38: =IF(J38=G38,0,1) -> 1 | E38: =IF(D38=0,"N/A",SUM($D38:D$83)) -> 25 | F38: Usina 3 | G38: =VLOOKUP(F38,Cad.Usinas!$A$4:$B$6,2,FALSE) -> 3023637013 | H38: 3.1 | I38: =VLOOKUP(H38,Cad.RateioConsumo!$B$4:$Z$106,2,FALSE) -> Associação dos Moradores do Residencial Araçagy | J38: =VLOOKUP(H38,Cad.RateioConsumo!$B$4:$Z$106,5,FALSE) -> 3021142432 | K38: 12/2025 | L38: 11/2025 | M38: =VLOOKUP(H38,Cad.RateioConsumo!$B$4:$Z$106,7,FALSE) -> 205.36364 | N38: =ROUND(VLOOKUP(H38,Cad.RateioConsumo!$B$4:$Z$106,11,FALSE),4) -> 0.0147 | O38: =IFERROR(ROUND(VLOOKUP(C38,Hist.Geração!$A$4:$F$64,4,FALSE)*N38,2)," ") -> 230.91 | P38: =IFERROR(VLOOKUP(B38,Hist.Consum!$B$5:$V$120,12,FALSE),"") -> 100 | Q38: =IFERROR(VLOOKUP(B38,Hist.Consum!$B$5:$V$120,15,FALSE),"") -> 120.86 | R38: =IFERROR(VLOOKUP(B38,Hist.Consum!$B$5:$W$120,22,FALSE),"") -> 1.1427 | S38: =IFERROR(Q38*R38,"") -> 138.10672 | T38: =VLOOKUP(K38,Hist.BT!$A$4:$C$27,3,FALSE) -> Amarela | U38: =IFERROR(ROUND(VLOOKUP(T38,Hist.BT!$G$3:$I$6,3,FALSE)*Q38,2),"") -> 2.96 | V38: =IFERROR(ROUND(SUM(S38+U38)*(1-AG38),2),"") -> 119.91 | W38: =S38+U38-V38 -> 21.156722 | X38: =O38-Q38 -> 110.05 | Y38: =SUMIF($J38:J$84,J38,$X38:X$84) -> 176.31 | AB38: =SUMIF($J38:J$84,J38,$Q38:Q$84) -> 537.36 | AC38: =IFERROR(VLOOKUP(B38,Hist.Consum!$B$5:$AD$120,23,FALSE),"") -> 0 | AD38: Percentual errado | AE38: Recorremos na esfera administrativa para o refaturamento para conta de 11/2025 e foi indeferida. Estamos entrando com um processo na ouvidoria para reverter a decisão | AG38: =VLOOKUP(H38,Cad.RateioConsumo!$B$4:$Z$106,8,FALSE) -> 0.15
A39: ok | B39: =H39&K39 -> 3.212/2025 | C39: =F39&L39 -> Usina 311/2025 | D39: =IF(J39=G39,0,1) -> 1 | E39: =IF(D39=0,"N/A",SUM($D39:D$83)) -> 24 | F39: Usina 3 | G39: =VLOOKUP(F39,Cad.Usinas!$A$4:$B$6,2,FALSE) -> 3023637013 | H39: 3.2 | I39: =VLOOKUP(H39,Cad.RateioConsumo!$B$4:$Z$106,2,FALSE) -> Associação dos Moradores do Residencial Araçagy | J39: =VLOOKUP(H39,Cad.RateioConsumo!$B$4:$Z$106,5,FALSE) -> 3021149593 | K39: 12/2025 | L39: 11/2025 | M39: =VLOOKUP(H39,Cad.RateioConsumo!$B$4:$Z$106,7,FALSE) -> 734.33333 | N39: =ROUND(VLOOKUP(H39,Cad.RateioConsumo!$B$4:$Z$106,11,FALSE),4) -> 0.0525 | O39: =IFERROR(ROUND(VLOOKUP(C39,Hist.Geração!$A$4:$F$64,4,FALSE)*N39,2)," ") -> 824.67 | P39: =IFERROR(VLOOKUP(B39,Hist.Consum!$B$5:$V$120,12,FALSE),"") -> 162.69 | Q39: =IFERROR(VLOOKUP(B39,Hist.Consum!$B$5:$V$120,15,FALSE),"") -> 824.67 | R39: =IFERROR(VLOOKUP(B39,Hist.Consum!$B$5:$W$120,22,FALSE),"") -> 1.1427 | S39: =IFERROR(Q39*R39,"") -> 942.35041 | T39: =VLOOKUP(K39,Hist.BT!$A$4:$C$27,3,FALSE) -> Amarela | U39: =IFERROR(ROUND(VLOOKUP(T39,Hist.BT!$G$3:$I$6,3,FALSE)*Q39,2),"") -> 20.19 | V39: =IFERROR(ROUND(SUM(S39+U39)*(1-AG39),2),"") -> 818.16 | W39: =S39+U39-V39 -> 144.38041 | X39: =O39-Q39 -> 0 | Y39: =SUMIF($J39:J$84,J39,$X39:X$84) -> 0.02 | AB39: =SUMIF($J39:J$84,J39,$Q39:Q$84) -> 2548.79 | AC39: =IFERROR(VLOOKUP(B39,Hist.Consum!$B$5:$AD$120,23,FALSE),"") -> 0 | AD39: Percentual errado | AE39: Recorremos na esfera administrativa para o refaturamento para conta de 11/2025 e foi indeferida. Estamos entrando com um processo na ouvidoria para reverter a decisão | AG39: =VLOOKUP(H39,Cad.RateioConsumo!$B$4:$Z$106,8,FALSE) -> 0.15
A40: ok | B40: =H40&K40 -> 3.312/2025 | C40: =F40&L40 -> Usina 311/2025 | D40: =IF(J40=G40,0,1) -> 1 | E40: =IF(D40=0,"N/A",SUM($D40:D$83)) -> 23 | F40: Usina 3 | G40: =VLOOKUP(F40,Cad.Usinas!$A$4:$B$6,2,FALSE) -> 3023637013 | H40: 3.3 | I40: =VLOOKUP(H40,Cad.RateioConsumo!$B$4:$Z$106,2,FALSE) -> Associação dos Moradores do Residencial Araçagy | J40: =VLOOKUP(H40,Cad.RateioConsumo!$B$4:$Z$106,5,FALSE) -> 3021150559 | K40: 12/2025 | L40: 11/2025 | M40: =VLOOKUP(H40,Cad.RateioConsumo!$B$4:$Z$106,7,FALSE) -> 2086.4545 | N40: =ROUND(VLOOKUP(H40,Cad.RateioConsumo!$B$4:$Z$106,11,FALSE),4) -> 0.107 | O40: =IFERROR(ROUND(VLOOKUP(C40,Hist.Geração!$A$4:$F$64,4,FALSE)*N40,2)," ") -> 1680.76 | P40: =IFERROR(VLOOKUP(B40,Hist.Consum!$B$5:$V$120,12,FALSE),"") -> 374.43 | Q40: =IFERROR(VLOOKUP(B40,Hist.Consum!$B$5:$V$120,15,FALSE),"") -> 1682.32 | R40: =IFERROR(VLOOKUP(B40,Hist.Consum!$B$5:$W$120,22,FALSE),"") -> 1.1427 | S40: =IFERROR(Q40*R40,"") -> 1922.3871 | T40: =VLOOKUP(K40,Hist.BT!$A$4:$C$27,3,FALSE) -> Amarela | U40: =IFERROR(ROUND(VLOOKUP(T40,Hist.BT!$G$3:$I$6,3,FALSE)*Q40,2),"") -> 41.18 | V40: =IFERROR(ROUND(SUM(S40+U40)*(1-AG40),2),"") -> 1669.03 | W40: =S40+U40-V40 -> 294.53706 | X40: =O40-Q40 -> -1.56 | Y40: =SUMIF($J40:J$84,J40,$X40:X$84) -> -1.55 | AB40: =SUMIF($J40:J$84,J40,$Q40:Q$84) -> 6568.29 | AC40: =IFERROR(VLOOKUP(B40,Hist.Consum!$B$5:$AD$120,23,FALSE),"") -> 0 | AD40: Percentual errado | AE40: Recorremos na esfera administrativa para o refaturamento para conta de 11/2025 e foi indeferida. Estamos entrando com um processo na ouvidoria para reverter a decisão | AG40: =VLOOKUP(H40,Cad.RateioConsumo!$B$4:$Z$106,8,FALSE) -> 0.15
A41: ok | B41: =H41&K41 -> 3.412/2025 | C41: =F41&L41 -> Usina 311/2025 | D41: =IF(J41=G41,0,1) -> 1 | E41: =IF(D41=0,"N/A",SUM($D41:D$83)) -> 22 | F41: Usina 3 | G41: =VLOOKUP(F41,Cad.Usinas!$A$4:$B$6,2,FALSE) -> 3023637013 | H41: 3.4 | I41: =VLOOKUP(H41,Cad.RateioConsumo!$B$4:$Z$106,2,FALSE) -> Antonio Jose Souza Filho | J41: =VLOOKUP(H41,Cad.RateioConsumo!$B$4:$Z$106,5,FALSE) -> 3007625048 | K41: 12/2025 | L41: 11/2025 | M41: =VLOOKUP(H41,Cad.RateioConsumo!$B$4:$Z$106,7,FALSE) -> 417.15385 | N41: =ROUND(VLOOKUP(H41,Cad.RateioConsumo!$B$4:$Z$106,11,FALSE),4) -> 0.0298 | O41: =IFERROR(ROUND(VLOOKUP(C41,Hist.Geração!$A$4:$F$64,4,FALSE)*N41,2)," ") -> 468.1 | P41: =IFERROR(VLOOKUP(B41,Hist.Consum!$B$5:$V$120,12,FALSE),"") -> 30 | Q41: =IFERROR(VLOOKUP(B41,Hist.Consum!$B$5:$V$120,15,FALSE),"") -> 452 | R41: =IFERROR(VLOOKUP(B41,Hist.Consum!$B$5:$W$120,22,FALSE),"") -> 1.1427 | S41: =IFERROR(Q41*R41,"") -> 516.5004 | T41: =VLOOKUP(K41,Hist.BT!$A$4:$C$27,3,FALSE) -> Amarela | U41: =IFERROR(ROUND(VLOOKUP(T41,Hist.BT!$G$3:$I$6,3,FALSE)*Q41,2),"") -> 11.07 | V41: =IFERROR(ROUND(SUM(S41+U41)*(1-AG41),2),"") -> 448.43 | W41: =S41+U41-V41 -> 79.1404 | X41: =O41-Q41 -> 16.1 | Y41: =SUMIF($J41:J$84,J41,$X41:X$84) -> 16.1 | AB41: =SUMIF($J41:J$84,J41,$Q41:Q$84) -> 1430.65 | AC41: =IFERROR(VLOOKUP(B41,Hist.Consum!$B$5:$AD$120,23,FALSE),"") -> 0 | AD41: Percentual errado | AE41: Recorremos na esfera administrativa para o refaturamento para conta de 11/2025 e foi indeferida. Estamos entrando com um processo na ouvidoria para reverter a decisão | AG41: =VLOOKUP(H41,Cad.RateioConsumo!$B$4:$Z$106,8,FALSE) -> 0.15
B42: =H42&K42 -> 3.5 | C42: =F42&L42 -> Usina 3 | D42: =IF(J42=G42,0,1) -> 1 | E42: =IF(D42=0,"N/A",SUM($D42:D$83)) -> 21 | F42: Usina 3 | G42: =VLOOKUP(F42,Cad.Usinas!$A$4:$B$6,2,FALSE) -> 3023637013 | H42: 3.5 | I42: =VLOOKUP(H42,Cad.RateioConsumo!$B$4:$Z$106,2,FALSE) -> João Carlos Pereira Dutra Filho | AB42: =SUMIF(J34:$J$84,J42,Q34:$Q$84) -> 0 | AC42: =IFERROR(VLOOKUP(B42,Hist.Consum!$B$5:$AD$120,23,FALSE),"") -> 0 | AD42: =IF((Y42/M42)>1,"Mudar Urgente",IF((Y42/M42)>0.4,"Rever Rateio",("ok"))) -> #DIV/0! | AG42: =VLOOKUP(H42,Cad.RateioConsumo!$B$4:$Z$106,8,FALSE) -> 0.15
A43: ok | B43: =H43&K43 -> 3.612/2025 | C43: =F43&L43 -> Usina 311/2025 | D43: =IF(J43=G43,0,1) -> 1 | E43: =IF(D43=0,"N/A",SUM($D43:D$83)) -> 20 | F43: Usina 3 | G43: =VLOOKUP(F43,Cad.Usinas!$A$4:$B$6,2,FALSE) -> 3023637013 | H43: 3.6 | I43: =VLOOKUP(H43,Cad.RateioConsumo!$B$4:$Z$106,2,FALSE) -> Patricia Maria Abreu Machado | J43: =VLOOKUP(H43,Cad.RateioConsumo!$B$4:$Z$106,5,FALSE) -> 3006793931 | K43: 12/2025 | L43: 11/2025 | M43: =VLOOKUP(H43,Cad.RateioConsumo!$B$4:$Z$106,7,FALSE) -> 776.76923 | N43: =ROUND(VLOOKUP(H43,Cad.RateioConsumo!$B$4:$Z$106,11,FALSE),4) -> 0.0555 | O43: =IFERROR(ROUND(VLOOKUP(C43,Hist.Geração!$A$4:$F$64,4,FALSE)*N43,2)," ") -> 871.79 | P43: =IFERROR(VLOOKUP(B43,Hist.Consum!$B$5:$V$120,12,FALSE),"") -> 210.2 | Q43: =IFERROR(VLOOKUP(B43,Hist.Consum!$B$5:$V$120,15,FALSE),"") -> 871.79 | R43: =IFERROR(VLOOKUP(B43,Hist.Consum!$B$5:$W$120,22,FALSE),"") -> 1.1427 | S43: =IFERROR(Q43*R43,"") -> 996.19443 | T43: =VLOOKUP(K43,Hist.BT!$A$4:$C$27,3,FALSE) -> Amarela | U43: =IFERROR(ROUND(VLOOKUP(T43,Hist.BT!$G$3:$I$6,3,FALSE)*Q43,2),"") -> 21.34 | V43: =IFERROR(ROUND(SUM(S43+U43)*(1-AG43),2),"") -> 864.9 | W43: =S43+U43-V43 -> 152.63443 | X43: =O43-Q43 -> 0 | Y43: =SUMIF($J43:J$84,J43,$X43:X$84) -> 0 | AB43: =SUMIF($J43:J$84,J43,$Q43:Q$84) -> 881.43 | AC43: =IFERROR(VLOOKUP(B43,Hist.Consum!$B$5:$AD$120,23,FALSE),"") -> O contrato foi feito com base no consumo médio de 777 kwh e em dezembro foi consumido energia maior que a média por isso a energia paga pela Equatorial foi maior. Se existir uma tendência de aumento do consumo da energia favor nos informar para ajustarmos o contrato. | AD43: Percentual errado | AE43: O contrato foi feito com base no consumo médio de 777 kwh e em dezembro foi consumido energia maior que a média por isso a energia paga pela Equatorial foi maior. Se existir uma tendência de aumento do consumo da energia favor nos informar para ajustarmos o contrato. | AG43: =VLOOKUP(H43,Cad.RateioConsumo!$B$4:$Z$106,8,FALSE) -> 0.15
A44: ok | B44: =H44&K44 -> 3.712/2025 | C44: =F44&L44 -> Usina 311/2025 | D44: =IF(J44=G44,0,1) -> 1 | E44: =IF(D44=0,"N/A",SUM($D44:D$83)) -> 19 | F44: Usina 3 | G44: =VLOOKUP(F44,Cad.Usinas!$A$4:$B$6,2,FALSE) -> 3023637013 | H44: 3.7 | I44: =VLOOKUP(H44,Cad.RateioConsumo!$B$4:$Z$106,2,FALSE) -> Fatima Abdel Hafiz Khalifa Cavalcanti | J44: =VLOOKUP(H44,Cad.RateioConsumo!$B$4:$Z$106,5,FALSE) -> 38398091 | K44: 12/2025 | L44: 11/2025 | M44: =VLOOKUP(H44,Cad.RateioConsumo!$B$4:$Z$106,7,FALSE) -> 1013.3846 | N44: =ROUND(VLOOKUP(H44,Cad.RateioConsumo!$B$4:$Z$106,11,FALSE),4) -> 0.0724 | O44: =IFERROR(ROUND(VLOOKUP(C44,Hist.Geração!$A$4:$F$64,4,FALSE)*N44,2)," ") -> 1137.26 | P44: =IFERROR(VLOOKUP(B44,Hist.Consum!$B$5:$V$120,12,FALSE),"") -> 30 | Q44: =IFERROR(VLOOKUP(B44,Hist.Consum!$B$5:$V$120,15,FALSE),"") -> 1096 | R44: =IFERROR(VLOOKUP(B44,Hist.Consum!$B$5:$W$120,22,FALSE),"") -> 1.1427 | S44: =IFERROR(Q44*R44,"") -> 1252.3992 | T44: =VLOOKUP(K44,Hist.BT!$A$4:$C$27,3,FALSE) -> Amarela | U44: =IFERROR(ROUND(VLOOKUP(T44,Hist.BT!$G$3:$I$6,3,FALSE)*Q44,2),"") -> 26.83 | V44: =IFERROR(ROUND(SUM(S44+U44)*(1-AG44),2),"") -> 1087.34 | W44: =S44+U44-V44 -> 191.8892 | X44: =O44-Q44 -> 41.26 | Y44: =SUMIF($J44:J$84,J44,$X44:X$84) -> 41.27 | AB44: =SUMIF($J44:J$84,J44,$Q44:Q$84) -> 1108.57 | AC44: =IFERROR(VLOOKUP(B44,Hist.Consum!$B$5:$AD$120,23,FALSE),"") -> 0.0007 | AD44: =IF((Y44/M44)>1,"Mudar Urgente",IF((Y44/M44)>0.4,"Rever Rateio",("ok"))) -> ok | AG44: =VLOOKUP(H44,Cad.RateioConsumo!$B$4:$Z$106,8,FALSE) -> 0.15
B45: =H45&K45 -> 3.012/2025 | C45: =F45&L45 -> Usina 311/2025 | D45: =IF(J45=G45,0,1) -> 0 | E45: =IF(D45=0,"N/A",SUM($D45:D$83)) -> N/A | F45: Usina 3 | G45: =VLOOKUP(F45,Cad.Usinas!$A$4:$B$6,2,FALSE) -> 3023637013 | H45: 3.0 | I45: =VLOOKUP(H45,Cad.RateioConsumo!$B$4:$Z$106,2,FALSE) -> Usina 3 | J45: =VLOOKUP(H45,Cad.RateioConsumo!$B$4:$Z$106,5,FALSE) -> 3023637013 | K45: 12/2025 | L45: 11/2025 | M45: =VLOOKUP(H45,Cad.RateioConsumo!$B$4:$Z$106,7,FALSE) -> 8931.2331 | N45: =ROUND(VLOOKUP(H45,Cad.RateioConsumo!$B$4:$Z$106,11,FALSE),4) -> 0.6799 | O45: =IFERROR(ROUND(VLOOKUP(C45,Hist.Geração!$A$4:$F$64,4,FALSE)*N45,2)," ") -> 10679.87 | P45: =IFERROR(VLOOKUP(B45,Hist.Consum!$B$5:$V$120,12,FALSE),"") -> 0 | Q45: =IFERROR(VLOOKUP(B45,Hist.Consum!$B$5:$V$120,15,FALSE),"") -> 0 | R45: =IFERROR(VLOOKUP(B45,Hist.Consum!$B$5:$W$120,22,FALSE),"") -> 1.1427 | S45: =IFERROR(Q45*R45,"") -> 0 | T45: =VLOOKUP(K45,Hist.BT!$A$4:$C$27,3,FALSE) -> Amarela | U45: =IFERROR(ROUND(VLOOKUP(T45,Hist.BT!$G$3:$I$6,3,FALSE)*Q45,2),"") -> 0 | V45: =IFERROR(ROUND(SUM(S45+U45)*(1-AG45),2),"") -> 0 | W45: =S45+U45-V45 -> 0 | X45: =O45-Q45 -> 10679.87 | Y45: =SUMIF($J45:J$84,J45,$X45:X$84) -> 75033.69 | AB45: =SUMIF($J45:J$84,J45,$Q45:Q$84) -> 0 | AC45: =IFERROR(VLOOKUP(B45,Hist.Consum!$B$5:$AD$120,23,FALSE),"") -> 0 | AG45: =VLOOKUP(H45,Cad.RateioConsumo!$B$4:$Z$106,8,FALSE) -> 0.15
B46: =H46&K46 | W46: =S46+U46-V46 -> 0 | AB46: =SUMIF($J46:J$84,J46,$Q46:Q$84) -> 0 | AC46: =IFERROR(VLOOKUP(B46,Hist.Consum!$B$5:$AD$120,23,FALSE),"") | AG46: =VLOOKUP(H46,Cad.RateioConsumo!$B$4:$Z$106,8,FALSE) -> #N/A
B47: =H47&K47 -> 1.011/2025 | C47: =F47&L47 -> Usina 110/2025 | D47: =IF(J47=G47,0,1) -> 0 | E47: =IF(D47=0,"N/A",SUM($D47:D$83)) -> N/A | F47: Usina 1 | G47: =VLOOKUP(F47,Cad.Usinas!$A$4:$B$6,2,FALSE) -> 3023633492 | H47: 1.0 | I47: =VLOOKUP(H47,Cad.RateioConsumo!$B$4:$Z$106,2,FALSE) -> Usina 1 | J47: =VLOOKUP(H47,Cad.RateioConsumo!$B$4:$Z$106,5,FALSE) -> 3023633492 | K47: 11/2025 | L47: 10/2025 | M47: =VLOOKUP(H47,Cad.RateioConsumo!$B$4:$Z$106,7,FALSE) -> 14000 | N47: =VLOOKUP(H47,Cad.RateioConsumo!$B$4:$Z$106,11,FALSE) -> 0.3201 | O47: =IFERROR(ROUND(VLOOKUP(C47,Hist.Geração!$A$4:$F$64,4,FALSE)*N47,2)," ") -> 5164.81 | P47: =IFERROR(VLOOKUP(B47,Hist.Consum!$B$5:$V$120,12,FALSE),"") -> 0 | Q47: =IFERROR(VLOOKUP(B47,Hist.Consum!$B$5:$V$120,15,FALSE),"") -> 0 | R47: =IFERROR(VLOOKUP(B47,Hist.Consum!$B$5:$W$120,22,FALSE),"") -> 1.172 | S47: =IFERROR(Q47*R47,"") -> 0 | T47: =VLOOKUP(K47,Hist.BT!$A$4:$C$27,3,FALSE) -> Vermelha 1 | U47: =IFERROR(ROUND(VLOOKUP(T47,Hist.BT!$G$3:$I$6,3,FALSE)*Q47,2),"") -> 0 | V47: =IFERROR(ROUND(SUM(S47+U47)*(1-AG47),2),"") -> 0 | W47: =S47+U47-V47 -> 0 | X47: =O47-Q47 -> 5164.81 | Y47: =SUMIF($J47:J$84,J47,$X47:X$84) -> 25231.56 | AB47: =SUMIF($J47:J$84,J47,$Q47:Q$84) -> 0 | AC47: =IFERROR(VLOOKUP(B47,Hist.Consum!$B$5:$AD$120,23,FALSE),"") -> 0 | AE47: =IFERROR(VLOOKUP(B47,Hist.Consum!$B$5:$AD$120,24,FALSE),"") -> A Equatorial cobrou errado uma tarida de GD2 , gerando itens que não são devidos: 1)Benefício Tarifário Bruto SCEE R$ 961,08 e 2) (-) Benefício Tarifário Líquido SCEE 702,62. O saldo deste valor foi dado como desconto para não te afetar os 15% de desconto na conta até que a Equatorial reverter esse valor. | AG47: =VLOOKUP(H47,Cad.RateioConsumo!$B$4:$Z$106,8,FALSE) -> 0.15
B48: =H48&K48 -> 2.111/2025 | C48: =F48&L48 -> Usina 210/2025 | D48: =IF(J48=G48,0,1) -> 1 | E48: =IF(D48=0,"N/A",SUM($D48:D$83)) -> 18 | F48: Usina 2 | G48: =VLOOKUP(F48,Cad.Usinas!$A$4:$B$6,2,FALSE) -> 3023594470 | H48: 2.1 | I48: =VLOOKUP(H48,Cad.RateioConsumo!$B$4:$Z$106,2,FALSE) -> Lucas Medeiros Lima | J48: =VLOOKUP(H48,Cad.RateioConsumo!$B$4:$Z$106,5,FALSE) -> 3002796782 | K48: 11/2025 | L48: 10/2025 | M48: =VLOOKUP(H48,Cad.RateioConsumo!$B$4:$Z$106,7,FALSE) -> 1536.5 | N48: =VLOOKUP(H48,Cad.RateioConsumo!$B$4:$Z$106,11,FALSE) -> 0.1098 | O48: =IFERROR(ROUND(VLOOKUP(C48,Hist.Geração!$A$4:$F$64,4,FALSE)*N48,2)," ") -> 1864.73 | P48: =IFERROR(VLOOKUP(B48,Hist.Consum!$B$5:$V$120,12,FALSE),"") -> 0 | Q48: =IFERROR(VLOOKUP(B48,Hist.Consum!$B$5:$V$120,15,FALSE),"") -> 1556 | R48: =IFERROR(VLOOKUP(B48,Hist.Consum!$B$5:$W$120,22,FALSE),"") -> 1.172 | S48: =IFERROR(Q48*R48,"") -> 1823.632 | T48: =VLOOKUP(K48,Hist.BT!$A$4:$C$27,3,FALSE) -> Vermelha 1 | U48: =IFERROR(ROUND(VLOOKUP(T48,Hist.BT!$G$3:$I$6,3,FALSE)*Q48,2),"") -> 90.19 | V48: =IFERROR(ROUND(SUM(S48+U48)*(1-AG48),2),"") -> 1626.75 | W48: =S48+U48-V48 -> 287.072 | X48: =O48-Q48 -> 308.73 | Y48: =SUMIF($J48:J$84,J48,$X48:X$84) -> #VALUE! | AC48: =IFERROR(VLOOKUP(B48,Hist.Consum!$B$5:$AD$120,23,FALSE),"") -> 258.46 | AD48: GD2 | AE48: =IFERROR(VLOOKUP(B48,Hist.Consum!$B$5:$AD$120,24,FALSE),"") -> A Equatorial errou no faturamento e cobrou indevidamente uma tarifa adicional:1)Benefício Tarifário Bruto SCEE e 2) (-) Benefício Tarifário Líquido SCEE . O saldo deste valor foi dado como desconto para não te afetar os 15% de desconto na conta até que a Equatorial reverter esse valor. | AG48: =VLOOKUP(H48,Cad.RateioConsumo!$B$4:$Z$106,8,FALSE) -> 0.15
A49: ok | B49: =H49&K49 -> 2.211/2025 | C49: =F49&L49 -> Usina 210/2025 | D49: =IF(J49=G49,0,1) -> 1 | E49: =IF(D49=0,"N/A",SUM($D49:D$83)) -> 17 | F49: Usina 2 | G49: =VLOOKUP(F49,Cad.Usinas!$A$4:$B$6,2,FALSE) -> 3023594470 | H49: 2.2 | I49: =VLOOKUP(H49,Cad.RateioConsumo!$B$4:$Z$106,2,FALSE) -> SORRISO SAUDE ODONTOLOGIA LTDA | J49: =VLOOKUP(H49,Cad.RateioConsumo!$B$4:$Z$106,5,FALSE) -> 3022893768 | K49: 11/2025 | L49: 10/2025 | M49: =VLOOKUP(H49,Cad.RateioConsumo!$B$4:$Z$106,7,FALSE) -> 859 | N49: =VLOOKUP(H49,Cad.RateioConsumo!$B$4:$Z$106,11,FALSE) -> 0.0614 | O49: =IFERROR(ROUND(VLOOKUP(C49,Hist.Geração!$A$4:$F$64,4,FALSE)*N49,2)," ") -> 1042.76 | P49: =IFERROR(VLOOKUP(B49,Hist.Consum!$B$5:$V$120,12,FALSE),"") -> 0 | Q49: =IFERROR(VLOOKUP(B49,Hist.Consum!$B$5:$V$120,15,FALSE),"") -> 902 | R49: =IFERROR(VLOOKUP(B49,Hist.Consum!$B$5:$W$120,22,FALSE),"") -> 1.172 | S49: =IFERROR(Q49*R49,"") -> 1057.144 | T49: =VLOOKUP(K49,Hist.BT!$A$4:$C$27,3,FALSE) -> Vermelha 1 | U49: =IFERROR(ROUND(VLOOKUP(T49,Hist.BT!$G$3:$I$6,3,FALSE)*Q49,2),"") -> 52.28 | V49: =IFERROR(ROUND(SUM(S49+U49)*(1-AG49),2),"") -> 920.82 | W49: =S49+U49-V49 -> 188.604 | X49: =O49-Q49 -> 140.76 | Y49: =SUMIF($J49:J$84,J49,$X49:X$84) -> 140.76 | AC49: =IFERROR(VLOOKUP(B49,Hist.Consum!$B$5:$AD$120,23,FALSE),"") -> 149.82 | AD49: GD2 | AE49: =IFERROR(VLOOKUP(B49,Hist.Consum!$B$5:$AD$120,24,FALSE),"") -> A Equatorial errou no faturamento e cobrou indevidamente uma tarifa adicional:1)Benefício Tarifário Bruto SCEE e 2) (-) Benefício Tarifário Líquido SCEE . O saldo deste valor foi dado como desconto para não te afetar os 15% de desconto na conta até que a Equatorial reverter esse valor. | AG49: =VLOOKUP(H49,Cad.RateioConsumo!$B$4:$Z$106,8,FALSE) -> 0.17
B50: =H50&K50 -> 2.011/2025 | C50: =F50&L50 -> Usina 210/2025 | D50: =IF(J50=G50,0,1) -> 0 | E50: =IF(D50=0,"N/A",SUM($D50:D$83)) -> N/A | F50: Usina 2 | G50: =VLOOKUP(F50,Cad.Usinas!$A$4:$B$6,2,FALSE) -> 3023594470 | H50: 2.0 | I50: =VLOOKUP(H50,Cad.RateioConsumo!$B$4:$Z$106,2,FALSE) -> Usina 2 | J50: =VLOOKUP(H50,Cad.RateioConsumo!$B$4:$Z$106,5,FALSE) -> 3023594470 | K50: 11/2025 | L50: 10/2025 | M50: =VLOOKUP(H50,Cad.RateioConsumo!$B$4:$Z$106,7,FALSE) -> 14000 | N50: =VLOOKUP(H50,Cad.RateioConsumo!$B$4:$Z$106,11,FALSE) -> 1 | O50: =IFERROR(ROUND(VLOOKUP(C50,Hist.Geração!$A$4:$F$64,4,FALSE)*N50,2)," ") -> 16983 | P50: =IFERROR(VLOOKUP(B50,Hist.Consum!$B$5:$V$120,12,FALSE),"") -> 0 | Q50: =IFERROR(VLOOKUP(B50,Hist.Consum!$B$5:$V$120,15,FALSE),"") -> 0 | R50: =IFERROR(VLOOKUP(B50,Hist.Consum!$B$5:$W$120,22,FALSE),"") -> 1.172 | S50: =IFERROR(Q50*R50,"") -> 0 | T50: =VLOOKUP(K50,Hist.BT!$A$4:$C$27,3,FALSE) -> Vermelha 1 | U50: =IFERROR(ROUND(VLOOKUP(T50,Hist.BT!$G$3:$I$6,3,FALSE)*Q50,2),"") -> 0 | V50: =IFERROR(ROUND(SUM(S50+U50)*(1-AG50),2),"") -> 0 | W50: =S50+U50-V50 -> 0 | X50: =O50-Q50 -> 16983 | Y50: =SUMIF($J50:J$84,J50,$X50:X$84) -> 81731 | AB50: =SUMIF($J50:J$84,J50,$Q50:Q$84) -> 0 | AC50: =IFERROR(VLOOKUP(B50,Hist.Consum!$B$5:$AD$120,23,FALSE),"") -> 0 | AG50: =VLOOKUP(H50,Cad.RateioConsumo!$B$4:$Z$106,8,FALSE) -> 0.15
B51: =H51&K51 -> 3.111/2025 | C51: =F51&L51 -> Usina 310/2025 | D51: =IF(J51=G51,0,1) -> 1 | E51: =IF(D51=0,"N/A",SUM($D51:D$83)) -> 16 | F51: Usina 3 | G51: =VLOOKUP(F51,Cad.Usinas!$A$4:$B$6,2,FALSE) -> 3023637013 | H51: 3.1 | I51: =VLOOKUP(H51,Cad.RateioConsumo!$B$4:$Z$106,2,FALSE) -> Associação dos Moradores do Residencial Araçagy | J51: =VLOOKUP(H51,Cad.RateioConsumo!$B$4:$Z$106,5,FALSE) -> 3021142432 | K51: 11/2025 | L51: 10/2025 | M51: =VLOOKUP(H51,Cad.RateioConsumo!$B$4:$Z$106,7,FALSE) -> 205.36364 | N51: =VLOOKUP(H51,Cad.RateioConsumo!$B$4:$Z$106,11,FALSE)/100 -> 0.000147 | O51: =IFERROR(ROUND(VLOOKUP(C51,Hist.Geração!$A$4:$F$64,4,FALSE)*N51,2)," ") -> 2.55 | P51: =IFERROR(VLOOKUP(B51,Hist.Consum!$B$5:$V$120,12,FALSE),"") -> 100 | Q51: =IFERROR(VLOOKUP(B51,Hist.Consum!$B$5:$V$120,15,FALSE),"") -> 156.81 | R51: =IFERROR(VLOOKUP(B51,Hist.Consum!$B$5:$W$120,22,FALSE),"") -> 1.172 | S51: =IFERROR(Q51*R51,"") -> 183.78132 | T51: =VLOOKUP(K51,Hist.BT!$A$4:$C$27,3,FALSE) -> Vermelha 1 | U51: =IFERROR(ROUND(VLOOKUP(T51,Hist.BT!$G$3:$I$6,3,FALSE)*Q51,2),"") -> 9.09 | V51: =IFERROR(ROUND(SUM(S51+U51)*(1-AG51),2),"") -> 163.94 | W51: =S51+U51-V51 -> 28.93132 | X51: =O51-Q51 -> -154.26 | Y51: =SUMIF($J51:J$84,J51,$X51:X$84) -> 66.26 | AB51: =SUMIF($J51:J$84,J51,$Q51:Q$84) -> 416.5 | AC51: =IFERROR(VLOOKUP(B51,Hist.Consum!$B$5:$AD$120,23,FALSE),"") -> 0 | AD51: Percentual errado | AE51: =Y51/M51 -> 0.32264719 | AG51: =VLOOKUP(H51,Cad.RateioConsumo!$B$4:$Z$106,8,FALSE) -> 0.15
B52: =H52&K52 -> 3.211/2025 | C52: =F52&L52 -> Usina 310/2025 | D52: =IF(J52=G52,0,1) -> 1 | E52: =IF(D52=0,"N/A",SUM($D52:D$83)) -> 15 | F52: Usina 3 | G52: =VLOOKUP(F52,Cad.Usinas!$A$4:$B$6,2,FALSE) -> 3023637013 | H52: 3.2 | I52: =VLOOKUP(H52,Cad.RateioConsumo!$B$4:$Z$106,2,FALSE) -> Associação dos Moradores do Residencial Araçagy | J52: =VLOOKUP(H52,Cad.RateioConsumo!$B$4:$Z$106,5,FALSE) -> 3021149593 | K52: 11/2025 | L52: 10/2025 | M52: =VLOOKUP(H52,Cad.RateioConsumo!$B$4:$Z$106,7,FALSE) -> 734.33333 | N52: =VLOOKUP(H52,Cad.RateioConsumo!$B$4:$Z$106,11,FALSE)/100 -> 0.000525 | O52: =IFERROR(ROUND(VLOOKUP(C52,Hist.Geração!$A$4:$F$64,4,FALSE)*N52,2)," ") -> 9.12 | P52: =IFERROR(VLOOKUP(B52,Hist.Consum!$B$5:$V$120,12,FALSE),"") -> 1086.92 | Q52: =IFERROR(VLOOKUP(B52,Hist.Consum!$B$5:$V$120,15,FALSE),"") -> 9.11 | R52: =IFERROR(VLOOKUP(B52,Hist.Consum!$B$5:$W$120,22,FALSE),"") -> 1.172 | S52: =IFERROR(Q52*R52,"") -> 10.67692 | T52: =VLOOKUP(K52,Hist.BT!$A$4:$C$27,3,FALSE) -> Vermelha 1 | U52: =IFERROR(ROUND(VLOOKUP(T52,Hist.BT!$G$3:$I$6,3,FALSE)*Q52,2),"") -> 0.53 | V52: =IFERROR(ROUND(SUM(S52+U52)*(1-AG52),2),"") -> 9.53 | W52: =S52+U52-V52 -> 1.67692 | X52: =O52-Q52 -> 0.01 | Y52: =SUMIF($J52:J$84,J52,$X52:X$84) -> 0.02 | AB52: =SUMIF($J52:J$84,J52,$Q52:Q$84) -> 1724.12 | AC52: =IFERROR(VLOOKUP(B52,Hist.Consum!$B$5:$AD$120,23,FALSE),"") -> 0 | AD52: Percentual errado | AG52: =VLOOKUP(H52,Cad.RateioConsumo!$B$4:$Z$106,8,FALSE) -> 0.15
B53: =H53&K53 -> 3.311/2025 | C53: =F53&L53 -> Usina 310/2025 | D53: =IF(J53=G53,0,1) -> 1 | E53: =IF(D53=0,"N/A",SUM($D53:D$83)) -> 14 | F53: Usina 3 | G53: =VLOOKUP(F53,Cad.Usinas!$A$4:$B$6,2,FALSE) -> 3023637013 | H53: 3.3 | I53: =VLOOKUP(H53,Cad.RateioConsumo!$B$4:$Z$106,2,FALSE) -> Associação dos Moradores do Residencial Araçagy | J53: =VLOOKUP(H53,Cad.RateioConsumo!$B$4:$Z$106,5,FALSE) -> 3021150559 | K53: 11/2025 | L53: 10/2025 | M53: =VLOOKUP(H53,Cad.RateioConsumo!$B$4:$Z$106,7,FALSE) -> 2086.4545 | N53: =10.71%/100 -> 0.001071 | O53: =IFERROR(ROUND(VLOOKUP(C53,Hist.Geração!$A$4:$F$64,4,FALSE)*N53,2)," ") -> 18.6 | P53: =IFERROR(VLOOKUP(B53,Hist.Consum!$B$5:$V$120,12,FALSE),"") -> 1012.83 | Q53: =IFERROR(VLOOKUP(B53,Hist.Consum!$B$5:$V$120,15,FALSE),"") -> 1276.97 | R53: =IFERROR(VLOOKUP(B53,Hist.Consum!$B$5:$W$120,22,FALSE),"") -> 1.172 | S53: =IFERROR(Q53*R53,"") -> 1496.6088 | T53: =VLOOKUP(K53,Hist.BT!$A$4:$C$27,3,FALSE) -> Vermelha 1 | U53: =IFERROR(ROUND(VLOOKUP(T53,Hist.BT!$G$3:$I$6,3,FALSE)*Q53,2),"") -> 74.01 | V53: =IFERROR(ROUND(SUM(S53+U53)*(1-AG53),2),"") -> 1335.03 | W53: =S53+U53-V53 -> 235.58884 | X53: =O53-Q53 -> -1258.37 | Y53: =SUMIF($J53:J$84,J53,$X53:X$84) -> 0.01 | AB53: =SUMIF($J53:J$84,J53,$Q53:Q$84) -> 4885.97 | AC53: =IFERROR(VLOOKUP(B53,Hist.Consum!$B$5:$AD$120,23,FALSE),"") -> 0 | AD53: Percentual errado | AE53: A Equatorial errou no percentual do rateio da geração. Para o próximo ciclo já será corrigido. Estou cobrando o refaturamento, mas ainda não consegui. | AG53: =VLOOKUP(H53,Cad.RateioConsumo!$B$4:$Z$106,8,FALSE) -> 0.15
B54: =H54&K54 -> 3.411/2025 | C54: =F54&L54 -> Usina 310/2025 | D54: =IF(J54=G54,0,1) -> 1 | E54: =IF(D54=0,"N/A",SUM($D54:D$83)) -> 13 | F54: Usina 3 | G54: =VLOOKUP(F54,Cad.Usinas!$A$4:$B$6,2,FALSE) -> 3023637013 | H54: 3.4 | I54: =VLOOKUP(H54,Cad.RateioConsumo!$B$4:$Z$106,2,FALSE) -> Antonio Jose Souza Filho | J54: =VLOOKUP(H54,Cad.RateioConsumo!$B$4:$Z$106,5,FALSE) -> 3007625048 | K54: 11/2025 | L54: 10/2025 | M54: =VLOOKUP(H54,Cad.RateioConsumo!$B$4:$Z$106,7,FALSE) -> 417.15385 | N54: =VLOOKUP(H54,Cad.RateioConsumo!$B$4:$Z$106,11,FALSE)/100 -> 0.000298 | O54: =IFERROR(ROUND(VLOOKUP(C54,Hist.Geração!$A$4:$F$64,4,FALSE)*N54,2)," ") -> 5.18 | P54: =IFERROR(VLOOKUP(B54,Hist.Consum!$B$5:$V$120,12,FALSE),"") -> 431.34 | Q54: =IFERROR(VLOOKUP(B54,Hist.Consum!$B$5:$V$120,15,FALSE),"") -> 36.65 | R54: =IFERROR(VLOOKUP(B54,Hist.Consum!$B$5:$W$120,22,FALSE),"") -> 1.172 | S54: =IFERROR(Q54*R54,"") -> 42.9538 | T54: =VLOOKUP(K54,Hist.BT!$A$4:$C$27,3,FALSE) -> Vermelha 1 | U54: =IFERROR(ROUND(VLOOKUP(T54,Hist.BT!$G$3:$I$6,3,FALSE)*Q54,2),"") -> 2.12 | V54: =IFERROR(ROUND(SUM(S54+U54)*(1-AG54),2),"") -> 38.31 | W54: =S54+U54-V54 -> 6.7638 | X54: =O54-Q54 -> -31.47 | Y54: =SUMIF($J54:J$84,J54,$X54:X$84) -> 2.8421709e-14 | AB54: =SUMIF($J54:J$84,J54,$Q54:Q$84) -> 978.65 | AC54: =IFERROR(VLOOKUP(B54,Hist.Consum!$B$5:$AD$120,23,FALSE),"") -> 0 | AD54: Percentual errado | AE54: A Equatorial errou no percentual do rateio da geração. Para o próximo ciclo já será corrigido. Estou cobrando o refaturamento, mas ainda não consegui. | AG54: =VLOOKUP(H54,Cad.RateioConsumo!$B$4:$Z$106,8,FALSE) -> 0.15
B55: =H55&K55 -> 3.511/2025 | C55: =F55&L55 -> Usina 310/2025 | D55: =IF(J55=G55,0,1) -> 1 | E55: =IF(D55=0,"N/A",SUM($D55:D$83)) -> 12 | F55: Usina 3 | G55: =VLOOKUP(F55,Cad.Usinas!$A$4:$B$6,2,FALSE) -> 3023637013 | H55: 3.5 | I55: =VLOOKUP(H55,Cad.RateioConsumo!$B$4:$Z$106,2,FALSE) -> João Carlos Pereira Dutra Filho | J55: =VLOOKUP(H55,Cad.RateioConsumo!$B$4:$Z$106,5,FALSE) -> 1163310 | K55: 11/2025 | L55: 10/2025 | M55: =VLOOKUP(H55,Cad.RateioConsumo!$B$4:$Z$106,7,FALSE) -> 848.69231 | N55: =VLOOKUP(H55,Cad.RateioConsumo!$B$4:$Z$106,11,FALSE)/100 -> 0.000606 | O55: =IFERROR(ROUND(VLOOKUP(C55,Hist.Geração!$A$4:$F$64,4,FALSE)*N55,2)," ") -> 10.53 | P55: =IFERROR(VLOOKUP(B55,Hist.Consum!$B$5:$V$120,12,FALSE),"") -> 899.47 | Q55: =IFERROR(VLOOKUP(B55,Hist.Consum!$B$5:$V$120,15,FALSE),"") -> 10.52 | R55: =IFERROR(VLOOKUP(B55,Hist.Consum!$B$5:$W$120,22,FALSE),"") -> 1.1698 | S55: =IFERROR(Q55*R55,"") -> 12.306296 | T55: =VLOOKUP(K55,Hist.BT!$A$4:$C$27,3,FALSE) -> Vermelha 1 | U55: =IFERROR(ROUND(VLOOKUP(T55,Hist.BT!$G$3:$I$6,3,FALSE)*Q55,2),"") -> 0.61 | V55: =IFERROR(ROUND(SUM(S55+U55)*(1-AG55),2),"") -> 10.98 | W55: =S55+U55-V55 -> 1.936296 | X55: =O55-Q55 -> 0.01 | Y55: =SUMIF(J47:$J$84,J55,X47:$X$84) -> 0.01 | AB55: =SUMIF(J47:$J$84,J55,Q47:$Q$84) -> 10.52 | AC55: =IFERROR(VLOOKUP(B55,Hist.Consum!$B$5:$AD$120,23,FALSE),"") -> 0 | AD55: =IF((Y55/M55)>1,"Mudar Urgente",IF((Y55/M55)>0.4,"Rever Rateio",("ok"))) -> ok | AG55: =VLOOKUP(H55,Cad.RateioConsumo!$B$4:$Z$106,8,FALSE) -> 0.15
B56: =H56&K56 -> 3.611/2025 | C56: =F56&L56 -> Usina 310/2025 | D56: =IF(J56=G56,0,1) -> 1 | E56: =IF(D56=0,"N/A",SUM($D56:D$83)) -> 11 | F56: Usina 3 | G56: =VLOOKUP(F56,Cad.Usinas!$A$4:$B$6,2,FALSE) -> 3023637013 | H56: 3.6 | I56: =VLOOKUP(H56,Cad.RateioConsumo!$B$4:$Z$106,2,FALSE) -> Patricia Maria Abreu Machado | J56: =VLOOKUP(H56,Cad.RateioConsumo!$B$4:$Z$106,5,FALSE) -> 3006793931 | K56: 11/2025 | L56: 10/2025 | M56: =VLOOKUP(H56,Cad.RateioConsumo!$B$4:$Z$106,7,FALSE) -> 776.76923 | N56: =VLOOKUP(H56,Cad.RateioConsumo!$B$4:$Z$106,11,FALSE)/100 -> 0.000555 | O56: =IFERROR(ROUND(VLOOKUP(C56,Hist.Geração!$A$4:$F$64,4,FALSE)*N56,2)," ") -> 9.64 | P56: =IFERROR(VLOOKUP(B56,Hist.Consum!$B$5:$V$120,12,FALSE),"") -> 850 | Q56: =O56 -> 9.64 | R56: =IFERROR(VLOOKUP(B56,Hist.Consum!$B$5:$W$120,22,FALSE),"") -> 1.1698 | S56: =IFERROR(Q56*R56,"") -> 11.276872 | T56: =VLOOKUP(K56,Hist.BT!$A$4:$C$27,3,FALSE) -> Vermelha 1 | U56: =IFERROR(ROUND(VLOOKUP(T56,Hist.BT!$G$3:$I$6,3,FALSE)*Q56,2),"") -> 0.56 | V56: =IFERROR(ROUND(SUM(S56+U56)*(1-AG56),2),"") -> 10.06 | W56: =S56+U56-V56 -> 1.776872 | X56: =O56-Q56 -> 0 | Y56: =SUMIF($J56:J$84,J56,$X56:X$84) -> 0 | AB56: =SUMIF($J56:J$84,J56,$Q56:Q$84) -> 9.64 | AC56: =IFERROR(VLOOKUP(B56,Hist.Consum!$B$5:$AD$120,23,FALSE),"") -> 0 | AD56: Percentual errado | AE56: A Equatorial errou no percentual do rateio da geração. Para o próximo ciclo já será corrigido. Estou cobrando o refaturamento, mas ainda não consegui. | AG56: =VLOOKUP(H56,Cad.RateioConsumo!$B$4:$Z$106,8,FALSE) -> 0.15
B57: =H57&K57 -> 3.711/2025 | C57: =F57&L57 -> Usina 310/2025 | D57: =IF(J57=G57,0,1) -> 1 | E57: =IF(D57=0,"N/A",SUM($D57:D$83)) -> 10 | F57: Usina 3 | G57: =VLOOKUP(F57,Cad.Usinas!$A$4:$B$6,2,FALSE) -> 3023637013 | H57: 3.7 | I57: =VLOOKUP(H57,Cad.RateioConsumo!$B$4:$Z$106,2,FALSE) -> Fatima Abdel Hafiz Khalifa Cavalcanti | J57: =VLOOKUP(H57,Cad.RateioConsumo!$B$4:$Z$106,5,FALSE) -> 38398091 | K57: 11/2025 | L57: 10/2025 | M57: =VLOOKUP(H57,Cad.RateioConsumo!$B$4:$Z$106,7,FALSE) -> 1013.3846 | N57: =VLOOKUP(H57,Cad.RateioConsumo!$B$4:$Z$106,11,FALSE)/100 -> 0.000724 | O57: =IFERROR(ROUND(VLOOKUP(C57,Hist.Geração!$A$4:$F$64,4,FALSE)*N57,2)," ") -> 12.58 | P57: =IFERROR(VLOOKUP(B57,Hist.Consum!$B$5:$V$120,12,FALSE),"") -> 1243.42 | Q57: =IFERROR(VLOOKUP(B57,Hist.Consum!$B$5:$V$120,15,FALSE),"") -> 12.57 | R57: =IFERROR(VLOOKUP(B57,Hist.Consum!$B$5:$W$120,22,FALSE),"") -> 1.172 | S57: =IFERROR(Q57*R57,"") -> 14.73204 | T57: =VLOOKUP(K57,Hist.BT!$A$4:$C$27,3,FALSE) -> Vermelha 1 | U57: =IFERROR(ROUND(VLOOKUP(T57,Hist.BT!$G$3:$I$6,3,FALSE)*Q57,2),"") -> 0.73 | V57: =IFERROR(ROUND(SUM(S57+U57)*(1-AG57),2),"") -> 13.14 | W57: =S57+U57-V57 -> 2.32204 | X57: =O57-Q57 -> 0.01 | Y57: =SUMIF($J57:J$84,J57,$X57:X$84) -> 0.01 | AB57: =SUMIF($J57:J$84,J57,$Q57:Q$84) -> 12.57 | AC57: =IFERROR(VLOOKUP(B57,Hist.Consum!$B$5:$AD$120,23,FALSE),"") -> 0 | AD57: =IF((Y57/M57)>1,"Mudar Urgente",IF((Y57/M57)>0.4,"Rever Rateio",("ok"))) -> ok | AG57: =VLOOKUP(H57,Cad.RateioConsumo!$B$4:$Z$106,8,FALSE) -> 0.15
B58: =H58&K58 -> 3.011/2025 | C58: =F58&L58 -> Usina 310/2025 | D58: =IF(J58=G58,0,1) -> 0 | E58: =IF(D58=0,"N/A",SUM($D58:D$83)) -> N/A | F58: Usina 3 | G58: =VLOOKUP(F58,Cad.Usinas!$A$4:$B$6,2,FALSE) -> 3023637013 | H58: 3.0 | I58: =VLOOKUP(H58,Cad.RateioConsumo!$B$4:$Z$106,2,FALSE) -> Usina 3 | J58: =VLOOKUP(H58,Cad.RateioConsumo!$B$4:$Z$106,5,FALSE) -> 3023637013 | K58: 11/2025 | L58: 10/2025 | M58: =VLOOKUP(H58,Cad.RateioConsumo!$B$4:$Z$106,7,FALSE) -> 8931.2331 | N58: =VLOOKUP(H58,Cad.RateioConsumo!$B$4:$Z$106,11,FALSE) -> 0.6799 | O58: =IFERROR(ROUND(VLOOKUP(C58,Hist.Geração!$A$4:$F$64,4,FALSE)*N58,2)," ") -> 11810.54 | P58: =IFERROR(VLOOKUP(B58,Hist.Consum!$B$5:$V$120,12,FALSE),"") -> 0 | Q58: =IFERROR(VLOOKUP(B58,Hist.Consum!$B$5:$V$120,15,FALSE),"") -> 0 | R58: =IFERROR(VLOOKUP(B58,Hist.Consum!$B$5:$W$120,22,FALSE),"") -> 1.172 | S58: =IFERROR(Q58*R58,"") -> 0 | T58: =VLOOKUP(K58,Hist.BT!$A$4:$C$27,3,FALSE) -> Vermelha 1 | U58: =IFERROR(ROUND(VLOOKUP(T58,Hist.BT!$G$3:$I$6,3,FALSE)*Q58,2),"") -> 0 | V58: =IFERROR(ROUND(SUM(S58+U58)*(1-AG58),2),"") -> 0 | W58: =S58+U58-V58 -> 0 | X58: =O58-Q58 -> 11810.54 | Y58: =SUMIF($J58:J$84,J58,$X58:X$84) -> 64353.82 | AB58: =SUMIF($J58:J$84,J58,$Q58:Q$84) -> 0 | AC58: =IFERROR(VLOOKUP(B58,Hist.Consum!$B$5:$AD$120,23,FALSE),"") -> 0 | AG58: =VLOOKUP(H58,Cad.RateioConsumo!$B$4:$Z$106,8,FALSE) -> 0.15
B59: =H59&K59 | W59: =S59+U59-V59 -> 0 | AB59: =SUMIF($J59:J$84,J59,$Q59:Q$84) -> 0 | AC59: =IFERROR(VLOOKUP(B59,Hist.Consum!$B$5:$AD$120,23,FALSE),"") | AG59: =VLOOKUP(H59,Cad.RateioConsumo!$B$4:$Z$106,8,FALSE) -> #N/A
B60: =H60&K60 -> 1.010/2025 | C60: =F60&L60 -> Usina 109/2025 | D60: =IF(J60=G60,0,1) -> 0 | E60: =IF(D60=0,"N/A",SUM($D60:D$83)) -> N/A | F60: Usina 1 | G60: =VLOOKUP(F60,Cad.Usinas!$A$4:$B$6,2,FALSE) -> 3023633492 | H60: 1.0 | I60: =VLOOKUP(H60,Cad.RateioConsumo!$B$4:$Z$106,2,FALSE) -> Usina 1 | J60: =VLOOKUP(H60,Cad.RateioConsumo!$B$4:$Z$106,5,FALSE) -> 3023633492 | K60: 10/2025 | L60: 09/2025 | M60: =VLOOKUP(H60,Cad.RateioConsumo!$B$4:$Z$106,7,FALSE) -> 14000 | N60: =VLOOKUP(H60,Cad.RateioConsumo!$B$4:$Z$106,11,FALSE) -> 0.3201 | O60: =IFERROR(ROUND(VLOOKUP(C60,Hist.Geração!$A$4:$F$64,4,FALSE)*N60,2)," ") -> 5405.53 | P60: =IFERROR(VLOOKUP(B60,Hist.Consum!$B$61:$V$120,12,FALSE),"") -> 0 | Q60: =IFERROR(VLOOKUP(B60,Hist.Consum!$B$61:$V$120,15,FALSE),"") -> 0 | R60: =IFERROR(VLOOKUP(B60,Hist.Consum!$B$61:$W$120,22,FALSE),"") -> 1.1698 | S60: =IFERROR(Q60*R60,"") -> 0 | T60: =VLOOKUP(K60,Hist.BT!$A$4:$C$27,3,FALSE) -> Vermelha 1 | U60: =IFERROR(ROUND(VLOOKUP(T60,Hist.BT!$G$3:$I$6,3,FALSE)*Q60,2),"") -> 0 | V60: =IFERROR(ROUND(SUM(S60+U60)*(1-15%),2),"") -> 0 | W60: =S60+U60-V60 -> 0 | X60: =O60-Q60 -> 5405.53 | Y60: =SUMIF($J60:J$84,J60,$X60:X$84) -> 20066.75 | AB60: =SUMIF($J60:J$84,J60,$Q60:Q$84) -> 0 | AG60: =VLOOKUP(H60,Cad.RateioConsumo!$B$4:$Z$106,8,FALSE) -> 0.15
B61: =H61&K61 -> 2.110/2025 | C61: =F61&L61 -> Usina 209/2025 | D61: =IF(J61=G61,0,1) -> 1 | E61: =IF(D61=0,"N/A",SUM($D61:D$83)) -> 9 | F61: Usina 2 | G61: =VLOOKUP(F61,Cad.Usinas!$A$4:$B$6,2,FALSE) -> 3023594470 | H61: 2.1 | I61: =VLOOKUP(H61,Cad.RateioConsumo!$B$4:$Z$106,2,FALSE) -> Lucas Medeiros Lima | J61: =VLOOKUP(H61,Cad.RateioConsumo!$B$4:$Z$106,5,FALSE) -> 3002796782 | K61: 10/2025 | L61: 09/2025 | M61: =VLOOKUP(H61,Cad.RateioConsumo!$B$4:$Z$106,7,FALSE) -> 1536.5 | N61: =VLOOKUP(H61,Cad.RateioConsumo!$B$4:$Z$106,11,FALSE) -> 0.1098 | O61: =IFERROR(ROUND(VLOOKUP(C61,Hist.Geração!$A$4:$F$64,4,FALSE)*N61,2)," ") -> 1837.17 | P61: =IFERROR(VLOOKUP(B61,Hist.Consum!$B$61:$V$120,12,FALSE),"") | Q61: =IFERROR(VLOOKUP(B61,Hist.Consum!$B$61:$V$120,15,FALSE),"") | R61: =IFERROR(VLOOKUP(B61,Hist.Consum!$B$61:$W$120,22,FALSE),"") | S61: =IFERROR(Q61*R61,"") | T61: =VLOOKUP(K61,Hist.BT!$A$4:$C$27,3,FALSE) -> Vermelha 1 | U61: =IFERROR(ROUND(VLOOKUP(T61,Hist.BT!$G$3:$I$6,3,FALSE)*Q61,2),"") | V61: =IFERROR(ROUND(SUM(S61+U61)*(1-15%),2),"") | W61: =S61+U61-V61 -> #VALUE! | X61: =O61-Q61 -> #VALUE! | Y61: =SUMIF($J61:J$84,J61,$X61:X$84) -> #VALUE! | AG61: =VLOOKUP(H61,Cad.RateioConsumo!$B$4:$Z$106,8,FALSE) -> 0.15
B62: =H62&K62 -> 2.010/2025 | C62: =F62&L62 -> Usina 209/2025 | D62: =IF(J62=G62,0,1) -> 0 | E62: =IF(D62=0,"N/A",SUM($D62:D$83)) -> N/A | F62: Usina 2 | G62: =VLOOKUP(F62,Cad.Usinas!$A$4:$B$6,2,FALSE) -> 3023594470 | H62: 2.0 | I62: =VLOOKUP(H62,Cad.RateioConsumo!$B$4:$Z$106,2,FALSE) -> Usina 2 | J62: =VLOOKUP(H62,Cad.RateioConsumo!$B$4:$Z$106,5,FALSE) -> 3023594470 | K62: 10/2025 | L62: 09/2025 | M62: =VLOOKUP(H62,Cad.RateioConsumo!$B$4:$Z$106,7,FALSE) -> 14000 | N62: =VLOOKUP(H62,Cad.RateioConsumo!$B$4:$Z$106,11,FALSE) -> 1 | O62: =IFERROR(ROUND(VLOOKUP(C62,Hist.Geração!$A$4:$F$64,4,FALSE)*N62,2)," ") -> 16732 | P62: =IFERROR(VLOOKUP(B62,Hist.Consum!$B$61:$V$120,12,FALSE),"") -> 0 | Q62: =IFERROR(VLOOKUP(B62,Hist.Consum!$B$61:$V$120,15,FALSE),"") -> 0 | R62: =IFERROR(VLOOKUP(B62,Hist.Consum!$B$61:$W$120,22,FALSE),"") -> 1.1698 | S62: =IFERROR(Q62*R62,"") -> 0 | T62: =VLOOKUP(K62,Hist.BT!$A$4:$C$27,3,FALSE) -> Vermelha 1 | U62: =IFERROR(ROUND(VLOOKUP(T62,Hist.BT!$G$3:$I$6,3,FALSE)*Q62,2),"") -> 0 | V62: =IFERROR(ROUND(SUM(S62+U62)*(1-15%),2),"") -> 0 | W62: =S62+U62-V62 -> 0 | X62: =O62-Q62 -> 16732 | Y62: =SUMIF($J62:J$84,J62,$X62:X$84) -> 64748 | AB62: =SUMIF($J62:J$84,J62,$Q62:Q$84) -> 0 | AG62: =VLOOKUP(H62,Cad.RateioConsumo!$B$4:$Z$106,8,FALSE) -> 0.15
B63: =H63&K63 -> 3.110/2025 | C63: =F63&L63 -> Usina 309/2025 | D63: =IF(J63=G63,0,1) -> 1 | E63: =IF(D63=0,"N/A",SUM($D63:D$83)) -> 8 | F63: Usina 3 | G63: =VLOOKUP(F63,Cad.Usinas!$A$4:$B$6,2,FALSE) -> 3023637013 | H63: 3.1 | I63: =VLOOKUP(H63,Cad.RateioConsumo!$B$4:$Z$106,2,FALSE) -> Associação dos Moradores do Residencial Araçagy | J63: =VLOOKUP(H63,Cad.RateioConsumo!$B$4:$Z$106,5,FALSE) -> 3021142432 | K63: 10/2025 | L63: 09/2025 | M63: =VLOOKUP(H63,Cad.RateioConsumo!$B$4:$Z$106,7,FALSE) -> 205.36364 | N63: =VLOOKUP(H63,Cad.RateioConsumo!$B$4:$Z$106,11,FALSE) -> 0.0147 | O63: =IFERROR(ROUND(VLOOKUP(C63,Hist.Geração!$A$4:$F$64,4,FALSE)*N63,2)," ") -> 240.17 | P63: =VLOOKUP(B63,Hist.Consum!$B$61:$S$135,12,FALSE) -> 100 | Q63: =IFERROR(VLOOKUP(B63,Hist.Consum!$B$61:$V$120,15,FALSE),"") -> 123.85 | R63: =IFERROR(VLOOKUP(B63,Hist.Consum!$B$61:$W$120,22,FALSE),"") -> 1.1698 | S63: =IFERROR(Q63*R63,"") -> 144.87973 | T63: =VLOOKUP(K63,Hist.BT!$A$4:$C$27,3,FALSE) -> Vermelha 1 | U63: =IFERROR(ROUND(VLOOKUP(T63,Hist.BT!$G$3:$I$6,3,FALSE)*Q63,2),"") -> 7.18 | V63: =IFERROR(ROUND(SUM(S63+U63)*(1-15%),2),"") -> 129.25 | W63: =S63+U63-V63 -> 22.80973 | X63: =O63-Q63 -> 116.32 | Y63: =SUMIF($J63:J$84,J63,$X63:X$84) -> 220.52 | AB63: =SUMIF($J63:J$84,J63,$Q63:Q$84) -> 259.69 | AD63: =IF((Y63/M63)>1,"Mudar Urgente",IF((Y63/M63)>0.4,"Rever Rateio",("ok"))) -> Mudar Urgente | AE63: =Y63/M63 -> 1.0738026 | AG63: =VLOOKUP(H63,Cad.RateioConsumo!$B$4:$Z$106,8,FALSE) -> 0.15
B64: =H64&K64 -> 3.210/2025 | C64: =F64&L64 -> Usina 309/2025 | D64: =IF(J64=G64,0,1) -> 1 | E64: =IF(D64=0,"N/A",SUM($D64:D$83)) -> 7 | F64: Usina 3 | G64: =VLOOKUP(F64,Cad.Usinas!$A$4:$B$6,2,FALSE) -> 3023637013 | H64: 3.2 | I64: =VLOOKUP(H64,Cad.RateioConsumo!$B$4:$Z$106,2,FALSE) -> Associação dos Moradores do Residencial Araçagy | J64: =VLOOKUP(H64,Cad.RateioConsumo!$B$4:$Z$106,5,FALSE) -> 3021149593 | K64: 10/2025 | L64: 09/2025 | M64: =VLOOKUP(H64,Cad.RateioConsumo!$B$4:$Z$106,7,FALSE) -> 734.33333 | N64: =VLOOKUP(H64,Cad.RateioConsumo!$B$4:$Z$106,11,FALSE) -> 0.0525 | O64: =IFERROR(ROUND(VLOOKUP(C64,Hist.Geração!$A$4:$F$64,4,FALSE)*N64,2)," ") -> 857.75 | P64: =VLOOKUP(B64,Hist.Consum!$B$61:$V$120,12,FALSE) -> 165.2 | Q64: =IFERROR(VLOOKUP(B64,Hist.Consum!$B$61:$V$120,15,FALSE),"") -> 857.74 | R64: =IFERROR(VLOOKUP(B64,Hist.Consum!$B$61:$W$120,22,FALSE),"") -> 1.1698 | S64: =IFERROR(Q64*R64,"") -> 1003.3843 | T64: =VLOOKUP(K64,Hist.BT!$A$4:$C$27,3,FALSE) -> Vermelha 1 | U64: =IFERROR(ROUND(VLOOKUP(T64,Hist.BT!$G$3:$I$6,3,FALSE)*Q64,2),"") -> 49.72 | V64: =IFERROR(ROUND(SUM(S64+U64)*(1-15%),2),"") -> 895.14 | W64: =S64+U64-V64 -> 157.96425 | X64: =O64-Q64 -> 0.01 | Y64: =SUMIF($J64:J$84,J64,$X64:X$84) -> 0.01 | AB64: =SUMIF($J64:J$84,J64,$Q64:Q$84) -> 1715.01 | AD64: =IF((Y64/M64)>1,"Mudar Urgente",IF((Y64/M64)>0.4,"Rever Rateio",("ok"))) -> ok | AG64: =VLOOKUP(H64,Cad.RateioConsumo!$B$4:$Z$106,8,FALSE) -> 0.15
B65: =H65&K65 -> 3.310/2025 | C65: =F65&L65 -> Usina 309/2025 | D65: =IF(J65=G65,0,1) -> 1 | E65: =IF(D65=0,"N/A",SUM($D65:D$83)) -> 6 | F65: Usina 3 | G65: =VLOOKUP(F65,Cad.Usinas!$A$4:$B$6,2,FALSE) -> 3023637013 | H65: 3.3 | I65: =VLOOKUP(H65,Cad.RateioConsumo!$B$4:$Z$106,2,FALSE) -> Associação dos Moradores do Residencial Araçagy | J65: =VLOOKUP(H65,Cad.RateioConsumo!$B$4:$Z$106,5,FALSE) -> 3021150559 | K65: 10/2025 | L65: 09/2025 | M65: =VLOOKUP(H65,Cad.RateioConsumo!$B$4:$Z$106,7,FALSE) -> 2086.4545 | N65: 0.149 | O65: =IFERROR(ROUND(VLOOKUP(C65,Hist.Geração!$A$4:$F$64,4,FALSE)*N65,2)," ") -> 2434.36 | P65: =VLOOKUP(B65,Hist.Consum!$B$61:$V$120,12,FALSE) -> 100 | Q65: =IFERROR(VLOOKUP(B65,Hist.Consum!$B$61:$V$120,15,FALSE),"") -> 1875.71 | R65: =IFERROR(VLOOKUP(B65,Hist.Consum!$B$61:$W$120,22,FALSE),"") -> 1.1698 | S65: =IFERROR(Q65*R65,"") -> 2194.2056 | T65: =VLOOKUP(K65,Hist.BT!$A$4:$C$27,3,FALSE) -> Vermelha 1 | U65: =IFERROR(ROUND(VLOOKUP(T65,Hist.BT!$G$3:$I$6,3,FALSE)*Q65,2),"") -> 108.72 | V65: =IFERROR(ROUND(SUM(S65+U65)*(1-15%),2),"") -> 1957.49 | W65: =S65+U65-V65 -> 345.43556 | X65: =O65-Q65 -> 558.65 | Y65: =SUMIF($J65:J$84,J65,$X65:X$84) -> 1258.38 | AB65: =SUMIF($J65:J$84,J65,$Q65:Q$84) -> 3609 | AD65: =IF((Y65/M65)>1,"Mudar Urgente",IF((Y65/M65)>0.4,"Rever Rateio",("ok"))) -> Rever Rateio | AG65: =VLOOKUP(H65,Cad.RateioConsumo!$B$4:$Z$106,8,FALSE) -> 0.15
B66: =H66&K66 -> 3.410/2025 | C66: =F66&L66 -> Usina 309/2025 | D66: =IF(J66=G66,0,1) -> 1 | E66: =IF(D66=0,"N/A",SUM($D66:D$83)) -> 5 | F66: Usina 3 | G66: =VLOOKUP(F66,Cad.Usinas!$A$4:$B$6,2,FALSE) -> 3023637013 | H66: 3.4 | I66: =VLOOKUP(H66,Cad.RateioConsumo!$B$4:$Z$106,2,FALSE) -> Antonio Jose Souza Filho | J66: =VLOOKUP(H66,Cad.RateioConsumo!$B$4:$Z$106,5,FALSE) -> 3007625048 | K66: 10/2025 | L66: 09/2025 | M66: =VLOOKUP(H66,Cad.RateioConsumo!$B$4:$Z$106,7,FALSE) -> 417.15385 | N66: =VLOOKUP(H66,Cad.RateioConsumo!$B$4:$Z$106,11,FALSE) -> 0.0298 | O66: =IFERROR(ROUND(VLOOKUP(C66,Hist.Geração!$A$4:$F$64,4,FALSE)*N66,2)," ") -> 486.87 | P66: =VLOOKUP(B66,Hist.Consum!$B$61:$V$120,12,FALSE) -> 30 | Q66: =IFERROR(VLOOKUP(B66,Hist.Consum!$B$61:$V$120,15,FALSE),"") -> 476 | R66: =IFERROR(VLOOKUP(B66,Hist.Consum!$B$61:$W$120,22,FALSE),"") -> 1.1698 | S66: =IFERROR(Q66*R66,"") -> 556.8248 | T66: =VLOOKUP(K66,Hist.BT!$A$4:$C$27,3,FALSE) -> Vermelha 1 | U66: =IFERROR(ROUND(VLOOKUP(T66,Hist.BT!$G$3:$I$6,3,FALSE)*Q66,2),"") -> 27.59 | V66: =IFERROR(ROUND(SUM(S66+U66)*(1-15%),2),"") -> 496.75 | W66: =S66+U66-V66 -> 87.6648 | X66: =O66-Q66 -> 10.87 | Y66: =SUMIF($J66:J$84,J66,$X66:X$84) -> 31.47 | AB66: =SUMIF($J66:J$84,J66,$Q66:Q$84) -> 942 | AD66: =IF((Y66/M66)>1,"Mudar Urgente",IF((Y66/M66)>0.4,"Rever Rateio",("ok"))) -> ok | AG66: =VLOOKUP(H66,Cad.RateioConsumo!$B$4:$Z$106,8,FALSE) -> 0.15
B67: =H67&K67 -> 3.010/2025 | C67: =F67&L67 -> Usina 309/2025 | D67: =IF(J67=G67,0,1) -> 0 | E67: =IF(D67=0,"N/A",SUM($D67:D$83)) -> N/A | F67: Usina 3 | G67: =VLOOKUP(F67,Cad.Usinas!$A$4:$B$6,2,FALSE) -> 3023637013 | H67: 3.0 | I67: =VLOOKUP(H67,Cad.RateioConsumo!$B$4:$Z$106,2,FALSE) -> Usina 3 | J67: =VLOOKUP(H67,Cad.RateioConsumo!$B$4:$Z$106,5,FALSE) -> 3023637013 | K67: 10/2025 | L67: 09/2025 | M67: =VLOOKUP(H67,Cad.RateioConsumo!$B$4:$Z$106,7,FALSE) -> 8931.2331 | N67: =VLOOKUP(H67,Cad.RateioConsumo!$B$4:$Z$106,11,FALSE) -> 0.6799 | O67: =IFERROR(ROUND(VLOOKUP(C67,Hist.Geração!$A$4:$F$64,4,FALSE)*N67,2)," ") -> 11108.21 | P67: =IFERROR(VLOOKUP(B67,Hist.Consum!$B$61:$V$120,12,FALSE),"") -> 0 | Q67: =IFERROR(VLOOKUP(B67,Hist.Consum!$B$61:$V$120,15,FALSE),"") -> 0 | R67: =IFERROR(VLOOKUP(B67,Hist.Consum!$B$61:$W$120,22,FALSE),"") -> 1.1698 | S67: =IFERROR(Q67*R67,"") -> 0 | T67: =VLOOKUP(K67,Hist.BT!$A$4:$C$27,3,FALSE) -> Vermelha 1 | U67: =IFERROR(ROUND(VLOOKUP(T67,Hist.BT!$G$3:$I$6,3,FALSE)*Q67,2),"") -> 0 | V67: =IFERROR(ROUND(SUM(S67+U67)*(1-15%),2),"") -> 0 | W67: =S67+U67-V67 -> 0 | X67: =O67-Q67 -> 11108.21 | Y67: =SUMIF($J67:J$84,J67,$X67:X$84) -> 52543.28 | AB67: =SUMIF($J67:J$84,J67,$Q67:Q$84) -> 0 | AG67: =VLOOKUP(H67,Cad.RateioConsumo!$B$4:$Z$106,8,FALSE) -> 0.15
B68: =H68&K68 | W68: =S68+U68-V68 -> 0 | AB68: =SUMIF($J68:J$84,J68,$Q68:Q$84) -> 0 | AG68: =VLOOKUP(H68,Cad.RateioConsumo!$B$4:$Z$106,8,FALSE) -> #N/A
B69: =H69&K69 -> 1.009/2025 | C69: =F69&L69 -> Usina 108/2025 | D69: =IF(J69=G69,0,1) -> 0 | E69: =IF(D69=0,"N/A",SUM($D69:D$83)) -> N/A | F69: Usina 1 | G69: =VLOOKUP(F69,Cad.Usinas!$A$4:$B$6,2,FALSE) -> 3023633492 | H69: 1.0 | I69: =VLOOKUP(H69,Cad.RateioConsumo!$B$4:$Z$106,2,FALSE) -> Usina 1 | J69: =VLOOKUP(H69,Cad.RateioConsumo!$B$4:$Z$106,5,FALSE) -> 3023633492 | K69: 09/2025 | L69: 08/2025 | M69: =VLOOKUP(H69,Cad.RateioConsumo!$B$4:$Z$106,7,FALSE) -> 14000 | N69: =VLOOKUP(H69,Cad.RateioConsumo!$B$4:$Z$106,11,FALSE) -> 0.3201 | O69: =IFERROR(ROUND(VLOOKUP(C69,Hist.Geração!$A$4:$F$64,4,FALSE)*N69,2)," ") -> 5312.7 | S69: =ROUND(Q69*R69,2) -> 0 | T69: =VLOOKUP(K69,Hist.BT!$A$4:$C$27,3,FALSE) -> Vermelha 2 | U69: =ROUND(VLOOKUP(T69,Hist.BT!$G$3:$I$6,3,FALSE)*Q69,2) -> 0 | V69: =ROUND(SUM(S69+U69)*(1-15%),2) -> 0 | W69: =S69+U69-V69 -> 0 | X69: =O69-Q69 -> 5312.7 | Y69: =SUMIF($J69:J$84,J69,$X69:X$84) -> 14661.22 | Z69: =VLOOKUP(B69,Hist.Consum!$B$71:$V$147,11,FALSE) -> 0 | AB69: =SUMIF($J69:J$84,J69,$Q69:Q$84) -> 0 | AG69: =VLOOKUP(H69,Cad.RateioConsumo!$B$4:$Z$106,8,FALSE) -> 0.15
B70: =H70&K70 -> 2.009/2025 | C70: =F70&L70 -> Usina 208/2025 | D70: =IF(J70=G70,0,1) -> 0 | E70: =IF(D70=0,"N/A",SUM($D70:D$83)) -> N/A | F70: Usina 2 | G70: =VLOOKUP(F70,Cad.Usinas!$A$4:$B$6,2,FALSE) -> 3023594470 | H70: 2.0 | I70: =VLOOKUP(H70,Cad.RateioConsumo!$B$4:$Z$106,2,FALSE) -> Usina 2 | J70: =VLOOKUP(H70,Cad.RateioConsumo!$B$4:$Z$106,5,FALSE) -> 3023594470 | K70: 09/2025 | L70: 08/2025 | M70: =VLOOKUP(H70,Cad.RateioConsumo!$B$4:$Z$106,7,FALSE) -> 14000 | N70: =VLOOKUP(H70,Cad.RateioConsumo!$B$4:$Z$106,11,FALSE) -> 1 | O70: =IFERROR(ROUND(VLOOKUP(C70,Hist.Geração!$A$4:$F$64,4,FALSE)*N70,2)," ") -> 16448 | S70: =ROUND(Q70*R70,2) -> 0 | T70: =VLOOKUP(K70,Hist.BT!$A$4:$C$27,3,FALSE) -> Vermelha 2 | U70: =ROUND(VLOOKUP(T70,Hist.BT!$G$3:$I$6,3,FALSE)*Q70,2) -> 0 | V70: =ROUND(SUM(S70+U70)*(1-15%),2) -> 0 | W70: =S70+U70-V70 -> 0 | X70: =O70-Q70 -> 16448 | Y70: =SUMIF($J70:J$84,J70,$X70:X$84) -> 48016 | Z70: =VLOOKUP(B70,Hist.Consum!$B$71:$V$147,11,FALSE) -> 0 | AB70: =SUMIF($J70:J$84,J70,$Q70:Q$84) -> 0 | AG70: =VLOOKUP(H70,Cad.RateioConsumo!$B$4:$Z$106,8,FALSE) -> 0.15
B71: =H71&K71 -> 3.109/2025 | C71: =F71&L71 -> Usina 308/2025 | D71: =IF(J71=G71,0,1) -> 1 | E71: =IF(D71=0,"N/A",SUM($D71:D$83)) -> 4 | F71: Usina 3 | G71: =VLOOKUP(F71,Cad.Usinas!$A$4:$B$6,2,FALSE) -> 3023637013 | H71: 3.1 | I71: =VLOOKUP(H71,Cad.RateioConsumo!$B$4:$Z$106,2,FALSE) -> Associação dos Moradores do Residencial Araçagy | J71: =VLOOKUP(H71,Cad.RateioConsumo!$B$4:$Z$106,5,FALSE) -> 3021142432 | K71: 09/2025 | L71: 08/2025 | M71: =VLOOKUP(H71,Cad.RateioConsumo!$B$4:$Z$106,7,FALSE) -> 205.36364 | N71: =VLOOKUP(H71,Cad.RateioConsumo!$B$4:$Z$106,11,FALSE) -> 0.0147 | O71: =IFERROR(ROUND(VLOOKUP(C71,Hist.Geração!$A$4:$F$64,4,FALSE)*N71,2)," ") -> 240.04 | P71: =VLOOKUP(B71,Hist.Consum!$B$71:$V$147,12,FALSE) -> 100 | Q71: =VLOOKUP(B71,Hist.Consum!$B$71:$V$147,15,FALSE()) -> 135.84 | R71: =VLOOKUP(B71,Hist.Consum!$B$71:$V$147,13,FALSE) -> 1.0037 | S71: =ROUND(Q71*R71,2) -> 136.34 | T71: =VLOOKUP(K71,Hist.BT!$A$4:$C$27,3,FALSE) -> Vermelha 2 | U71: =ROUND(VLOOKUP(T71,Hist.BT!$G$3:$I$6,3,FALSE)*Q71,2) -> 13.9 | V71: =ROUND(SUM(S71+U71)*(1-15%),2) -> 127.7 | W71: =S71+U71-V71 -> 22.54 | X71: =O71-Q71 -> 104.2 | Y71: =SUMIF($J71:J$84,J71,$X71:X$84) -> 104.2 | Z71: =VLOOKUP(B71,Hist.Consum!$B$71:$V$147,11,FALSE) -> 45924 | AB71: =SUMIF($J71:J$84,J71,$Q71:Q$84) -> 135.84 | AG71: =VLOOKUP(H71,Cad.RateioConsumo!$B$4:$Z$106,8,FALSE) -> 0.15
B72: =H72&K72 -> 3.209/2025 | C72: =F72&L72 -> Usina 308/2025 | D72: =IF(J72=G72,0,1) -> 1 | E72: =IF(D72=0,"N/A",SUM($D72:D$83)) -> 3 | F72: Usina 3 | G72: =VLOOKUP(F72,Cad.Usinas!$A$4:$B$6,2,FALSE) -> 3023637013 | H72: 3.2 | I72: =VLOOKUP(H72,Cad.RateioConsumo!$B$4:$Z$106,2,FALSE) -> Associação dos Moradores do Residencial Araçagy | J72: =VLOOKUP(H72,Cad.RateioConsumo!$B$4:$Z$106,5,FALSE) -> 3021149593 | K72: 09/2025 | L72: 08/2025 | M72: =VLOOKUP(H72,Cad.RateioConsumo!$B$4:$Z$106,7,FALSE) -> 734.33333 | N72: =VLOOKUP(H72,Cad.RateioConsumo!$B$4:$Z$106,11,FALSE) -> 0.0525 | O72: =IFERROR(ROUND(VLOOKUP(C72,Hist.Geração!$A$4:$F$64,4,FALSE)*N72,2)," ") -> 857.27 | P72: =VLOOKUP(B72,Hist.Consum!$B$71:$V$147,12,FALSE) -> 53.93 | Q72: =VLOOKUP(B72,Hist.Consum!$B$71:$V$147,15,FALSE()) -> 857.27 | R72: =VLOOKUP(B72,Hist.Consum!$B$71:$V$147,13,FALSE) -> 1.003523 | S72: =ROUND(Q72*R72,2) -> 860.29 | T72: =VLOOKUP(K72,Hist.BT!$A$4:$C$27,3,FALSE) -> Vermelha 2 | U72: =ROUND(VLOOKUP(T72,Hist.BT!$G$3:$I$6,3,FALSE)*Q72,2) -> 87.7 | V72: =ROUND(SUM(S72+U72)*(1-15%),2) -> 805.79 | W72: =S72+U72-V72 -> 142.2 | X72: =O72-Q72 -> 0 | Y72: =SUMIF($J72:J$84,J72,$X72:X$84) -> 0 | Z72: =VLOOKUP(B72,Hist.Consum!$B$71:$V$147,11,FALSE) -> 45924 | AB72: =SUMIF($J72:J$84,J72,$Q72:Q$84) -> 857.27 | AF72: =Y72/M72 -> 0 | AG72: =VLOOKUP(H72,Cad.RateioConsumo!$B$4:$Z$106,8,FALSE) -> 0.15
B73: =H73&K73 -> 3.309/2025 | C73: =F73&L73 -> Usina 308/2025 | D73: =IF(J73=G73,0,1) -> 1 | E73: =IF(D73=0,"N/A",SUM($D73:D$83)) -> 2 | F73: Usina 3 | G73: =VLOOKUP(F73,Cad.Usinas!$A$4:$B$6,2,FALSE) -> 3023637013 | H73: 3.3 | I73: =VLOOKUP(H73,Cad.RateioConsumo!$B$4:$Z$106,2,FALSE) -> Associação dos Moradores do Residencial Araçagy | J73: =VLOOKUP(H73,Cad.RateioConsumo!$B$4:$Z$106,5,FALSE) -> 3021150559 | K73: 09/2025 | L73: 08/2025 | M73: =VLOOKUP(H73,Cad.RateioConsumo!$B$4:$Z$106,7,FALSE) -> 2086.4545 | N73: 0.149 | O73: =IFERROR(ROUND(VLOOKUP(C73,Hist.Geração!$A$4:$F$64,4,FALSE)*N73,2)," ") -> 2433.02 | P73: =VLOOKUP(B73,Hist.Consum!$B$71:$V$147,12,FALSE) -> 100 | Q73: =VLOOKUP(B73,Hist.Consum!$B$71:$V$147,15,FALSE()) -> 1733.29 | R73: =VLOOKUP(B73,Hist.Consum!$B$71:$V$147,13,FALSE) -> 1.0037 | S73: =ROUND(Q73*R73,2) -> 1739.7 | T73: =VLOOKUP(K73,Hist.BT!$A$4:$C$27,3,FALSE) -> Vermelha 2 | U73: =ROUND(VLOOKUP(T73,Hist.BT!$G$3:$I$6,3,FALSE)*Q73,2) -> 177.31 | V73: =ROUND(SUM(S73+U73)*(1-15%),2) -> 1629.46 | W73: =S73+U73-V73 -> 287.55 | X73: =O73-Q73 -> 699.73 | Y73: =SUMIF($J73:J$84,J73,$X73:X$84) -> 699.73 | Z73: =VLOOKUP(B73,Hist.Consum!$B$71:$V$147,11,FALSE) -> 45924 | AB73: =SUMIF($J73:J$84,J73,$Q73:Q$84) -> 1733.29 | AF73: =X73/Q73 -> 0.40370048 | AG73: =VLOOKUP(H73,Cad.RateioConsumo!$B$4:$Z$106,8,FALSE) -> 0.15
B74: =H74&K74 -> 3.409/2025 | C74: =F74&L74 -> Usina 308/2025 | D74: =IF(J74=G74,0,1) -> 1 | E74: =IF(D74=0,"N/A",SUM($D74:D$83)) -> 1 | F74: Usina 3 | G74: =VLOOKUP(F74,Cad.Usinas!$A$4:$B$6,2,FALSE) -> 3023637013 | H74: 3.4 | I74: =VLOOKUP(H74,Cad.RateioConsumo!$B$4:$Z$106,2,FALSE) -> Antonio Jose Souza Filho | J74: =VLOOKUP(H74,Cad.RateioConsumo!$B$4:$Z$106,5,FALSE) -> 3007625048 | K74: 09/2025 | L74: 08/2025 | M74: =VLOOKUP(H74,Cad.RateioConsumo!$B$4:$Z$106,7,FALSE) -> 417.15385 | N74: =VLOOKUP(H74,Cad.RateioConsumo!$B$4:$Z$106,11,FALSE) -> 0.0298 | O74: =IFERROR(ROUND(VLOOKUP(C74,Hist.Geração!$A$4:$F$64,4,FALSE)*N74,2)," ") -> 486.6 | P74: =VLOOKUP(B74,Hist.Consum!$B$71:$V$147,12,FALSE) -> 30 | Q74: =VLOOKUP(B74,Hist.Consum!$B$71:$V$147,15,FALSE()) -> 466 | R74: =VLOOKUP(B74,Hist.Consum!$B$71:$V$147,13,FALSE) -> 1.014333 | S74: =ROUND(Q74*R74,2) -> 472.68 | T74: =VLOOKUP(K74,Hist.BT!$A$4:$C$27,3,FALSE) -> Vermelha 2 | U74: =ROUND(VLOOKUP(T74,Hist.BT!$G$3:$I$6,3,FALSE)*Q74,2) -> 47.67 | V74: =ROUND(SUM(S74+U74)*(1-15%),2) -> 442.3 | W74: =S74+U74-V74 -> 78.05 | X74: =O74-Q74 -> 20.6 | Y74: =SUMIF($J74:J$84,J74,$X74:X$84) -> 20.6 | Z74: =VLOOKUP(B74,Hist.Consum!$B$71:$V$147,11,FALSE) -> 45924 | AB74: =SUMIF($J74:J$84,J74,$Q74:Q$84) -> 466 | AF74: =Y74/M74 -> 0.049382261 | AG74: =VLOOKUP(H74,Cad.RateioConsumo!$B$4:$Z$106,8,FALSE) -> 0.15
B75: =H75&K75 -> 3.009/2025 | C75: =F75&L75 -> Usina 308/2025 | D75: =IF(J75=G75,0,1) -> 0 | E75: =IF(D75=0,"N/A",SUM($D75:D$83)) -> N/A | F75: Usina 3 | G75: =VLOOKUP(F75,Cad.Usinas!$A$4:$B$6,2,FALSE) -> 3023637013 | H75: 3.0 | I75: =VLOOKUP(H75,Cad.RateioConsumo!$B$4:$Z$106,2,FALSE) -> Usina 3 | J75: =VLOOKUP(H75,Cad.RateioConsumo!$B$4:$Z$106,5,FALSE) -> 3023637013 | K75: 09/2025 | L75: 08/2025 | M75: =VLOOKUP(H75,Cad.RateioConsumo!$B$4:$Z$106,7,FALSE) -> 8931.2331 | N75: =100%-SUM(N71:N74) -> 0.754 | O75: =IFERROR(ROUND(VLOOKUP(C75,Hist.Geração!$A$4:$F$64,4,FALSE)*N75,2)," ") -> 12312.07 | P75: =VLOOKUP(H75,Hist.Consum!$E$79:$S$135,7,FALSE) -> 0 | Q75: =VLOOKUP(H75,Hist.Consum!$E$79:$S$135,10,FALSE) -> 0 | R75: =VLOOKUP(H75,Hist.Consum!$E$79:$S$135,8,FALSE) -> 0 | S75: =ROUND(Q75*R75,2) -> 0 | T75: =VLOOKUP(K75,Hist.BT!$A$4:$C$27,3,FALSE) -> Vermelha 2 | U75: =ROUND(VLOOKUP(T75,Hist.BT!$G$3:$I$6,3,FALSE)*Q75,2) -> 0 | V75: =ROUND(SUM(S75+U75)*(1-15%),2) -> 0 | W75: =S75+U75-V75 -> 0 | X75: =O75-Q75 -> 12312.07 | Y75: =SUMIF($J75:J$84,J75,$X75:X$84) -> 41435.07 | Z75: =VLOOKUP(B75,Hist.Consum!$B$71:$V$147,11,FALSE) -> 0 | AB75: =SUMIF($J75:J$84,J75,$Q75:Q$84) -> 0 | AG75: =VLOOKUP(H75,Cad.RateioConsumo!$B$4:$Z$106,8,FALSE) -> 0.15
B76: =H76&K76 | AG76: =VLOOKUP(H76,Cad.RateioConsumo!$B$4:$Z$106,8,FALSE) -> #N/A
B77: =H77&K77 -> 1.008/2025 | C77: =F77&L77 -> Usina 108/2025 | D77: =IF(J77=G77,0,1) -> 0 | E77: =IF(D77=0,"N/A",SUM($D77:D$83)) -> N/A | F77: Usina 1 | G77: =VLOOKUP(F77,Cad.Usinas!$A$4:$B$6,2,FALSE) -> 3023633492 | H77: 1.0 | I77: =VLOOKUP(H77,Cad.RateioConsumo!$B$4:$Z$106,2,FALSE) -> Usina 1 | J77: =VLOOKUP(H77,Cad.RateioConsumo!$B$4:$Z$106,5,FALSE) -> 3023633492 | K77: 08/2025 | L77: 08/2025 | M77: =VLOOKUP(H77,Cad.RateioConsumo!$B$4:$Z$106,7,FALSE) -> 14000 | N77: =VLOOKUP(H77,Cad.RateioConsumo!$B$4:$Z$106,11,FALSE) -> 0.3201 | O77: =IFERROR(ROUND(VLOOKUP(C77,Hist.Geração!$A$4:$F$64,4,FALSE)*N77,2)," ") -> 5312.7 | T77: Vermelha – patamar 1 | V77: =SUM(S77+U77)*(1-15%) -> 0 | X77: =O77-Q77 -> 5312.7 | Y77: =SUMIF($J77:J$84,J77,$X77:X$84) -> 9348.52 | AG77: =VLOOKUP(H77,Cad.RateioConsumo!$B$4:$Z$106,8,FALSE) -> 0.15
B78: =H78&K78 -> 2.008/2025 | C78: =F78&L78 -> Usina 208/2025 | D78: =IF(J78=G78,0,1) -> 0 | E78: =IF(D78=0,"N/A",SUM($D78:D$83)) -> N/A | F78: Usina 2 | G78: =VLOOKUP(F78,Cad.Usinas!$A$4:$B$6,2,FALSE) -> 3023594470 | H78: 2.0 | I78: =VLOOKUP(H78,Cad.RateioConsumo!$B$4:$Z$106,2,FALSE) -> Usina 2 | J78: =VLOOKUP(H78,Cad.RateioConsumo!$B$4:$Z$106,5,FALSE) -> 3023594470 | K78: 08/2025 | L78: 08/2025 | M78: =VLOOKUP(H78,Cad.RateioConsumo!$B$4:$Z$106,7,FALSE) -> 14000 | N78: =VLOOKUP(H78,Cad.RateioConsumo!$B$4:$Z$106,11,FALSE) -> 1 | O78: =IFERROR(ROUND(VLOOKUP(C78,Hist.Geração!$A$4:$F$64,4,FALSE)*N78,2)," ") -> 16448 | T78: Vermelha – patamar 1 | V78: =SUM(S78+U78)*(1-15%) -> 0 | X78: =O78-Q78 -> 16448 | Y78: =SUMIF($J78:J$84,J78,$X78:X$84) -> 31568 | AG78: =VLOOKUP(H78,Cad.RateioConsumo!$B$4:$Z$106,8,FALSE) -> 0.15
B79: =H79&K79 -> 3.008/2025 | C79: =F79&L79 -> Usina 308/2025 | D79: =IF(J79=G79,0,1) -> 0 | E79: =IF(D79=0,"N/A",SUM($D79:D$83)) -> N/A | F79: Usina 3 | G79: =VLOOKUP(F79,Cad.Usinas!$A$4:$B$6,2,FALSE) -> 3023637013 | H79: 3.0 | I79: =VLOOKUP(H79,Cad.RateioConsumo!$B$4:$Z$106,2,FALSE) -> Usina 3 | J79: =VLOOKUP(H79,Cad.RateioConsumo!$B$4:$Z$106,5,FALSE) -> 3023637013 | K79: 08/2025 | L79: 08/2025 | M79: =VLOOKUP(H79,Cad.RateioConsumo!$B$4:$Z$106,7,FALSE) -> 8931.2331 | N79: 1 | O79: =IFERROR(ROUND(VLOOKUP(C79,Hist.Geração!$A$4:$F$64,4,FALSE)*N79,2)," ") -> 16329 | P79: =VLOOKUP(H79,Hist.Consum!$E$79:$S$135,7,FALSE) -> 0 | Q79: =VLOOKUP(H79,Hist.Consum!$E$79:$S$135,10,FALSE) -> 0 | R79: =VLOOKUP(H79,Hist.Consum!$E$79:$S$135,8,FALSE) -> 0 | T79: Vermelha – patamar 1 | V79: =SUM(S79+U79)*(1-15%) -> 0 | X79: =O79-Q79 -> 16329 | Y79: =SUMIF($J79:J$84,J79,$X79:X$84) -> 29123 | AG79: =VLOOKUP(H79,Cad.RateioConsumo!$B$4:$Z$106,8,FALSE) -> 0.15
B80: =H80&K80 | O80: =SUM(O71:O75) -> 16329 | AG80: =VLOOKUP(H80,Cad.RateioConsumo!$B$4:$Z$106,8,FALSE) -> #N/A
B81: =H81&K81 -> 1.007/2025 | C81: =F81&L81 -> Usina 107/2025 | D81: =IF(J81=G81,0,1) -> 0 | E81: =IF(D81=0,"N/A",SUM($D81:D$83)) -> N/A | F81: Usina 1 | G81: =VLOOKUP(F81,Cad.Usinas!$A$4:$B$6,2,FALSE) -> 3023633492 | H81: 1.0 | I81: =VLOOKUP(H81,Cad.RateioConsumo!$B$4:$Z$106,2,FALSE) -> Usina 1 | J81: =VLOOKUP(H81,Cad.RateioConsumo!$B$4:$Z$106,5,FALSE) -> 3023633492 | K81: 07/2025 | L81: 07/2025 | M81: =VLOOKUP(H81,Cad.RateioConsumo!$B$4:$Z$106,7,FALSE) -> 14000 | N81: =VLOOKUP(H81,Cad.RateioConsumo!$B$4:$Z$106,11,FALSE) -> 0.3201 | O81: =IFERROR(ROUND(VLOOKUP(C81,Hist.Geração!$A$4:$F$64,4,FALSE)*N81,2)," ") -> 4035.82 | T81: Vermelha – patamar 1 | V81: =SUM(S81+U81)*(1-15%) -> 0 | X81: =O81-Q81 -> 4035.82 | Y81: =SUMIF($J81:J$84,J81,$X81:X$84) -> 4035.82 | AG81: =VLOOKUP(H81,Cad.RateioConsumo!$B$4:$Z$106,8,FALSE) -> 0.15
B82: =H82&K82 -> 2.007/2025 | C82: =F82&L82 -> Usina 207/2025 | D82: =IF(J82=G82,0,1) -> 0 | E82: =IF(D82=0,"N/A",SUM($D82:D$83)) -> N/A | F82: Usina 2 | G82: =VLOOKUP(F82,Cad.Usinas!$A$4:$B$6,2,FALSE) -> 3023594470 | H82: 2.0 | I82: =VLOOKUP(H82,Cad.RateioConsumo!$B$4:$Z$106,2,FALSE) -> Usina 2 | J82: =VLOOKUP(H82,Cad.RateioConsumo!$B$4:$Z$106,5,FALSE) -> 3023594470 | K82: 07/2025 | L82: 07/2025 | M82: =VLOOKUP(H82,Cad.RateioConsumo!$B$4:$Z$106,7,FALSE) -> 14000 | N82: =VLOOKUP(H82,Cad.RateioConsumo!$B$4:$Z$106,11,FALSE) -> 1 | O82: =IFERROR(ROUND(VLOOKUP(C82,Hist.Geração!$A$4:$F$64,4,FALSE)*N82,2)," ") -> 15120 | T82: Vermelha – patamar 1 | V82: =SUM(S82+U82)*(1-15%) -> 0 | X82: =O82-Q82 -> 15120 | Y82: =SUMIF($J82:J$84,J82,$X82:X$84) -> 15120 | AG82: =VLOOKUP(H82,Cad.RateioConsumo!$B$4:$Z$106,8,FALSE) -> 0.15
B83: =H83&K83 -> 3.007/2025 | C83: =F83&L83 -> Usina 307/2025 | D83: =IF(J83=G83,0,1) -> 0 | E83: =IF(D83=0,"N/A",D83) -> N/A | F83: Usina 3 | G83: =VLOOKUP(F83,Cad.Usinas!$A$4:$B$6,2,FALSE) -> 3023637013 | H83: 3.0 | I83: =VLOOKUP(H83,Cad.RateioConsumo!$B$4:$Z$106,2,FALSE) -> Usina 3 | J83: =VLOOKUP(H83,Cad.RateioConsumo!$B$4:$Z$106,5,FALSE) -> 3023637013 | K83: 07/2025 | L83: 07/2025 | M83: =VLOOKUP(H83,Cad.RateioConsumo!$B$4:$Z$106,7,FALSE) -> 8931.2331 | N83: 1 | O83: =IFERROR(ROUND(VLOOKUP(C83,Hist.Geração!$A$4:$F$64,4,FALSE)*N83,2)," ") -> 12794 | P83: =VLOOKUP(H83,Hist.Consum!$E$79:$S$135,7,FALSE) -> 0 | Q83: =VLOOKUP(H83,Hist.Consum!$E$79:$S$135,10,FALSE) -> 0 | R83: =VLOOKUP(H83,Hist.Consum!$E$79:$S$135,8,FALSE) -> 0 | T83: Vermelha – patamar 1 | V83: =SUM(S83+U83)*(1-15%) -> 0 | X83: =O83-Q83 -> 12794 | Y83: =SUMIF($J83:J$84,J83,$X83:X$84) -> 12794 | AG83: =VLOOKUP(H83,Cad.RateioConsumo!$B$4:$Z$106,8,FALSE) -> 0.15
B84: =H84&K84 | AG84: =VLOOKUP(H84,Cad.RateioConsumo!$B$4:$Z$106,8,FALSE) -> #N/A

Sheet Faturas
A1: 1 | B1: 2 | C1: 3 | D1: 4 | E1: 5 | F1: 6 | G1: 7 | H1: 8 | I1: 9 | J1: 10 | K1: 11 | L1: 12 | M1: 13 | R1: Recibo | T1: 39 | X1: =YEAR(X7)&" "&MONTH(X7)&" Fatura e Medição"&" CC"&VLOOKUP($T$1,$A$5:$L$47,6,FALSE)&" "&S12 -> 2026 1 Fatura e Medição CC3006793931 Patricia Maria Abreu Machado | AO1: Envio a sua conta de energia de jan/26 com o crédito da geração solar!
AJ2: 1175.98 | AO2: Se você ficar com alguma dúvida estou a disposição
A3: Recibo | AJ3: 699.73 | AO3: A boa notícia é que depois de 8 meses com adicional de bandeira tarifária em jan/26 o governo aprovou a bandeira verde , portanto sem cobrança adicional na conta de luz
A4: Código | B4: Coluna1 | C4: Cliente | D4: Tipo | E4: Identificação | F4: Conta Contrato | G4: Coluna2 | H4: Referência | I4: Locação | J4: Vencimento | K4: Conta Contrato Geração | L4: Usina 3 | M4: Geração | N4: Consumo C.Acumulado | O4: FATURA | P4: ENVIO | U4: AMEL | V4: ="Recibo de Locação " -> Recibo de Locação | Z4: Dados do Cliente: | AE4: Mês de referência: | AJ4: =AJ2+AJ3 -> 1875.71
A5: 1 | B5: =VLOOKUP(A5,Medições!$E$3:$Y$89,4,FALSE) -> 3.4 | C5: =VLOOKUP(B5,Cad.RateioConsumo!$B$3:$Q$55,14,FALSE) -> Antonio Jose Souza Filho | D5: =IF(VLOOKUP(B5,Cad.RateioConsumo!$B$3:$Q$35,3,FALSE)="PF","CPF","CNPJ") -> CNPJ | E5: =VLOOKUP(B5,Cad.RateioConsumo!$B$3:$Q$35,4,FALSE) -> 682.957.583-49 | F5: =VLOOKUP(B5,Cad.RateioConsumo!$B$3:$Q$35,5,FALSE) -> 3007625048 | G5: =VLOOKUP(B5,Cad.RateioConsumo!$B$3:$Q$35,13,FALSE) -> R. 03 , 23 , LOT ALTO DO JAGUAREMA QD 05 LOT - ALTO DO JAGUAREMA QD 05 CEP: 65110-000 ARACAGY | H5: =VLOOKUP(A5,Medições!$E$3:$Y$95,7,FALSE) -> 09/2025 | I5: =VLOOKUP(A5,Medições!$E$3:$Y$95,18,FALSE) -> 442.3 | J5: =VLOOKUP(Faturas!$B5&Faturas!$H5,Hist.Consum!$B$61:$V$119,11,FALSE) -> 45924 | K5: =VLOOKUP(A5,Medições!$E$3:$Y$95,3,FALSE) -> 3023637013 | L5: =VLOOKUP(Faturas!$A5,Medições!$E$3:$Y$86,2,FALSE) -> Usina 3 | M5: =VLOOKUP(Faturas!$A5,Medições!$E$3:$Z$103,11,FALSE) -> 486.6 | N5: =VLOOKUP(Faturas!$A5,Medições!$E$3:$BA$97,24,FALSE) -> 466 | Z5: ="Nome do Cliente: "&S12 -> Nome do Cliente: Patricia Maria Abreu Machado | AE5: ="Referência: "&X7 -> Referência: 01/2026 | AO5: Assim como o demonstrativo, a fatura, e o boleto do mesmo período
A6: 2 | B6: =VLOOKUP(A6,Medições!$E$3:$Y$89,4,FALSE) -> 3.3 | C6: =VLOOKUP(B6,Cad.RateioConsumo!$B$3:$Q$55,14,FALSE) -> Associação dos Moradores do Residencial Araçagy | D6: =IF(VLOOKUP(B6,Cad.RateioConsumo!$B$3:$Q$35,3,FALSE)="PF","CPF","CNPJ") -> CNPJ | E6: =VLOOKUP(B6,Cad.RateioConsumo!$B$3:$Q$35,4,FALSE) -> 20.069.500/0001-97 | F6: =VLOOKUP(B6,Cad.RateioConsumo!$B$3:$Q$35,5,FALSE) -> 3021150559 | G6: =VLOOKUP(B6,Cad.RateioConsumo!$B$3:$Q$35,13,FALSE) -> R. Granja , s/n , CP 26 CS 36 PS 1, cep: 65138-000 Aracagi - Raposa - MA, | H6: =VLOOKUP(A6,Medições!$E$3:$Y$95,7,FALSE) -> 09/2025 | I6: =VLOOKUP(A6,Medições!$E$3:$Y$95,18,FALSE) -> 1629.46 | J6: =VLOOKUP(Faturas!$B6&Faturas!$H6,Hist.Consum!$B$61:$V$119,11,FALSE) -> 45924 | K6: =VLOOKUP(A6,Medições!$E$3:$Y$95,3,FALSE) -> 3023637013 | L6: =VLOOKUP(Faturas!$A6,Medições!$E$3:$Y$86,2,FALSE) -> Usina 3 | M6: =VLOOKUP(Faturas!$A6,Medições!$E$3:$Z$103,11,FALSE) -> 2433.02 | N6: =VLOOKUP(Faturas!$A6,Medições!$E$3:$BA$97,24,FALSE) -> 1733.29 | U6: ASSOCIACAO MARANHENSE DE ENERGIA LIMPA | V6: Nº | X6: =VLOOKUP(T1,$A$5:$L$77,1,FALSE) -> 39 | Z6: ="Conta Contrato da Cliente: "&VLOOKUP($T$1,$A$5:$L$47,6,FALSE) -> Conta Contrato da Cliente: 3006793931
A7: 3 | B7: =VLOOKUP(A7,Medições!$E$3:$Y$89,4,FALSE) -> 3.2 | C7: =VLOOKUP(B7,Cad.RateioConsumo!$B$3:$Q$55,14,FALSE) -> Associação dos Moradores do Residencial Araçagy | D7: =IF(VLOOKUP(B7,Cad.RateioConsumo!$B$3:$Q$35,3,FALSE)="PF","CPF","CNPJ") -> CNPJ | E7: =VLOOKUP(B7,Cad.RateioConsumo!$B$3:$Q$35,4,FALSE) -> 20.069.500/0001-97 | F7: =VLOOKUP(B7,Cad.RateioConsumo!$B$3:$Q$35,5,FALSE) -> 3021149593 | G7: =VLOOKUP(B7,Cad.RateioConsumo!$B$3:$Q$35,13,FALSE) -> R. da Agranja , 50 , CP 26 CS 36 PS 4, cep: 65138-000 Aracagi - Raposa - MA | H7: =VLOOKUP(A7,Medições!$E$3:$Y$95,7,FALSE) -> 09/2025 | I7: =VLOOKUP(A7,Medições!$E$3:$Y$95,18,FALSE) -> 805.79 | J7: =VLOOKUP(Faturas!$B7&Faturas!$H7,Hist.Consum!$B$61:$V$119,11,FALSE) -> 45924 | K7: =VLOOKUP(A7,Medições!$E$3:$Y$95,3,FALSE) -> 3023637013 | L7: =VLOOKUP(Faturas!$A7,Medições!$E$3:$Y$86,2,FALSE) -> Usina 3 | M7: =VLOOKUP(Faturas!$A7,Medições!$E$3:$Z$103,11,FALSE) -> 857.27 | N7: =VLOOKUP(Faturas!$A7,Medições!$E$3:$BA$97,24,FALSE) -> 857.27 | V7: Referência: | X7: =VLOOKUP(T1,$A$5:$L$77,8,FALSE) -> 01/2026 | AL7: =VLOOKUP($T$1,$A$5:$L$229,2,FALSE) -> 3.6
A8: 4 | B8: =VLOOKUP(A8,Medições!$E$3:$Y$89,4,FALSE) -> 3.1 | C8: =VLOOKUP(B8,Cad.RateioConsumo!$B$3:$Q$55,14,FALSE) -> Associação dos Moradores do Residencial Araçagy | D8: =IF(VLOOKUP(B8,Cad.RateioConsumo!$B$3:$Q$35,3,FALSE)="PF","CPF","CNPJ") -> CNPJ | E8: =VLOOKUP(B8,Cad.RateioConsumo!$B$3:$Q$35,4,FALSE) -> 20.069.500/0001-97 | F8: =VLOOKUP(B8,Cad.RateioConsumo!$B$3:$Q$35,5,FALSE) -> 3021142432 | G8: =VLOOKUP(B8,Cad.RateioConsumo!$B$3:$Q$35,13,FALSE) -> R. da Agranja , 50 , CP 26 CS 59 PS 1, CEP: 65138-000 Aracagi - Raposa - MA | H8: =VLOOKUP(A8,Medições!$E$3:$Y$95,7,FALSE) -> 09/2025 | I8: =VLOOKUP(A8,Medições!$E$3:$Y$95,18,FALSE) -> 127.7 | J8: =VLOOKUP(Faturas!$B8&Faturas!$H8,Hist.Consum!$B$61:$V$119,11,FALSE) -> 45924 | K8: =VLOOKUP(A8,Medições!$E$3:$Y$95,3,FALSE) -> 3023637013 | L8: =VLOOKUP(Faturas!$A8,Medições!$E$3:$Y$86,2,FALSE) -> Usina 3 | M8: =VLOOKUP(Faturas!$A8,Medições!$E$3:$Z$103,11,FALSE) -> 240.04 | N8: =VLOOKUP(Faturas!$A8,Medições!$E$3:$BA$97,24,FALSE) -> 135.84 | V8: Vencimento: | X8: =VLOOKUP(T1,$A$5:$L$77,10,FALSE) -> 46057 | Z8: Medição | AL8: =VLOOKUP($T$1,$A$5:$L$229,8,FALSE) -> 01/2026
A9: 5 | B9: =VLOOKUP(A9,Medições!$E$3:$Y$89,4,FALSE) -> 3.4 | C9: =VLOOKUP(B9,Cad.RateioConsumo!$B$3:$Q$55,14,FALSE) -> Antonio Jose Souza Filho | D9: =IF(VLOOKUP(B9,Cad.RateioConsumo!$B$3:$Q$35,3,FALSE)="PF","CPF","CNPJ") -> CNPJ | E9: =VLOOKUP(B9,Cad.RateioConsumo!$B$3:$Q$35,4,FALSE) -> 682.957.583-49 | F9: =VLOOKUP(B9,Cad.RateioConsumo!$B$3:$Q$35,5,FALSE) -> 3007625048 | G9: =VLOOKUP(B9,Cad.RateioConsumo!$B$3:$Q$35,13,FALSE) -> R. 03 , 23 , LOT ALTO DO JAGUAREMA QD 05 LOT - ALTO DO JAGUAREMA QD 05 CEP: 65110-000 ARACAGY | H9: =VLOOKUP(A9,Medições!$E$3:$Y$95,7,FALSE) -> 10/2025 | I9: =VLOOKUP(A9,Medições!$E$3:$Y$95,18,FALSE) -> 496.75 | J9: =VLOOKUP(Faturas!$B9&Faturas!$H9,Hist.Consum!$B$61:$V$119,11,FALSE) -> 45954 | K9: =VLOOKUP(A9,Medições!$E$3:$Y$95,3,FALSE) -> 3023637013 | L9: =VLOOKUP(Faturas!$A9,Medições!$E$3:$Y$86,2,FALSE) -> Usina 3 | M9: =VLOOKUP(Faturas!$A9,Medições!$E$3:$Z$103,11,FALSE) -> 486.87 | N9: =VLOOKUP(Faturas!$A9,Medições!$E$3:$BA$97,24,FALSE) -> 942 | U9: CNPJ: 61.434.675/0001-33 | V9: Condição: | X9: Á vista | Z9: Consumo pela Equatorial | AA9: Consumo Compensado | AB9: Tarifa Equatorial | AC9: Valor Energia Equatorial | AD9: Bandeira Tarifária | AE9: Adicional Bandeira | AF9: Fatura Locação Usina | AG9: Economia Real | AH9: =AL7&AL8 -> 3.601/2026
A10: 6 | B10: =VLOOKUP(A10,Medições!$E$3:$Y$89,4,FALSE) -> 3.3 | C10: =VLOOKUP(B10,Cad.RateioConsumo!$B$3:$Q$55,14,FALSE) -> Associação dos Moradores do Residencial Araçagy | D10: =IF(VLOOKUP(B10,Cad.RateioConsumo!$B$3:$Q$35,3,FALSE)="PF","CPF","CNPJ") -> CNPJ | E10: =VLOOKUP(B10,Cad.RateioConsumo!$B$3:$Q$35,4,FALSE) -> 20.069.500/0001-97 | F10: =VLOOKUP(B10,Cad.RateioConsumo!$B$3:$Q$35,5,FALSE) -> 3021150559 | G10: =VLOOKUP(B10,Cad.RateioConsumo!$B$3:$Q$35,13,FALSE) -> R. Granja , s/n , CP 26 CS 36 PS 1, cep: 65138-000 Aracagi - Raposa - MA, | H10: =VLOOKUP(A10,Medições!$E$3:$Y$95,7,FALSE) -> 10/2025 | I10: =VLOOKUP(A10,Medições!$E$3:$Y$95,18,FALSE) -> 1957.49 | J10: =VLOOKUP(Faturas!$B10&Faturas!$H10,Hist.Consum!$B$61:$V$119,11,FALSE) -> 45954 | K10: =VLOOKUP(A10,Medições!$E$3:$Y$95,3,FALSE) -> 3023637013 | L10: =VLOOKUP(Faturas!$A10,Medições!$E$3:$Y$86,2,FALSE) -> Usina 3 | M10: =VLOOKUP(Faturas!$A10,Medições!$E$3:$Z$103,11,FALSE) -> 2434.36 | N10: =VLOOKUP(Faturas!$A10,Medições!$E$3:$BA$97,24,FALSE) -> 3609
A11: 7 | B11: =VLOOKUP(A11,Medições!$E$3:$Y$89,4,FALSE) -> 3.2 | C11: =VLOOKUP(B11,Cad.RateioConsumo!$B$3:$Q$55,14,FALSE) -> Associação dos Moradores do Residencial Araçagy | D11: =IF(VLOOKUP(B11,Cad.RateioConsumo!$B$3:$Q$35,3,FALSE)="PF","CPF","CNPJ") -> CNPJ | E11: =VLOOKUP(B11,Cad.RateioConsumo!$B$3:$Q$35,4,FALSE) -> 20.069.500/0001-97 | F11: =VLOOKUP(B11,Cad.RateioConsumo!$B$3:$Q$35,5,FALSE) -> 3021149593 | G11: =VLOOKUP(B11,Cad.RateioConsumo!$B$3:$Q$35,13,FALSE) -> R. da Agranja , 50 , CP 26 CS 36 PS 4, cep: 65138-000 Aracagi - Raposa - MA | H11: =VLOOKUP(A11,Medições!$E$3:$Y$95,7,FALSE) -> 10/2025 | I11: =VLOOKUP(A11,Medições!$E$3:$Y$95,18,FALSE) -> 895.14 | J11: =VLOOKUP(Faturas!$B11&Faturas!$H11,Hist.Consum!$B$5:$V$119,11,FALSE) -> 45954 | K11: =VLOOKUP(A11,Medições!$E$3:$Y$95,3,FALSE) -> 3023637013 | L11: =VLOOKUP(Faturas!$A11,Medições!$E$3:$Y$86,2,FALSE) -> Usina 3 | M11: =VLOOKUP(Faturas!$A11,Medições!$E$3:$Z$103,11,FALSE) -> 857.75 | N11: =VLOOKUP(Faturas!$A11,Medições!$E$3:$BA$97,24,FALSE) -> 1715.01 | S11: Locatário: | Z11: (kWh) | AA11: (kWh) | AB11: (R$/kWh) | AC11: (R$) | AD11: Tipo | AE11: (R$) | AF11: (R$) | AG11: % | AO11: Simulação Conta Equatorial | AR11: Conta c/ Solar | AU11: Conta c/ Solar + erro Equatorial
A12: 8 | B12: =VLOOKUP(A12,Medições!$E$3:$Y$89,4,FALSE) -> 3.1 | C12: =VLOOKUP(B12,Cad.RateioConsumo!$B$3:$Q$55,14,FALSE) -> Associação dos Moradores do Residencial Araçagy | D12: =IF(VLOOKUP(B12,Cad.RateioConsumo!$B$3:$Q$35,3,FALSE)="PF","CPF","CNPJ") -> CNPJ | E12: =VLOOKUP(B12,Cad.RateioConsumo!$B$3:$Q$35,4,FALSE) -> 20.069.500/0001-97 | F12: =VLOOKUP(B12,Cad.RateioConsumo!$B$3:$Q$35,5,FALSE) -> 3021142432 | G12: =VLOOKUP(B12,Cad.RateioConsumo!$B$3:$Q$35,13,FALSE) -> R. da Agranja , 50 , CP 26 CS 59 PS 1, CEP: 65138-000 Aracagi - Raposa - MA | H12: =VLOOKUP(A12,Medições!$E$3:$Y$95,7,FALSE) -> 10/2025 | I12: =VLOOKUP(A12,Medições!$E$3:$Y$95,18,FALSE) -> 129.25 | J12: =VLOOKUP(Faturas!$B12&Faturas!$H12,Hist.Consum!$B$5:$V$119,11,FALSE) -> 45954 | K12: =VLOOKUP(A12,Medições!$E$3:$Y$95,3,FALSE) -> 3023637013 | L12: =VLOOKUP(Faturas!$A12,Medições!$E$3:$Y$86,2,FALSE) -> Usina 3 | M12: =VLOOKUP(Faturas!$A12,Medições!$E$3:$Z$103,11,FALSE) -> 240.17 | N12: =VLOOKUP(Faturas!$A12,Medições!$E$3:$BA$97,24,FALSE) -> 259.69 | S12: =VLOOKUP(T1,$A$5:$L$77,3,FALSE) -> Patricia Maria Abreu Machado | Z12: A | AA12: B | AB12: C | AC12: D=B*C | AD12: E | AE12: F=B*tarifa bandeira | AF12: G=(d+F)*(1-15%) | AG12: H=G/(D+F)-1 | AS12: desc
A13: 9 | B13: =VLOOKUP(A13,Medições!$E$3:$Y$89,4,FALSE) -> 2.1 | C13: =VLOOKUP(B13,Cad.RateioConsumo!$B$3:$Q$55,14,FALSE) -> Lucas Medeiros Lima | D13: =IF(VLOOKUP(B13,Cad.RateioConsumo!$B$3:$Q$35,3,FALSE)="PF","CPF","CNPJ") -> CNPJ | E13: =VLOOKUP(B13,Cad.RateioConsumo!$B$3:$Q$35,4,FALSE) -> 612.634.903-28 | F13: =VLOOKUP(B13,Cad.RateioConsumo!$B$3:$Q$35,5,FALSE) -> 3002796782 | G13: =VLOOKUP(B13,Cad.RateioConsumo!$B$3:$Q$35,13,FALSE) -> VL ARISTOTELES , S/N , RUA FRANCISCO MARCELINO DE MEDEIROS RUA FRANCISCO MARCELINO DE MEDEIROS CEP: 65728-000 CENTRO - LIMA CAMPOS - MA | H13: =VLOOKUP(A13,Medições!$E$3:$Y$95,7,FALSE) -> 10/2025 | I13: =VLOOKUP(A13,Medições!$E$3:$Y$95,18,FALSE) | J13: =VLOOKUP(Faturas!$B13&Faturas!$H13,Hist.Consum!$B$5:$V$119,11,FALSE) -> #N/A | K13: =VLOOKUP(A13,Medições!$E$3:$Y$95,3,FALSE) -> 3023594470 | L13: =VLOOKUP(Faturas!$A13,Medições!$E$3:$Y$86,2,FALSE) -> Usina 2 | M13: =VLOOKUP(Faturas!$A13,Medições!$E$3:$Z$103,11,FALSE) -> 1837.17 | N13: =VLOOKUP(Faturas!$A13,Medições!$E$3:$BA$97,24,FALSE) -> 0 | S13: =VLOOKUP(T1,$A$5:$L$77,4,FALSE)&": "&VLOOKUP(T1,$A$5:$L$77,5,FALSE) -> CNPJ: 676.211.553-53 | Z13: =VLOOKUP($T$1,Medições!$E$3:$Z$100,12,FALSE) -> 100 | AA13: =VLOOKUP($T$1,Medições!$E$3:$Z$100,13,FALSE) -> 713 | AB13: =AD28 -> 1.1286 | AC13: =AA13*AB13 -> 804.6918 | AD13: =VLOOKUP($T$1,Medições!$E$3:$Z$100,16,FALSE) -> Verde | AE13: =VLOOKUP($T$1,Medições!$E$3:$Z$100,17,FALSE) -> 0 | AF13: =VLOOKUP($T$1,Medições!$E$3:$Z$100,18,FALSE) -> 683.99 | AG13: =AF13/(AC13+AE13)-1 -> -0.14999755 | AO13: Energia | AQ13: =Z13 -> 100 | AR13: =AQ13*(1-AS13) -> 85.000245 | AS13: =-AG13 -> 0.14999755 | AU13: Locação | AV13: =AR13 -> 85.000245
A14: 10 | B14: =VLOOKUP(A14,Medições!$E$3:$Y$89,4,FALSE) -> 3.7 | C14: =VLOOKUP(B14,Cad.RateioConsumo!$B$3:$Q$55,14,FALSE) -> Fatima Abdel Hafiz Khalifa Cavalcanti | D14: =IF(VLOOKUP(B14,Cad.RateioConsumo!$B$3:$Q$35,3,FALSE)="PF","CPF","CNPJ") -> CNPJ | E14: =VLOOKUP(B14,Cad.RateioConsumo!$B$3:$Q$35,4,FALSE) -> 840.670.553-15 | F14: =VLOOKUP(B14,Cad.RateioConsumo!$B$3:$Q$35,5,FALSE) -> 38398091 | G14: =VLOOKUP(B14,Cad.RateioConsumo!$B$3:$Q$35,13,FALSE) -> Rua Nova nº63, Anil, São Luis, MA CEP: 65046-160 | H14: =VLOOKUP(A14,Medições!$E$3:$Y$95,7,FALSE) -> 11/2025 | I14: =VLOOKUP(A14,Medições!$E$3:$Y$95,18,FALSE) -> 13.14 | J14: =VLOOKUP(Faturas!$B14&Faturas!$H14,Hist.Consum!$B$5:$V$119,11,FALSE) -> 45997 | K14: =VLOOKUP(A14,Medições!$E$3:$Y$95,3,FALSE) -> 3023637013 | L14: =VLOOKUP(Faturas!$A14,Medições!$E$3:$Y$86,2,FALSE) -> Usina 3 | M14: =VLOOKUP(Faturas!$A14,Medições!$E$3:$Z$103,11,FALSE) -> 12.58 | N14: =VLOOKUP(Faturas!$A14,Medições!$E$3:$BA$97,24,FALSE) -> 12.57 | S14: ="Conta contrato: "&VLOOKUP($T$1,$A$5:$L$129,6) -> Conta contrato: 3006793931 | AO14: Energia Compensada | AQ14: =AA13 -> 713 | AR14: =AQ14*(1-AS14) -> #VALUE! | AS14: =-AG12 -> #VALUE! | AU14: Bandeira tarifária | AV14: =AR15 -> 0
A15: 11 | B15: =VLOOKUP(A15,Medições!$E$3:$Y$89,4,FALSE) -> 3.6 | C15: =VLOOKUP(B15,Cad.RateioConsumo!$B$3:$Q$55,14,FALSE) -> Patricia Maria Abreu Machado | D15: =IF(VLOOKUP(B15,Cad.RateioConsumo!$B$3:$Q$35,3,FALSE)="PF","CPF","CNPJ") -> CNPJ | E15: =VLOOKUP(B15,Cad.RateioConsumo!$B$3:$Q$35,4,FALSE) -> 676.211.553-53 | F15: =VLOOKUP(B15,Cad.RateioConsumo!$B$3:$Q$35,5,FALSE) -> 3006793931 | G15: =VLOOKUP(B15,Cad.RateioConsumo!$B$3:$Q$35,13,FALSE) -> R. MARIA F REIS , 20 , QD B CONJ BASA QD B CONJ BASA CEP: 65010-000 SAO FRANCISCO, na cidade de São Luís, Estado do Maranhão | H15: =VLOOKUP(A15,Medições!$E$3:$Y$95,7,FALSE) -> 11/2025 | I15: =VLOOKUP(A15,Medições!$E$3:$Y$95,18,FALSE) -> 10.06 | J15: =VLOOKUP(Faturas!$B15&Faturas!$H15,Hist.Consum!$B$5:$V$119,11,FALSE) -> 45965 | K15: =VLOOKUP(A15,Medições!$E$3:$Y$95,3,FALSE) -> 3023637013 | L15: =VLOOKUP(Faturas!$A15,Medições!$E$3:$Y$86,2,FALSE) -> Usina 3 | M15: =VLOOKUP(Faturas!$A15,Medições!$E$3:$Z$103,11,FALSE) -> 9.64 | N15: =VLOOKUP(Faturas!$A15,Medições!$E$3:$BA$97,24,FALSE) -> 9.64 | Z15: Composição do Saldo | AI15: Cálculo Co2 Evitado | AO15: Bandeira tarifária | AQ15: =AE13 -> 0 | AR15: =AQ15*(1-AS15) -> 0 | AS15: =-AG13 -> 0.14999755 | AU15: Desconto erro | AV15: =-AV23 -> 0
A16: 12 | B16: =VLOOKUP(A16,Medições!$E$3:$Y$89,4,FALSE) -> 3.5 | C16: =VLOOKUP(B16,Cad.RateioConsumo!$B$3:$Q$55,14,FALSE) -> João Carlos Pereira Dutra Filho | D16: =IF(VLOOKUP(B16,Cad.RateioConsumo!$B$3:$Q$35,3,FALSE)="PF","CPF","CNPJ") -> CNPJ | E16: =VLOOKUP(B16,Cad.RateioConsumo!$B$3:$Q$35,4,FALSE) -> 064837473-49 | F16: =VLOOKUP(B16,Cad.RateioConsumo!$B$3:$Q$35,5,FALSE) -> 1163310 | G16: =VLOOKUP(B16,Cad.RateioConsumo!$B$3:$Q$35,13,FALSE) -> R. 13 , 31 , QD 7 QD 7 CEP: 65010-000 PLN - VINHAIS II - SAO LUIS - MA | H16: =VLOOKUP(A16,Medições!$E$3:$Y$95,7,FALSE) -> 11/2025 | I16: =VLOOKUP(A16,Medições!$E$3:$Y$95,18,FALSE) -> 10.98 | J16: =VLOOKUP(Faturas!$B16&Faturas!$H16,Hist.Consum!$B$5:$V$119,11,FALSE) -> 45967 | K16: =VLOOKUP(A16,Medições!$E$3:$Y$95,3,FALSE) -> 3023637013 | L16: =VLOOKUP(Faturas!$A16,Medições!$E$3:$Y$86,2,FALSE) -> Usina 3 | M16: =VLOOKUP(Faturas!$A16,Medições!$E$3:$Z$103,11,FALSE) -> 10.53 | N16: =VLOOKUP(Faturas!$A16,Medições!$E$3:$BA$97,24,FALSE) -> 10.52 | T16: Item | U16: Descrição | V16: Preço (R$) | Z16: Energia da Sua Usina | AA16: Energia Consumida | AB16: Crédito Acumulado do Mês | AD16: Crédito Acumulado do Total | AI16: Consumo Compesado Acumulado | AJ16: CO2 | AU16: Sub-total | AV16: =SUM(AV13:AV15) -> 85.000245
A17: 13 | B17: =VLOOKUP(A17,Medições!$E$3:$Y$89,4,FALSE) -> 3.4 | C17: =VLOOKUP(B17,Cad.RateioConsumo!$B$3:$Q$55,14,FALSE) -> Antonio Jose Souza Filho | D17: =IF(VLOOKUP(B17,Cad.RateioConsumo!$B$3:$Q$35,3,FALSE)="PF","CPF","CNPJ") -> CNPJ | E17: =VLOOKUP(B17,Cad.RateioConsumo!$B$3:$Q$35,4,FALSE) -> 682.957.583-49 | F17: =VLOOKUP(B17,Cad.RateioConsumo!$B$3:$Q$35,5,FALSE) -> 3007625048 | G17: =VLOOKUP(B17,Cad.RateioConsumo!$B$3:$Q$35,13,FALSE) -> R. 03 , 23 , LOT ALTO DO JAGUAREMA QD 05 LOT - ALTO DO JAGUAREMA QD 05 CEP: 65110-000 ARACAGY | H17: =VLOOKUP(A17,Medições!$E$3:$Y$95,7,FALSE) -> 11/2025 | I17: =VLOOKUP(A17,Medições!$E$3:$Y$95,18,FALSE) -> 38.31 | J17: =VLOOKUP(Faturas!$B17&Faturas!$H17,Hist.Consum!$B$5:$V$119,11,FALSE) -> 45985 | K17: =VLOOKUP(A17,Medições!$E$3:$Y$95,3,FALSE) -> 3023637013 | L17: =VLOOKUP(Faturas!$A17,Medições!$E$3:$Y$86,2,FALSE) -> Usina 3 | M17: =VLOOKUP(Faturas!$A17,Medições!$E$3:$Z$103,11,FALSE) -> 5.18 | N17: =VLOOKUP(Faturas!$A17,Medições!$E$3:$BA$97,24,FALSE) -> 978.65 | V17: Quant | W17: Unit. | X17: Total | AI17: =VLOOKUP(T1,$A$4:$N$29,14,FALSE) -> #N/A | AO17: Total | AQ17: =AQ13+AQ15 -> 100 | AR17: =AR13+AR15 -> 85.000245
A18: 14 | B18: =VLOOKUP(A18,Medições!$E$3:$Y$89,4,FALSE) -> 3.3 | C18: =VLOOKUP(B18,Cad.RateioConsumo!$B$3:$Q$55,14,FALSE) -> Associação dos Moradores do Residencial Araçagy | D18: =IF(VLOOKUP(B18,Cad.RateioConsumo!$B$3:$Q$35,3,FALSE)="PF","CPF","CNPJ") -> CNPJ | E18: =VLOOKUP(B18,Cad.RateioConsumo!$B$3:$Q$35,4,FALSE) -> 20.069.500/0001-97 | F18: =VLOOKUP(B18,Cad.RateioConsumo!$B$3:$Q$35,5,FALSE) -> 3021150559 | G18: =VLOOKUP(B18,Cad.RateioConsumo!$B$3:$Q$35,13,FALSE) -> R. Granja , s/n , CP 26 CS 36 PS 1, cep: 65138-000 Aracagi - Raposa - MA, | H18: =VLOOKUP(A18,Medições!$E$3:$Y$95,7,FALSE) -> 11/2025 | I18: =VLOOKUP(A18,Medições!$E$3:$Y$95,18,FALSE) -> 1335.03 | J18: =VLOOKUP(Faturas!$B18&Faturas!$H18,Hist.Consum!$B$5:$V$119,11,FALSE) -> 45985 | K18: =VLOOKUP(A18,Medições!$E$3:$Y$95,3,FALSE) -> 3023637013 | L18: =VLOOKUP(Faturas!$A18,Medições!$E$3:$Y$86,2,FALSE) -> Usina 3 | M18: =VLOOKUP(Faturas!$A18,Medições!$E$3:$Z$103,11,FALSE) -> 18.6 | N18: =VLOOKUP(Faturas!$A18,Medições!$E$3:$BA$97,24,FALSE) -> 4885.97 | T18: 1 | U18: Locação de Usina Fotovoltaica | V18: 1 | W18: =VLOOKUP($T$1,$A$4:$L$45,9,FALSE) -> 683.99 | X18: =V18*W18 -> 683.99 | Z18: (kWh) | AA18: (kWh) | AB18: (kWh) | AD18: (kWh) | AU18: Itens Adicionais
A19: 15 | B19: =VLOOKUP(A19,Medições!$E$3:$Y$89,4,FALSE) -> 3.2 | C19: =VLOOKUP(B19,Cad.RateioConsumo!$B$3:$Q$55,14,FALSE) -> Associação dos Moradores do Residencial Araçagy | D19: =IF(VLOOKUP(B19,Cad.RateioConsumo!$B$3:$Q$35,3,FALSE)="PF","CPF","CNPJ") -> CNPJ | E19: =VLOOKUP(B19,Cad.RateioConsumo!$B$3:$Q$35,4,FALSE) -> 20.069.500/0001-97 | F19: =VLOOKUP(B19,Cad.RateioConsumo!$B$3:$Q$35,5,FALSE) -> 3021149593 | G19: =VLOOKUP(B19,Cad.RateioConsumo!$B$3:$Q$35,13,FALSE) -> R. da Agranja , 50 , CP 26 CS 36 PS 4, cep: 65138-000 Aracagi - Raposa - MA | H19: =VLOOKUP(A19,Medições!$E$3:$Y$95,7,FALSE) -> 11/2025 | I19: =VLOOKUP(A19,Medições!$E$3:$Y$95,18,FALSE) -> 9.53 | J19: =VLOOKUP(Faturas!$B19&Faturas!$H19,Hist.Consum!$B$5:$V$119,11,FALSE) -> 45985 | K19: =VLOOKUP(A19,Medições!$E$3:$Y$95,3,FALSE) -> 3023637013 | L19: =VLOOKUP(Faturas!$A19,Medições!$E$3:$Y$86,2,FALSE) -> Usina 3 | M19: =VLOOKUP(Faturas!$A19,Medições!$E$3:$Z$103,11,FALSE) -> 9.12 | N19: =VLOOKUP(Faturas!$A19,Medições!$E$3:$BA$97,24,FALSE) -> 1724.12 | Z19: =VLOOKUP($T$1,Medições!$E$3:$Z$97,11,FALSE) -> 792.32 | AA19: =AA13 -> 713 | AB19: =Z19-AA19 -> 79.32 | AD19: =VLOOKUP(T1,Medições!$E$3:$Z$103,21,FALSE) -> 158.64 | AO19: Itens adicionais | AU19: =AO20 -> Cip-Ilum Pub Pref Munic | AV19: =AQ20 -> 102.58
A20: 16 | B20: =VLOOKUP(A20,Medições!$E$3:$Y$89,4,FALSE) -> 3.1 | C20: =VLOOKUP(B20,Cad.RateioConsumo!$B$3:$Q$55,14,FALSE) -> Associação dos Moradores do Residencial Araçagy | D20: =IF(VLOOKUP(B20,Cad.RateioConsumo!$B$3:$Q$35,3,FALSE)="PF","CPF","CNPJ") -> CNPJ | E20: =VLOOKUP(B20,Cad.RateioConsumo!$B$3:$Q$35,4,FALSE) -> 20.069.500/0001-97 | F20: =VLOOKUP(B20,Cad.RateioConsumo!$B$3:$Q$35,5,FALSE) -> 3021142432 | G20: =VLOOKUP(B20,Cad.RateioConsumo!$B$3:$Q$35,13,FALSE) -> R. da Agranja , 50 , CP 26 CS 59 PS 1, CEP: 65138-000 Aracagi - Raposa - MA | H20: =VLOOKUP(A20,Medições!$E$3:$Y$95,7,FALSE) -> 11/2025 | I20: =VLOOKUP(A20,Medições!$E$3:$Y$95,18,FALSE) -> 163.94 | J20: =VLOOKUP(Faturas!$B20&Faturas!$H20,Hist.Consum!$B$5:$V$119,11,FALSE) -> 45985 | K20: =VLOOKUP(A20,Medições!$E$3:$Y$95,3,FALSE) -> 3023637013 | L20: =VLOOKUP(Faturas!$A20,Medições!$E$3:$Y$86,2,FALSE) -> Usina 3 | M20: =VLOOKUP(Faturas!$A20,Medições!$E$3:$Z$103,11,FALSE) -> 2.55 | N20: =VLOOKUP(Faturas!$A20,Medições!$E$3:$BA$97,24,FALSE) -> 416.5 | AO20: Cip-Ilum Pub Pref Munic | AQ20: 102.58 | AR20: =AQ20 -> 102.58 | AU20: =AO21 -> Multa | AV20: =AQ21 -> 40.32
A21: 17 | B21: =VLOOKUP(A21,Medições!$E$3:$Y$89,4,FALSE) -> 2.2 | C21: =VLOOKUP(B21,Cad.RateioConsumo!$B$3:$Q$55,14,FALSE) -> SORRISO SAUDE ODONTOLOGIA LTDA | D21: =IF(VLOOKUP(B21,Cad.RateioConsumo!$B$3:$Q$35,3,FALSE)="PF","CPF","CNPJ") -> CNPJ | E21: =VLOOKUP(B21,Cad.RateioConsumo!$B$3:$Q$35,4,FALSE) -> 60.080.581/0001-40 | F21: =VLOOKUP(B21,Cad.RateioConsumo!$B$3:$Q$35,5,FALSE) -> 3022893768 | G21: =VLOOKUP(B21,Cad.RateioConsumo!$B$3:$Q$35,13,FALSE) -> AV RAIMUNDO CORREIA DA SILVA , 1346 , B B CEP: 65633-641 CIDADE NOVA - TIMON - MA | H21: =VLOOKUP(A21,Medições!$E$3:$Y$95,7,FALSE) -> 11/2025 | I21: =VLOOKUP(A21,Medições!$E$3:$Y$95,18,FALSE) -> 920.82 | J21: 45989 | K21: =VLOOKUP(A21,Medições!$E$3:$Y$95,3,FALSE) -> 3023594470 | L21: =VLOOKUP(Faturas!$A21,Medições!$E$3:$Y$86,2,FALSE) -> Usina 2 | M21: =VLOOKUP(Faturas!$A21,Medições!$E$3:$Z$103,11,FALSE) -> 1042.76 | N21: =VLOOKUP(Faturas!$A21,Medições!$E$3:$BA$97,24,FALSE) -> 0 | AO21: Multa | AQ21: 40.32 | AR21: =AQ21 -> 40.32 | AU21: =AO22 -> Correção Monetária | AV21: =AQ22 -> 5.71
A22: 18 | B22: =VLOOKUP(A22,Medições!$E$3:$Y$89,4,FALSE) -> 2.1 | C22: =VLOOKUP(B22,Cad.RateioConsumo!$B$3:$Q$55,14,FALSE) -> Lucas Medeiros Lima | D22: =IF(VLOOKUP(B22,Cad.RateioConsumo!$B$3:$Q$35,3,FALSE)="PF","CPF","CNPJ") -> CNPJ | E22: =VLOOKUP(B22,Cad.RateioConsumo!$B$3:$Q$35,4,FALSE) -> 612.634.903-28 | F22: =VLOOKUP(B22,Cad.RateioConsumo!$B$3:$Q$35,5,FALSE) -> 3002796782 | G22: =VLOOKUP(B22,Cad.RateioConsumo!$B$3:$Q$35,13,FALSE) -> VL ARISTOTELES , S/N , RUA FRANCISCO MARCELINO DE MEDEIROS RUA FRANCISCO MARCELINO DE MEDEIROS CEP: 65728-000 CENTRO - LIMA CAMPOS - MA | H22: =VLOOKUP(A22,Medições!$E$3:$Y$95,7,FALSE) -> 11/2025 | I22: =VLOOKUP(A22,Medições!$E$3:$Y$95,18,FALSE) -> 1626.75 | J22: 45989 | K22: =VLOOKUP(A22,Medições!$E$3:$Y$95,3,FALSE) -> 3023594470 | L22: =VLOOKUP(Faturas!$A22,Medições!$E$3:$Y$86,2,FALSE) -> Usina 2 | M22: =VLOOKUP(Faturas!$A22,Medições!$E$3:$Z$103,11,FALSE) -> 1864.73 | N22: =VLOOKUP(Faturas!$A22,Medições!$E$3:$BA$97,24,FALSE) -> 0 | AO22: Correção Monetária | AQ22: 5.71 | AR22: =AQ22 -> 5.71 | AU22: =AO23 -> Juros | AV22: =AQ23 -> 12.09
A23: 19 | B23: =VLOOKUP(A23,Medições!$E$3:$Y$89,4,FALSE) -> 3.7 | C23: =VLOOKUP(B23,Cad.RateioConsumo!$B$3:$Q$55,14,FALSE) -> Fatima Abdel Hafiz Khalifa Cavalcanti | D23: =IF(VLOOKUP(B23,Cad.RateioConsumo!$B$3:$Q$35,3,FALSE)="PF","CPF","CNPJ") -> CNPJ | E23: =VLOOKUP(B23,Cad.RateioConsumo!$B$3:$Q$35,4,FALSE) -> 840.670.553-15 | F23: =VLOOKUP(B23,Cad.RateioConsumo!$B$3:$Q$35,5,FALSE) -> 38398091 | G23: =VLOOKUP(B23,Cad.RateioConsumo!$B$3:$Q$35,13,FALSE) -> Rua Nova nº63, Anil, São Luis, MA CEP: 65046-160 | H23: =VLOOKUP(A23,Medições!$E$3:$Y$95,7,FALSE) -> 12/2025 | I23: =VLOOKUP(A23,Medições!$E$3:$Y$95,18,FALSE) -> 1087.34 | J23: =VLOOKUP(Faturas!$B23&Faturas!$H23,Hist.Consum!$B$5:$V$119,11,FALSE) -> 45663 | K23: =VLOOKUP(A23,Medições!$E$3:$Y$95,3,FALSE) -> 3023637013 | L23: =VLOOKUP(Faturas!$A23,Medições!$E$3:$Y$86,2,FALSE) -> Usina 3 | M23: =VLOOKUP(Faturas!$A23,Medições!$E$3:$Z$103,11,FALSE) -> 1137.26 | N23: =VLOOKUP(Faturas!$A23,Medições!$E$3:$BA$97,24,FALSE) -> 1108.57 | Z23: Demonstrativo de Tarifas | AO23: Juros | AQ23: 12.09 | AR23: =AQ23 -> 12.09 | AU23: Cobrança Errada | AV23: =-SUM(X20:X23) -> 0
A24: 20 | B24: =VLOOKUP(A24,Medições!$E$3:$Y$89,4,FALSE) -> 3.6 | C24: =VLOOKUP(B24,Cad.RateioConsumo!$B$3:$Q$55,14,FALSE) -> Patricia Maria Abreu Machado | D24: =IF(VLOOKUP(B24,Cad.RateioConsumo!$B$3:$Q$35,3,FALSE)="PF","CPF","CNPJ") -> CNPJ | E24: =VLOOKUP(B24,Cad.RateioConsumo!$B$3:$Q$35,4,FALSE) -> 676.211.553-53 | F24: =VLOOKUP(B24,Cad.RateioConsumo!$B$3:$Q$35,5,FALSE) -> 3006793931 | G24: =VLOOKUP(B24,Cad.RateioConsumo!$B$3:$Q$35,13,FALSE) -> R. MARIA F REIS , 20 , QD B CONJ BASA QD B CONJ BASA CEP: 65010-000 SAO FRANCISCO, na cidade de São Luís, Estado do Maranhão | H24: =VLOOKUP(A24,Medições!$E$3:$Y$95,7,FALSE) -> 12/2025 | I24: =VLOOKUP(A24,Medições!$E$3:$Y$95,18,FALSE) -> 864.9 | J24: =VLOOKUP(Faturas!$B24&Faturas!$H24,Hist.Consum!$B$5:$V$119,11,FALSE) -> 46029 | K24: =VLOOKUP(A24,Medições!$E$3:$Y$95,3,FALSE) -> 3023637013 | L24: =VLOOKUP(Faturas!$A24,Medições!$E$3:$Y$86,2,FALSE) -> Usina 3 | M24: =VLOOKUP(Faturas!$A24,Medições!$E$3:$Z$103,11,FALSE) -> 871.79 | N24: =VLOOKUP(Faturas!$A24,Medições!$E$3:$BA$97,24,FALSE) -> 881.43 | Z24: Tarifa Vigente | AA24: Alíquota Vigente | AC24: ICMS vigente | AD24: Tarifa Média Vigente | AV24: =SUM(AV18:AV23) -> 160.7
A25: 21 | B25: =VLOOKUP(A25,Medições!$E$3:$Y$89,4,FALSE) -> 3.5 | C25: =VLOOKUP(B25,Cad.RateioConsumo!$B$3:$Q$55,14,FALSE) -> João Carlos Pereira Dutra Filho | D25: =IF(VLOOKUP(B25,Cad.RateioConsumo!$B$3:$Q$35,3,FALSE)="PF","CPF","CNPJ") -> CNPJ | E25: =VLOOKUP(B25,Cad.RateioConsumo!$B$3:$Q$35,4,FALSE) -> 064837473-49 | F25: =VLOOKUP(B25,Cad.RateioConsumo!$B$3:$Q$35,5,FALSE) -> 1163310 | G25: =VLOOKUP(B25,Cad.RateioConsumo!$B$3:$Q$35,13,FALSE) -> R. 13 , 31 , QD 7 QD 7 CEP: 65010-000 PLN - VINHAIS II - SAO LUIS - MA | H25: =VLOOKUP(A25,Medições!$E$3:$Y$95,7,FALSE) -> 0 | I25: =VLOOKUP(A25,Medições!$E$3:$Y$95,18,FALSE) -> 0 | J25: =VLOOKUP(Faturas!$B25&Faturas!$H25,Hist.Consum!$B$5:$V$119,11,FALSE) -> #N/A | K25: =VLOOKUP(A25,Medições!$E$3:$Y$95,3,FALSE) -> 3023637013 | L25: =VLOOKUP(Faturas!$A25,Medições!$E$3:$Y$86,2,FALSE) -> Usina 3 | M25: =VLOOKUP(Faturas!$A25,Medições!$E$3:$Z$103,11,FALSE) -> 0 | N25: =VLOOKUP(Faturas!$A25,Medições!$E$3:$BA$97,24,FALSE) -> 0 | AA25: Pis | AB25: COFINS | AO25: Subtotal | AQ25: =SUM(AQ20:AQ23) -> 160.7 | AR25: =AQ25 -> 160.7
A26: 22 | B26: =VLOOKUP(A26,Medições!$E$3:$Y$89,4,FALSE) -> 3.4 | C26: =VLOOKUP(B26,Cad.RateioConsumo!$B$3:$Q$55,14,FALSE) -> Antonio Jose Souza Filho | D26: =IF(VLOOKUP(B26,Cad.RateioConsumo!$B$3:$Q$35,3,FALSE)="PF","CPF","CNPJ") -> CNPJ | E26: =VLOOKUP(B26,Cad.RateioConsumo!$B$3:$Q$35,4,FALSE) -> 682.957.583-49 | F26: =VLOOKUP(B26,Cad.RateioConsumo!$B$3:$Q$35,5,FALSE) -> 3007625048 | G26: =VLOOKUP(B26,Cad.RateioConsumo!$B$3:$Q$35,13,FALSE) -> R. 03 , 23 , LOT ALTO DO JAGUAREMA QD 05 LOT - ALTO DO JAGUAREMA QD 05 CEP: 65110-000 ARACAGY | H26: =VLOOKUP(A26,Medições!$E$3:$Y$95,7,FALSE) -> 12/2025 | I26: =VLOOKUP(A26,Medições!$E$3:$Y$95,18,FALSE) -> 448.43 | J26: =VLOOKUP(Faturas!$B26&Faturas!$H26,Hist.Consum!$B$5:$V$119,11,FALSE) -> 46015 | K26: =VLOOKUP(A26,Medições!$E$3:$Y$95,3,FALSE) -> 3023637013 | L26: =VLOOKUP(Faturas!$A26,Medições!$E$3:$Y$86,2,FALSE) -> Usina 3 | M26: =VLOOKUP(Faturas!$A26,Medições!$E$3:$Z$103,11,FALSE) -> 468.1 | N26: =VLOOKUP(Faturas!$A26,Medições!$E$3:$BA$97,24,FALSE) -> 1430.65 | O26: OK | V26: Valor total: | X26: =SUM(X18:X25) -> 683.99 | Z26: A | AA26: B | AB26: C | AC26: D | AD26: E=A/((1-B-B)*(1-D)) | AV26: =AV16+AV24 -> 245.70024
A27: 23 | B27: =VLOOKUP(A27,Medições!$E$3:$Y$89,4,FALSE) -> 3.3 | C27: =VLOOKUP(B27,Cad.RateioConsumo!$B$3:$Q$55,14,FALSE) -> Associação dos Moradores do Residencial Araçagy | D27: =IF(VLOOKUP(B27,Cad.RateioConsumo!$B$3:$Q$35,3,FALSE)="PF","CPF","CNPJ") -> CNPJ | E27: =VLOOKUP(B27,Cad.RateioConsumo!$B$3:$Q$35,4,FALSE) -> 20.069.500/0001-97 | F27: =VLOOKUP(B27,Cad.RateioConsumo!$B$3:$Q$35,5,FALSE) -> 3021150559 | G27: =VLOOKUP(B27,Cad.RateioConsumo!$B$3:$Q$35,13,FALSE) -> R. Granja , s/n , CP 26 CS 36 PS 1, cep: 65138-000 Aracagi - Raposa - MA, | H27: =VLOOKUP(A27,Medições!$E$3:$Y$95,7,FALSE) -> 12/2025 | I27: =VLOOKUP(A27,Medições!$E$3:$Y$95,18,FALSE) -> 1669.03 | J27: =VLOOKUP(Faturas!$B27&Faturas!$H27,Hist.Consum!$B$5:$V$119,11,FALSE) -> 46015 | K27: =VLOOKUP(A27,Medições!$E$3:$Y$95,3,FALSE) -> 3023637013 | L27: =VLOOKUP(Faturas!$A27,Medições!$E$3:$Y$86,2,FALSE) -> Usina 3 | M27: =VLOOKUP(Faturas!$A27,Medições!$E$3:$Z$103,11,FALSE) -> 1680.76 | N27: =VLOOKUP(Faturas!$A27,Medições!$E$3:$BA$97,24,FALSE) -> 6568.29 | O27: OK | V27: Outras retenções: | Z27: R$/kWh | AA27: % | AB27: % | AC27: % | AD27: R$/kWh | AO27: TOTAL COM ENERGIA | AQ27: =AQ17+AQ25 -> 260.7 | AR27: =AR17+AR25 -> 245.70024
A28: 24 | B28: =VLOOKUP(A28,Medições!$E$3:$Y$89,4,FALSE) -> 3.2 | C28: =VLOOKUP(B28,Cad.RateioConsumo!$B$3:$Q$55,14,FALSE) -> Associação dos Moradores do Residencial Araçagy | D28: =IF(VLOOKUP(B28,Cad.RateioConsumo!$B$3:$Q$35,3,FALSE)="PF","CPF","CNPJ") -> CNPJ | E28: =VLOOKUP(B28,Cad.RateioConsumo!$B$3:$Q$35,4,FALSE) -> 20.069.500/0001-97 | F28: =VLOOKUP(B28,Cad.RateioConsumo!$B$3:$Q$35,5,FALSE) -> 3021149593 | G28: =VLOOKUP(B28,Cad.RateioConsumo!$B$3:$Q$35,13,FALSE) -> R. da Agranja , 50 , CP 26 CS 36 PS 4, cep: 65138-000 Aracagi - Raposa - MA | H28: =VLOOKUP(A28,Medições!$E$3:$Y$95,7,FALSE) -> 12/2025 | I28: =VLOOKUP(A28,Medições!$E$3:$Y$95,18,FALSE) -> 818.16 | J28: =VLOOKUP(Faturas!$B28&Faturas!$H28,Hist.Consum!$B$5:$V$119,11,FALSE) -> 46015 | K28: =VLOOKUP(A28,Medições!$E$3:$Y$95,3,FALSE) -> 3023637013 | L28: =VLOOKUP(Faturas!$A28,Medições!$E$3:$Y$86,2,FALSE) -> Usina 3 | M28: =VLOOKUP(Faturas!$A28,Medições!$E$3:$Z$103,11,FALSE) -> 824.67 | N28: =VLOOKUP(Faturas!$A28,Medições!$E$3:$BA$97,24,FALSE) -> 2548.79 | O28: OK | V28: Valor a pagar: | X28: =X26+X27 -> 683.99 | Z28: =AI32 -> 0.84318 | AA28: =VLOOKUP($AH$9,Hist.Consum!$B$4:$V$240,20,FALSE) -> 0.005288 | AB28: =VLOOKUP($AH$9,Hist.Consum!$B$4:$V$140,21,FALSE) -> 0.02441 | AC28: =VLOOKUP($AH$9,Hist.Consum!$B$4:$V$140,19,FALSE) -> 0.23 | AD28: =ROUND(Z28/((1-AA28-AB28)*(1-AC28)),4) -> 1.1286
